Workbook

Sheet Daily Sales
A2: DAILY SALES - FEBRUARI 2026
A4: Date | B4: Time | D4: Cust | E4: Code | F4: S | G4: P | H4: Item Descriptions | I4: Qty | J4: Price | K4: Discount | L4: Total | M4: Cogs | N4: Margin | O4: Payment | P4: Margin%
A5: 01/02/26 | B5: 10:29:00 | D5: 1 | E5: PK5043 | F5: =A5&E5 -> 01/02/26PK5043 | G5: =O5&A5 -> C01/02/26 | H5: =IFNA(VLOOKUP(TRIM(E5),Master!D:M,4,0),"") -> PUPUK KAMBING 5KG | I5: 1 | J5: =IFNA(VLOOKUP(E5,Master!D:U,14,0),0) -> 15000 | K5: 0 | L5: =J5*I5-K5 -> 15000 | M5: =IFNA(VLOOKUP(TRIM(E5),Master!D:U,13,0),"") -> 8000 | N5: =L5-(M5*I5) -> 7000 | O5: C | P5: =IFERROR((J5-M5)/J5*100,0) -> 46.666667
A6: 01/02/26 | E6: PL3182 | F6: =A6&E6 -> 01/02/26PL3182 | G6: =O6&A6 -> C01/02/26 | H6: =IFNA(VLOOKUP(TRIM(E6),Master!D:M,4,0),"") -> POT MOTIF BUNGA HITAM 25 | I6: 1 | J6: =IFNA(VLOOKUP(E6,Master!D:U,14,0),0) -> 7000 | K6: 0 | L6: =J6*I6-K6 -> 7000 | M6: =IFNA(VLOOKUP(TRIM(E6),Master!D:U,13,0),"") -> 5250 | N6: =L6-(M6*I6) -> 1750 | O6: C | P6: =IFERROR((J6-M6)/J6*100,0) -> 25
A7: 01/02/26 | B7: 11:00:00 | D7: 1 | E7: MT2037 | F7: =A7&E7 -> 01/02/26MT2037 | G7: =O7&A7 -> I01/02/26 | H7: =IFNA(VLOOKUP(TRIM(E7),Master!D:M,4,0),"") -> PUPUK KOMPOS 5KG | I7: 1 | J7: =IFNA(VLOOKUP(E7,Master!D:U,14,0),0) -> 10000 | K7: 0 | L7: =J7*I7-K7 -> 10000 | M7: =IFNA(VLOOKUP(TRIM(E7),Master!D:U,13,0),"") -> 5000 | N7: =L7-(M7*I7) -> 5000 | O7: I | P7: =IFERROR((J7-M7)/J7*100,0) -> 50
A8: 01/02/26 | B8: 11:53:00 | D8: 1 | E8: PL3182 | F8: =A8&E8 -> 01/02/26PL3182 | G8: =O8&A8 -> C01/02/26 | H8: =IFNA(VLOOKUP(TRIM(E8),Master!D:M,4,0),"") -> POT MOTIF BUNGA HITAM 25 | I8: 2 | J8: =IFNA(VLOOKUP(E8,Master!D:U,14,0),0) -> 7000 | K8: 0 | L8: =J8*I8-K8 -> 14000 | M8: =IFNA(VLOOKUP(TRIM(E8),Master!D:U,13,0),"") -> 5250 | N8: =L8-(M8*I8) -> 3500 | O8: C | P8: =IFERROR((J8-M8)/J8*100,0) -> 25
A9: 01/02/26 | B9: 11:53:00 | D9: 1 | E9: PK5041 | F9: =A9&E9 -> 01/02/26PK5041 | G9: =O9&A9 -> C01/02/26 | H9: =IFNA(VLOOKUP(TRIM(E9),Master!D:M,4,0),"") -> PUPUK BOOSTER 76 250ML | I9: 1 | J9: =IFNA(VLOOKUP(E9,Master!D:U,14,0),0) -> 45000 | K9: 0 | L9: =J9*I9-K9 -> 45000 | M9: =IFNA(VLOOKUP(TRIM(E9),Master!D:U,13,0),"") -> 25000 | N9: =L9-(M9*I9) -> 20000 | O9: C | P9: =IFERROR((J9-M9)/J9*100,0) -> 44.444444
A10: 01/02/26 | B10: 12:07:00 | D10: 1 | E10: PK5069 | F10: =A10&E10 -> 01/02/26PK5069 | G10: =O10&A10 -> O01/02/26 | H10: =IFNA(VLOOKUP(TRIM(E10),Master!D:M,4,0),"") -> ROOTUP 100GR | I10: 1 | J10: =IFNA(VLOOKUP(E10,Master!D:U,14,0),0) -> 35000 | K10: 0 | L10: =J10*I10-K10 -> 35000 | M10: =IFNA(VLOOKUP(TRIM(E10),Master!D:U,13,0),"") -> 16200 | N10: =L10-(M10*I10) -> 18800 | O10: O | P10: =IFERROR((J10-M10)/J10*100,0) -> 53.714286
A11: 01/02/26 | E11: PL3028 | F11: =A11&E11 -> 01/02/26PL3028 | G11: =O11&A11 -> O01/02/26 | H11: =IFNA(VLOOKUP(TRIM(E11),Master!D:M,4,0),"") -> KAWAT BONSAI HITAM NO.2 ECERAN | I11: 5 | J11: =IFNA(VLOOKUP(E11,Master!D:U,14,0),0) -> 2000 | K11: 0 | L11: =J11*I11-K11 -> 10000 | M11: =IFNA(VLOOKUP(TRIM(E11),Master!D:U,13,0),"") -> 1220 | N11: =L11-(M11*I11) -> 3900 | O11: O | P11: =IFERROR((J11-M11)/J11*100,0) -> 39
A12: 01/02/26 | E12: PL3115 | F12: =A12&E12 -> 01/02/26PL3115 | G12: =O12&A12 -> O01/02/26 | H12: =IFNA(VLOOKUP(TRIM(E12),Master!D:M,4,0),"") -> POLYBAG 40 | I12: 5 | J12: =IFNA(VLOOKUP(E12,Master!D:U,14,0),0) -> 1000 | K12: 0 | L12: =J12*I12-K12 -> 5000 | M12: =IFNA(VLOOKUP(TRIM(E12),Master!D:U,13,0),"") -> 500 | N12: =L12-(M12*I12) -> 2500 | O12: O | P12: =IFERROR((J12-M12)/J12*100,0) -> 50
A13: 01/02/26 | E13: PL3117 | F13: =A13&E13 -> 01/02/26PL3117 | G13: =O13&A13 -> O01/02/26 | H13: =IFNA(VLOOKUP(TRIM(E13),Master!D:M,4,0),"") -> POLYBAG 50 | I13: 5 | J13: =IFNA(VLOOKUP(E13,Master!D:U,14,0),0) -> 2000 | K13: 0 | L13: =J13*I13-K13 -> 10000 | M13: =IFNA(VLOOKUP(TRIM(E13),Master!D:U,13,0),"") -> 1316 | N13: =L13-(M13*I13) -> 3420 | O13: O | P13: =IFERROR((J13-M13)/J13*100,0) -> 34.2
A14: 01/02/26 | B14: 12:24:00 | D14: 1 | E14: PL3040 | F14: =A14&E14 -> 01/02/26PL3040 | G14: =O14&A14 -> C01/02/26 | H14: =IFNA(VLOOKUP(TRIM(E14),Master!D:M,4,0),"") -> KAWAT BONSAI SILVER NO.1.5 ECERAN | I14: 20 | J14: =IFNA(VLOOKUP(E14,Master!D:U,14,0),0) -> 750 | K14: 0 | L14: =J14*I14-K14 -> 15000 | M14: =IFNA(VLOOKUP(TRIM(E14),Master!D:U,13,0),"") -> 444 | N14: =L14-(M14*I14) -> 6120 | O14: C | P14: =IFERROR((J14-M14)/J14*100,0) -> 40.8
A15: 01/02/26 | B15: 12:24:00 | D15: 1 | E15: MT2053 | F15: =A15&E15 -> 01/02/26MT2053 | G15: =O15&A15 -> C01/02/26 | H15: =IFNA(VLOOKUP(TRIM(E15),Master!D:M,4,0),"") -> TANAH SUBUR 25KG BINTANG TANI | I15: 1 | J15: =IFNA(VLOOKUP(E15,Master!D:U,14,0),0) -> 25000 | K15: 0 | L15: =J15*I15-K15 -> 25000 | M15: =IFNA(VLOOKUP(TRIM(E15),Master!D:U,13,0),"") -> 15000 | N15: =L15-(M15*I15) -> 10000 | O15: C | P15: =IFERROR((J15-M15)/J15*100,0) -> 40
A16: 01/02/26 | E16: PL3113 | F16: =A16&E16 -> 01/02/26PL3113 | G16: =O16&A16 -> C01/02/26 | H16: =IFNA(VLOOKUP(TRIM(E16),Master!D:M,4,0),"") -> POLYBAG 30 | I16: 1 | J16: =IFNA(VLOOKUP(E16,Master!D:U,14,0),0) -> 5000 | K16: 0 | L16: =J16*I16-K16 -> 5000 | M16: =IFNA(VLOOKUP(TRIM(E16),Master!D:U,13,0),"") -> 3500 | N16: =L16-(M16*I16) -> 1500 | O16: C | P16: =IFERROR((J16-M16)/J16*100,0) -> 30
A17: 01/02/26 | B17: 12:48:00 | D17: 1 | E17: MT2050 | F17: =A17&E17 -> 01/02/26MT2050 | G17: =O17&A17 -> C01/02/26 | H17: =IFNA(VLOOKUP(TRIM(E17),Master!D:M,4,0),"") -> TANAH SUBUR 10KG BINTANG TANI | I17: 1 | J17: =IFNA(VLOOKUP(E17,Master!D:U,14,0),0) -> 10000 | K17: 0 | L17: =J17*I17-K17 -> 10000 | M17: =IFNA(VLOOKUP(TRIM(E17),Master!D:U,13,0),"") -> 6000 | N17: =L17-(M17*I17) -> 4000 | O17: C | P17: =IFERROR((J17-M17)/J17*100,0) -> 40
A18: 01/02/26 | B18: 13:32:00 | D18: 1 | E18: MT2053 | F18: =A18&E18 -> 01/02/26MT2053 | G18: =O18&A18 -> C01/02/26 | H18: =IFNA(VLOOKUP(TRIM(E18),Master!D:M,4,0),"") -> TANAH SUBUR 25KG BINTANG TANI | I18: 1 | J18: =IFNA(VLOOKUP(E18,Master!D:U,14,0),0) -> 25000 | K18: 0 | L18: =J18*I18-K18 -> 25000 | M18: =IFNA(VLOOKUP(TRIM(E18),Master!D:U,13,0),"") -> 15000 | N18: =L18-(M18*I18) -> 10000 | O18: C | P18: =IFERROR((J18-M18)/J18*100,0) -> 40
A19: 01/02/26 | E19: PL3066 | F19: =A19&E19 -> 01/02/26PL3066 | G19: =O19&A19 -> C01/02/26 | H19: =IFNA(VLOOKUP(TRIM(E19),Master!D:M,4,0),"") -> BIBIT BINTANG ASIA | I19: 1 | J19: =IFNA(VLOOKUP(E19,Master!D:U,14,0),0) -> 15000 | K19: 0 | L19: =J19*I19-K19 -> 15000 | M19: =IFNA(VLOOKUP(TRIM(E19),Master!D:U,13,0),"") -> 12500 | N19: =L19-(M19*I19) -> 2500 | O19: C | P19: =IFERROR((J19-M19)/J19*100,0) -> 16.666667
A20: 01/02/26 | E20: PL3068 | F20: =A20&E20 -> 01/02/26PL3068 | G20: =O20&A20 -> C01/02/26 | H20: =IFNA(VLOOKUP(TRIM(E20),Master!D:M,4,0),"") -> BIBIT PUTIH | I20: 2 | J20: =IFNA(VLOOKUP(E20,Master!D:U,14,0),0) -> 5000 | K20: 0 | L20: =J20*I20-K20 -> 10000 | M20: =IFNA(VLOOKUP(TRIM(E20),Master!D:U,13,0),"") -> 2000 | N20: =L20-(M20*I20) -> 6000 | O20: C | P20: =IFERROR((J20-M20)/J20*100,0) -> 60
A21: 01/02/26 | B21: 14:15:00 | D21: 1 | E21: PL3042 | F21: =A21&E21 -> 01/02/26PL3042 | G21: =O21&A21 -> O01/02/26 | H21: =IFNA(VLOOKUP(TRIM(E21),Master!D:M,4,0),"") -> KAWAT BONSAI SILVER NO.2 ECERAN | I21: 2 | J21: =IFNA(VLOOKUP(E21,Master!D:U,14,0),0) -> 1500 | K21: 0 | L21: =J21*I21-K21 -> 3000 | M21: =IFNA(VLOOKUP(TRIM(E21),Master!D:U,13,0),"") -> 800 | N21: =L21-(M21*I21) -> 1400 | O21: O | P21: =IFERROR((J21-M21)/J21*100,0) -> 46.666667
A22: 01/02/26 | E22: PL3044 | F22: =A22&E22 -> 01/02/26PL3044 | G22: =O22&A22 -> O01/02/26 | H22: =IFNA(VLOOKUP(TRIM(E22),Master!D:M,4,0),"") -> KAWAT BONSAI SILVER NO.2.5 ECERAN | I22: 4 | J22: =IFNA(VLOOKUP(E22,Master!D:U,14,0),0) -> 2000 | K22: 0 | L22: =J22*I22-K22 -> 8000 | M22: =IFNA(VLOOKUP(TRIM(E22),Master!D:U,13,0),"") -> 1143 | N22: =L22-(M22*I22) -> 3428 | O22: O | P22: =IFERROR((J22-M22)/J22*100,0) -> 42.85
A23: 01/02/26 | B23: 15:49:00 | D23: 1 | E23: MT2008 | F23: =A23&E23 -> 01/02/26MT2008 | G23: =O23&A23 -> C01/02/26 | H23: =IFNA(VLOOKUP(TRIM(E23),Master!D:M,4,0),"") -> COCOPEAT NON FERMENTASI 10KG | I23: 1 | J23: =IFNA(VLOOKUP(E23,Master!D:U,14,0),0) -> 10000 | K23: -5000 | L23: =J23*I23-K23 -> 15000 | M23: =IFNA(VLOOKUP(TRIM(E23),Master!D:U,13,0),"") -> 6000 | N23: =L23-(M23*I23) -> 9000 | O23: C | P23: =IFERROR((J23-M23)/J23*100,0) -> 40
A24: 01/02/26 | B24: 15:49:00 | D24: 1 | E24: MT2008 | F24: =A24&E24 -> 01/02/26MT2008 | G24: =O24&A24 -> C01/02/26 | H24: =IFNA(VLOOKUP(TRIM(E24),Master!D:M,4,0),"") -> COCOPEAT NON FERMENTASI 10KG | I24: 1 | J24: =IFNA(VLOOKUP(E24,Master!D:U,14,0),0) -> 10000 | K24: -5000 | L24: =J24*I24-K24 -> 15000 | M24: =IFNA(VLOOKUP(TRIM(E24),Master!D:U,13,0),"") -> 6000 | N24: =L24-(M24*I24) -> 9000 | O24: C | P24: =IFERROR((J24-M24)/J24*100,0) -> 40
A25: 01/02/26 | E25: MT2044 | F25: =A25&E25 -> 01/02/26MT2044 | G25: =O25&A25 -> C01/02/26 | H25: =IFNA(VLOOKUP(TRIM(E25),Master!D:M,4,0),"") -> SEKAM MENTAH 10KG | I25: 1 | J25: =IFNA(VLOOKUP(E25,Master!D:U,14,0),0) -> 10000 | K25: 0 | L25: =J25*I25-K25 -> 10000 | M25: =IFNA(VLOOKUP(TRIM(E25),Master!D:U,13,0),"") -> 6000 | N25: =L25-(M25*I25) -> 4000 | O25: C | P25: =IFERROR((J25-M25)/J25*100,0) -> 40
A26: 01/02/26 | B26: 16:56:00 | D26: 1 | E26: PL3040 | F26: =A26&E26 -> 01/02/26PL3040 | G26: =O26&A26 -> O01/02/26 | H26: =IFNA(VLOOKUP(TRIM(E26),Master!D:M,4,0),"") -> KAWAT BONSAI SILVER NO.1.5 ECERAN | I26: 12 | J26: =IFNA(VLOOKUP(E26,Master!D:U,14,0),0) -> 750 | K26: 0 | L26: =J26*I26-K26 -> 9000 | M26: =IFNA(VLOOKUP(TRIM(E26),Master!D:U,13,0),"") -> 444 | N26: =L26-(M26*I26) -> 3672 | O26: O | P26: =IFERROR((J26-M26)/J26*100,0) -> 40.8
A27: 01/02/26 | B27: 17:35:00 | D27: 1 | E27: MT2053 | F27: =A27&E27 -> 01/02/26MT2053 | G27: =O27&A27 -> C01/02/26 | H27: =IFNA(VLOOKUP(TRIM(E27),Master!D:M,4,0),"") -> TANAH SUBUR 25KG BINTANG TANI | I27: 2 | J27: =IFNA(VLOOKUP(E27,Master!D:U,14,0),0) -> 25000 | K27: 0 | L27: =J27*I27-K27 -> 50000 | M27: =IFNA(VLOOKUP(TRIM(E27),Master!D:U,13,0),"") -> 15000 | N27: =L27-(M27*I27) -> 20000 | O27: C | P27: =IFERROR((J27-M27)/J27*100,0) -> 40
A28: 02/02/26 | B28: 08:34:00 | D28: 1 | E28: PK5011 | F28: =A28&E28 -> 02/02/26PK5011 | G28: =O28&A28 -> O02/02/26 | H28: =IFNA(VLOOKUP(TRIM(E28),Master!D:M,4,0),"") -> DEKASTAR 131313 KTK 500GR | I28: 1 | J28: =IFNA(VLOOKUP(E28,Master!D:U,14,0),0) -> 95000 | K28: 0 | L28: =J28*I28-K28 -> 95000 | M28: =IFNA(VLOOKUP(TRIM(E28),Master!D:U,13,0),"") -> 74000 | N28: =L28-(M28*I28) -> 21000 | O28: O | P28: =IFERROR((J28-M28)/J28*100,0) -> 22.105263
A29: 02/02/26 | B29: 10:00:00 | D29: 1 | E29: PL3089 | F29: =A29&E29 -> 02/02/26PL3089 | G29: =O29&A29 -> I02/02/26 | H29: =IFNA(VLOOKUP(TRIM(E29),Master!D:M,4,0),"") -> SPRAYER 1LITER | I29: 1 | J29: =IFNA(VLOOKUP(E29,Master!D:U,14,0),0) -> 35000 | K29: 0 | L29: =J29*I29-K29 -> 35000 | M29: =IFNA(VLOOKUP(TRIM(E29),Master!D:U,13,0),"") -> 29000 | N29: =L29-(M29*I29) -> 6000 | O29: I | P29: =IFERROR((J29-M29)/J29*100,0) -> 17.142857
A30: 02/02/26 | B30: 10:00:00 | D30: 1 | E30: PL3090 | F30: =A30&E30 -> 02/02/26PL3090 | G30: =O30&A30 -> I02/02/26 | H30: =IFNA(VLOOKUP(TRIM(E30),Master!D:M,4,0),"") -> SPRAYER 2LITER | I30: 1 | J30: =IFNA(VLOOKUP(E30,Master!D:U,14,0),0) -> 43000 | K30: 0 | L30: =J30*I30-K30 -> 43000 | M30: =IFNA(VLOOKUP(TRIM(E30),Master!D:U,13,0),"") -> 33000 | N30: =L30-(M30*I30) -> 10000 | O30: I | P30: =IFERROR((J30-M30)/J30*100,0) -> 23.255814
A31: 02/02/26 | B31: 10:24:00 | D31: 1 | E31: PK5064 | F31: =A31&E31 -> 02/02/26PK5064 | G31: =O31&A31 -> C02/02/26 | H31: =IFNA(VLOOKUP(TRIM(E31),Master!D:M,4,0),"") -> PUPUK UREA 1KG | I31: 1 | J31: =IFNA(VLOOKUP(E31,Master!D:U,14,0),0) -> 14000 | K31: 0 | L31: =J31*I31-K31 -> 14000 | M31: =IFNA(VLOOKUP(TRIM(E31),Master!D:U,13,0),"") -> 10000 | N31: =L31-(M31*I31) -> 4000 | O31: C | P31: =IFERROR((J31-M31)/J31*100,0) -> 28.571429
A32: 02/02/26 | B32: 12:54:00 | D32: 1 | E32: PL3042 | F32: =A32&E32 -> 02/02/26PL3042 | G32: =O32&A32 -> O02/02/26 | H32: =IFNA(VLOOKUP(TRIM(E32),Master!D:M,4,0),"") -> KAWAT BONSAI SILVER NO.2 ECERAN | I32: 5 | J32: =IFNA(VLOOKUP(E32,Master!D:U,14,0),0) -> 1500 | K32: 0 | L32: =J32*I32-K32 -> 7500 | M32: =IFNA(VLOOKUP(TRIM(E32),Master!D:U,13,0),"") -> 800 | N32: =L32-(M32*I32) -> 3500 | O32: O | P32: =IFERROR((J32-M32)/J32*100,0) -> 46.666667
A33: 02/02/26 | E33: MT2041 | F33: =A33&E33 -> 02/02/26MT2041 | G33: =O33&A33 -> O02/02/26 | H33: =IFNA(VLOOKUP(TRIM(E33),Master!D:M,4,0),"") -> SEKAM BAKAR 5KG | I33: 1 | J33: =IFNA(VLOOKUP(E33,Master!D:U,14,0),0) -> 8000 | K33: 0 | L33: =J33*I33-K33 -> 8000 | M33: =IFNA(VLOOKUP(TRIM(E33),Master!D:U,13,0),"") -> 3400 | N33: =L33-(M33*I33) -> 4600 | O33: O | P33: =IFERROR((J33-M33)/J33*100,0) -> 57.5
A34: 02/02/26 | E34: PK5068 | F34: =A34&E34 -> 02/02/26PK5068 | G34: =O34&A34 -> O02/02/26 | H34: =IFNA(VLOOKUP(TRIM(E34),Master!D:M,4,0),"") -> PUPUK ZA 1KG | I34: 1 | J34: =IFNA(VLOOKUP(E34,Master!D:U,14,0),0) -> 9000 | K34: 0 | L34: =J34*I34-K34 -> 9000 | M34: =IFNA(VLOOKUP(TRIM(E34),Master!D:U,13,0),"") -> 6000 | N34: =L34-(M34*I34) -> 3000 | O34: O | P34: =IFERROR((J34-M34)/J34*100,0) -> 33.333333
A35: 02/02/26 | E35: PK5066 | F35: =A35&E35 -> 02/02/26PK5066 | G35: =O35&A35 -> O02/02/26 | H35: =IFNA(VLOOKUP(TRIM(E35),Master!D:M,4,0),"") -> PUPUK XPK 1KG | I35: 1 | J35: =IFNA(VLOOKUP(E35,Master!D:U,14,0),0) -> 90000 | K35: 0 | L35: =J35*I35-K35 -> 90000 | M35: =IFNA(VLOOKUP(TRIM(E35),Master!D:U,13,0),"") -> 75000 | N35: =L35-(M35*I35) -> 15000 | O35: O | P35: =IFERROR((J35-M35)/J35*100,0) -> 16.666667
A36: 02/02/26 | B36: 16:08:00 | D36: 1 | E36: MT2050 | F36: =A36&E36 -> 02/02/26MT2050 | G36: =O36&A36 -> C02/02/26 | H36: =IFNA(VLOOKUP(TRIM(E36),Master!D:M,4,0),"") -> TANAH SUBUR 10KG BINTANG TANI | I36: 1 | J36: =IFNA(VLOOKUP(E36,Master!D:U,14,0),0) -> 10000 | K36: 0 | L36: =J36*I36-K36 -> 10000 | M36: =IFNA(VLOOKUP(TRIM(E36),Master!D:U,13,0),"") -> 6000 | N36: =L36-(M36*I36) -> 4000 | O36: C | P36: =IFERROR((J36-M36)/J36*100,0) -> 40
A37: 02/02/26 | E37: MT2044 | F37: =A37&E37 -> 02/02/26MT2044 | G37: =O37&A37 -> C02/02/26 | H37: =IFNA(VLOOKUP(TRIM(E37),Master!D:M,4,0),"") -> SEKAM MENTAH 10KG | I37: 1 | J37: =IFNA(VLOOKUP(E37,Master!D:U,14,0),0) -> 10000 | K37: 0 | L37: =J37*I37-K37 -> 10000 | M37: =IFNA(VLOOKUP(TRIM(E37),Master!D:U,13,0),"") -> 6000 | N37: =L37-(M37*I37) -> 4000 | O37: C | P37: =IFERROR((J37-M37)/J37*100,0) -> 40
A38: 02/02/26 | E38: PK5043 | F38: =A38&E38 -> 02/02/26PK5043 | G38: =O38&A38 -> C02/02/26 | H38: =IFNA(VLOOKUP(TRIM(E38),Master!D:M,4,0),"") -> PUPUK KAMBING 5KG | I38: 1 | J38: =IFNA(VLOOKUP(E38,Master!D:U,14,0),0) -> 15000 | K38: 0 | L38: =J38*I38-K38 -> 15000 | M38: =IFNA(VLOOKUP(TRIM(E38),Master!D:U,13,0),"") -> 8000 | N38: =L38-(M38*I38) -> 7000 | O38: C | P38: =IFERROR((J38-M38)/J38*100,0) -> 46.666667
A39: 02/02/26 | B39: 17:22:00 | D39: 1 | E39: PL3040 | F39: =A39&E39 -> 02/02/26PL3040 | G39: =O39&A39 -> O02/02/26 | H39: =IFNA(VLOOKUP(TRIM(E39),Master!D:M,4,0),"") -> KAWAT BONSAI SILVER NO.1.5 ECERAN | I39: 5 | J39: =IFNA(VLOOKUP(E39,Master!D:U,14,0),0) -> 750 | K39: 0 | L39: =J39*I39-K39 -> 3750 | M39: =IFNA(VLOOKUP(TRIM(E39),Master!D:U,13,0),"") -> 444 | N39: =L39-(M39*I39) -> 1530 | O39: O | P39: =IFERROR((J39-M39)/J39*100,0) -> 40.8
A40: 02/02/26 | B40: 18:40:00 | D40: 1 | E40: MT2050 | F40: =A40&E40 -> 02/02/26MT2050 | G40: =O40&A40 -> C02/02/26 | H40: =IFNA(VLOOKUP(TRIM(E40),Master!D:M,4,0),"") -> TANAH SUBUR 10KG BINTANG TANI | I40: 1 | J40: =IFNA(VLOOKUP(E40,Master!D:U,14,0),0) -> 10000 | K40: 0 | L40: =J40*I40-K40 -> 10000 | M40: =IFNA(VLOOKUP(TRIM(E40),Master!D:U,13,0),"") -> 6000 | N40: =L40-(M40*I40) -> 4000 | O40: C | P40: =IFERROR((J40-M40)/J40*100,0) -> 40
A41: 02/02/26 | B41: 18:40:00 | D41: 1 | E41: MT2053 | F41: =A41&E41 -> 02/02/26MT2053 | G41: =O41&A41 -> C02/02/26 | H41: =IFNA(VLOOKUP(TRIM(E41),Master!D:M,4,0),"") -> TANAH SUBUR 25KG BINTANG TANI | I41: 2 | J41: =IFNA(VLOOKUP(E41,Master!D:U,14,0),0) -> 25000 | K41: 0 | L41: =J41*I41-K41 -> 50000 | M41: =IFNA(VLOOKUP(TRIM(E41),Master!D:U,13,0),"") -> 15000 | N41: =L41-(M41*I41) -> 20000 | O41: C | P41: =IFERROR((J41-M41)/J41*100,0) -> 40
A42: 03/02/26 | B42: 10:38:00 | D42: 1 | E42: PL3040 | F42: =A42&E42 -> 03/02/26PL3040 | G42: =O42&A42 -> O03/02/26 | H42: =IFNA(VLOOKUP(TRIM(E42),Master!D:M,4,0),"") -> KAWAT BONSAI SILVER NO.1.5 ECERAN | I42: 12 | J42: =IFNA(VLOOKUP(E42,Master!D:U,14,0),0) -> 750 | K42: 0 | L42: =J42*I42-K42 -> 9000 | M42: =IFNA(VLOOKUP(TRIM(E42),Master!D:U,13,0),"") -> 444 | N42: =L42-(M42*I42) -> 3672 | O42: O | P42: =IFERROR((J42-M42)/J42*100,0) -> 40.8
A43: 03/02/26 | E43: PL3038 | F43: =A43&E43 -> 03/02/26PL3038 | G43: =O43&A43 -> O03/02/26 | H43: =IFNA(VLOOKUP(TRIM(E43),Master!D:M,4,0),"") -> KAWAT BONSAI SILVER NO.1 ECERAN | I43: 20 | J43: =IFNA(VLOOKUP(E43,Master!D:U,14,0),0) -> 500 | K43: 0 | L43: =J43*I43-K43 -> 10000 | M43: =IFNA(VLOOKUP(TRIM(E43),Master!D:U,13,0),"") -> 267 | N43: =L43-(M43*I43) -> 4660 | O43: O | P43: =IFERROR((J43-M43)/J43*100,0) -> 46.6
A44: 03/02/26 | E44: PL3040 | F44: =A44&E44 -> 03/02/26PL3040 | G44: =O44&A44 -> O03/02/26 | H44: =IFNA(VLOOKUP(TRIM(E44),Master!D:M,4,0),"") -> KAWAT BONSAI SILVER NO.1.5 ECERAN | I44: 10 | J44: =IFNA(VLOOKUP(E44,Master!D:U,14,0),0) -> 750 | K44: 0 | L44: =J44*I44-K44 -> 7500 | M44: =IFNA(VLOOKUP(TRIM(E44),Master!D:U,13,0),"") -> 444 | N44: =L44-(M44*I44) -> 3060 | O44: O | P44: =IFERROR((J44-M44)/J44*100,0) -> 40.8
A45: 03/02/26 | E45: MT2044 | F45: =A45&E45 -> 03/02/26MT2044 | G45: =O45&A45 -> O03/02/26 | H45: =IFNA(VLOOKUP(TRIM(E45),Master!D:M,4,0),"") -> SEKAM MENTAH 10KG | I45: 1 | J45: =IFNA(VLOOKUP(E45,Master!D:U,14,0),0) -> 10000 | K45: 0 | L45: =J45*I45-K45 -> 10000 | M45: =IFNA(VLOOKUP(TRIM(E45),Master!D:U,13,0),"") -> 6000 | N45: =L45-(M45*I45) -> 4000 | O45: O | P45: =IFERROR((J45-M45)/J45*100,0) -> 40
A46: 03/02/26 | E46: MT2041 | F46: =A46&E46 -> 03/02/26MT2041 | G46: =O46&A46 -> O03/02/26 | H46: =IFNA(VLOOKUP(TRIM(E46),Master!D:M,4,0),"") -> SEKAM BAKAR 5KG | I46: 2 | J46: =IFNA(VLOOKUP(E46,Master!D:U,14,0),0) -> 8000 | K46: 0 | L46: =J46*I46-K46 -> 16000 | M46: =IFNA(VLOOKUP(TRIM(E46),Master!D:U,13,0),"") -> 3400 | N46: =L46-(M46*I46) -> 9200 | O46: O | P46: =IFERROR((J46-M46)/J46*100,0) -> 57.5
A47: 03/02/26 | E47: MT2009 | F47: =A47&E47 -> 03/02/26MT2009 | G47: =O47&A47 -> O03/02/26 | H47: =IFNA(VLOOKUP(TRIM(E47),Master!D:M,4,0),"") -> COCOPEAT NON FERMENTASI 5KG | I47: 2 | J47: =IFNA(VLOOKUP(E47,Master!D:U,14,0),0) -> 5000 | K47: 0 | L47: =J47*I47-K47 -> 10000 | M47: =IFNA(VLOOKUP(TRIM(E47),Master!D:U,13,0),"") -> 3000 | N47: =L47-(M47*I47) -> 4000 | O47: O | P47: =IFERROR((J47-M47)/J47*100,0) -> 40
A48: 03/02/26 | B48: 10:40:00 | D48: 1 | E48: MT2018 | F48: =A48&E48 -> 03/02/26MT2018 | G48: =O48&A48 -> C03/02/26 | H48: =IFNA(VLOOKUP(TRIM(E48),Master!D:M,4,0),"") -> MOSS HITAM 5KG | I48: 1 | J48: =IFNA(VLOOKUP(E48,Master!D:U,14,0),0) -> 12000 | K48: 0 | L48: =J48*I48-K48 -> 12000 | M48: =IFNA(VLOOKUP(TRIM(E48),Master!D:U,13,0),"") -> 7500 | N48: =L48-(M48*I48) -> 4500 | O48: C | P48: =IFERROR((J48-M48)/J48*100,0) -> 37.5
A49: 03/02/26 | F49: =A49&E49 -> 03/02/26 | G49: =O49&A49 -> C03/02/26 | H49: KABEL TIS | I49: 1 | J49: 15000 | K49: 0 | L49: =J49*I49-K49 -> 15000 | M49: =IFNA(VLOOKUP(TRIM(E49),Master!D:U,13,0),"") | N49: =L49-(M49*I49) -> 15000 | O49: C | P49: =IFERROR((J49-M49)/J49*100,0) -> 100
A50: 03/02/26 | B50: 11:43:00 | D50: 1 | E50: MT2050 | F50: =A50&E50 -> 03/02/26MT2050 | G50: =O50&A50 -> C03/02/26 | H50: =IFNA(VLOOKUP(TRIM(E50),Master!D:M,4,0),"") -> TANAH SUBUR 10KG BINTANG TANI | I50: 2 | J50: =IFNA(VLOOKUP(E50,Master!D:U,14,0),0) -> 10000 | K50: 0 | L50: =J50*I50-K50 -> 20000 | M50: =IFNA(VLOOKUP(TRIM(E50),Master!D:U,13,0),"") -> 6000 | N50: =L50-(M50*I50) -> 8000 | O50: C | P50: =IFERROR((J50-M50)/J50*100,0) -> 40
A51: 03/02/26 | B51: 11:43:00 | D51: 1 | E51: MT2050 | F51: =A51&E51 -> 03/02/26MT2050 | G51: =O51&A51 -> C03/02/26 | H51: =IFNA(VLOOKUP(TRIM(E51),Master!D:M,4,0),"") -> TANAH SUBUR 10KG BINTANG TANI | I51: 2 | J51: =IFNA(VLOOKUP(E51,Master!D:U,14,0),0) -> 10000 | K51: 0 | L51: =J51*I51-K51 -> 20000 | M51: =IFNA(VLOOKUP(TRIM(E51),Master!D:U,13,0),"") -> 6000 | N51: =L51-(M51*I51) -> 8000 | O51: C | P51: =IFERROR((J51-M51)/J51*100,0) -> 40
A52: 03/02/26 | B52: 12:12:00 | D52: 1 | E52: MT2041 | F52: =A52&E52 -> 03/02/26MT2041 | G52: =O52&A52 -> O03/02/26 | H52: =IFNA(VLOOKUP(TRIM(E52),Master!D:M,4,0),"") -> SEKAM BAKAR 5KG | I52: 1 | J52: =IFNA(VLOOKUP(E52,Master!D:U,14,0),0) -> 8000 | K52: 0 | L52: =J52*I52-K52 -> 8000 | M52: =IFNA(VLOOKUP(TRIM(E52),Master!D:U,13,0),"") -> 3400 | N52: =L52-(M52*I52) -> 4600 | O52: O | P52: =IFERROR((J52-M52)/J52*100,0) -> 57.5
A53: 03/02/26 | E53: PK5072 | F53: =A53&E53 -> 03/02/26PK5072 | G53: =O53&A53 -> O03/02/26 | H53: =IFNA(VLOOKUP(TRIM(E53),Master!D:M,4,0),"") -> VITAMIN B1 500ML | I53: 1 | J53: =IFNA(VLOOKUP(E53,Master!D:U,14,0),0) -> 50000 | K53: 0 | L53: =J53*I53-K53 -> 50000 | M53: =IFNA(VLOOKUP(TRIM(E53),Master!D:U,13,0),"") -> 25000 | N53: =L53-(M53*I53) -> 25000 | O53: O | P53: =IFERROR((J53-M53)/J53*100,0) -> 50
A54: 03/02/26 | E54: PL3026 | F54: =A54&E54 -> 03/02/26PL3026 | G54: =O54&A54 -> O03/02/26 | H54: =IFNA(VLOOKUP(TRIM(E54),Master!D:M,4,0),"") -> KAWAT BONSAI HITAM NO.1 ECERAN | I54: 10 | J54: =IFNA(VLOOKUP(E54,Master!D:U,14,0),0) -> 750 | K54: 0 | L54: =J54*I54-K54 -> 7500 | M54: =IFNA(VLOOKUP(TRIM(E54),Master!D:U,13,0),"") -> 407 | N54: =L54-(M54*I54) -> 3430 | O54: O | P54: =IFERROR((J54-M54)/J54*100,0) -> 45.733333
A55: 03/02/26 | B55: 14:59:00 | D55: 1 | E55: MT2050 | F55: =A55&E55 -> 03/02/26MT2050 | G55: =O55&A55 -> I03/02/26 | H55: =IFNA(VLOOKUP(TRIM(E55),Master!D:M,4,0),"") -> TANAH SUBUR 10KG BINTANG TANI | I55: 3 | J55: =IFNA(VLOOKUP(E55,Master!D:U,14,0),0) -> 10000 | K55: 0 | L55: =J55*I55-K55 -> 30000 | M55: =IFNA(VLOOKUP(TRIM(E55),Master!D:U,13,0),"") -> 6000 | N55: =L55-(M55*I55) -> 12000 | O55: I | P55: =IFERROR((J55-M55)/J55*100,0) -> 40
A56: 03/02/26 | B56: 15:08:00 | D56: 1 | E56: MT2050 | F56: =A56&E56 -> 03/02/26MT2050 | G56: =O56&A56 -> T03/02/26 | H56: =IFNA(VLOOKUP(TRIM(E56),Master!D:M,4,0),"") -> TANAH SUBUR 10KG BINTANG TANI | I56: 1 | J56: =IFNA(VLOOKUP(E56,Master!D:U,14,0),0) -> 10000 | K56: 0 | L56: =J56*I56-K56 -> 10000 | M56: =IFNA(VLOOKUP(TRIM(E56),Master!D:U,13,0),"") -> 6000 | N56: =L56-(M56*I56) -> 4000 | O56: T | P56: =IFERROR((J56-M56)/J56*100,0) -> 40
A57: 03/02/26 | E57: MT2037 | F57: =A57&E57 -> 03/02/26MT2037 | G57: =O57&A57 -> T03/02/26 | H57: =IFNA(VLOOKUP(TRIM(E57),Master!D:M,4,0),"") -> PUPUK KOMPOS 5KG | I57: 1 | J57: =IFNA(VLOOKUP(E57,Master!D:U,14,0),0) -> 10000 | K57: 0 | L57: =J57*I57-K57 -> 10000 | M57: =IFNA(VLOOKUP(TRIM(E57),Master!D:U,13,0),"") -> 5000 | N57: =L57-(M57*I57) -> 5000 | O57: T | P57: =IFERROR((J57-M57)/J57*100,0) -> 50
A58: 03/02/26 | E58: PK5043 | F58: =A58&E58 -> 03/02/26PK5043 | G58: =O58&A58 -> T03/02/26 | H58: =IFNA(VLOOKUP(TRIM(E58),Master!D:M,4,0),"") -> PUPUK KAMBING 5KG | I58: 1 | J58: =IFNA(VLOOKUP(E58,Master!D:U,14,0),0) -> 15000 | K58: 0 | L58: =J58*I58-K58 -> 15000 | M58: =IFNA(VLOOKUP(TRIM(E58),Master!D:U,13,0),"") -> 8000 | N58: =L58-(M58*I58) -> 7000 | O58: T | P58: =IFERROR((J58-M58)/J58*100,0) -> 46.666667
A59: 03/02/26 | E59: MT2003 | F59: =A59&E59 -> 03/02/26MT2003 | G59: =O59&A59 -> T03/02/26 | H59: =IFNA(VLOOKUP(TRIM(E59),Master!D:M,4,0),"") -> ARANG 5KG | I59: 1 | J59: =IFNA(VLOOKUP(E59,Master!D:U,14,0),0) -> 15000 | K59: 0 | L59: =J59*I59-K59 -> 15000 | M59: =IFNA(VLOOKUP(TRIM(E59),Master!D:U,13,0),"") -> 8000 | N59: =L59-(M59*I59) -> 7000 | O59: T | P59: =IFERROR((J59-M59)/J59*100,0) -> 46.666667
A60: 03/02/26 | B60: 15:47:00 | D60: 1 | E60: MT2050 | F60: =A60&E60 -> 03/02/26MT2050 | G60: =O60&A60 -> C03/02/26 | H60: =IFNA(VLOOKUP(TRIM(E60),Master!D:M,4,0),"") -> TANAH SUBUR 10KG BINTANG TANI | I60: 2 | J60: =IFNA(VLOOKUP(E60,Master!D:U,14,0),0) -> 10000 | K60: 0 | L60: =J60*I60-K60 -> 20000 | M60: =IFNA(VLOOKUP(TRIM(E60),Master!D:U,13,0),"") -> 6000 | N60: =L60-(M60*I60) -> 8000 | O60: C | P60: =IFERROR((J60-M60)/J60*100,0) -> 40
A61: 03/02/26 | B61: 15:47:00 | D61: 1 | E61: PK5043 | F61: =A61&E61 -> 03/02/26PK5043 | G61: =O61&A61 -> C03/02/26 | H61: =IFNA(VLOOKUP(TRIM(E61),Master!D:M,4,0),"") -> PUPUK KAMBING 5KG | I61: 1 | J61: =IFNA(VLOOKUP(E61,Master!D:U,14,0),0) -> 15000 | K61: 0 | L61: =J61*I61-K61 -> 15000 | M61: =IFNA(VLOOKUP(TRIM(E61),Master!D:U,13,0),"") -> 8000 | N61: =L61-(M61*I61) -> 7000 | O61: C | P61: =IFERROR((J61-M61)/J61*100,0) -> 46.666667
A62: 03/02/26 | B62: 17:20:00 | D62: 1 | E62: MT2041 | F62: =A62&E62 -> 03/02/26MT2041 | G62: =O62&A62 -> C03/02/26 | H62: =IFNA(VLOOKUP(TRIM(E62),Master!D:M,4,0),"") -> SEKAM BAKAR 5KG | I62: 1 | J62: =IFNA(VLOOKUP(E62,Master!D:U,14,0),0) -> 8000 | K62: 0 | L62: =J62*I62-K62 -> 8000 | M62: =IFNA(VLOOKUP(TRIM(E62),Master!D:U,13,0),"") -> 3400 | N62: =L62-(M62*I62) -> 4600 | O62: C | P62: =IFERROR((J62-M62)/J62*100,0) -> 57.5
A63: 03/02/26 | B63: 17:20:00 | D63: 1 | E63: MT2050 | F63: =A63&E63 -> 03/02/26MT2050 | G63: =O63&A63 -> C03/02/26 | H63: =IFNA(VLOOKUP(TRIM(E63),Master!D:M,4,0),"") -> TANAH SUBUR 10KG BINTANG TANI | I63: 1 | J63: =IFNA(VLOOKUP(E63,Master!D:U,14,0),0) -> 10000 | K63: 0 | L63: =J63*I63-K63 -> 10000 | M63: =IFNA(VLOOKUP(TRIM(E63),Master!D:U,13,0),"") -> 6000 | N63: =L63-(M63*I63) -> 4000 | O63: C | P63: =IFERROR((J63-M63)/J63*100,0) -> 40
A64: 03/02/26 | B64: 18:35:00 | D64: 1 | E64: PS4013 | F64: =A64&E64 -> 03/02/26PS4013 | G64: =O64&A64 -> I03/02/26 | H64: =IFNA(VLOOKUP(TRIM(E64),Master!D:M,4,0),"") -> ALIKA 50ML | I64: 1 | J64: =IFNA(VLOOKUP(E64,Master!D:U,14,0),0) -> 42000 | K64: 0 | L64: =J64*I64-K64 -> 42000 | M64: =IFNA(VLOOKUP(TRIM(E64),Master!D:U,13,0),"") -> 36000 | N64: =L64-(M64*I64) -> 6000 | O64: I | P64: =IFERROR((J64-M64)/J64*100,0) -> 14.285714
A65: 04/02/26 | B65: 08:15:00 | D65: 1 | E65: PS4009 | F65: =A65&E65 -> 04/02/26PS4009 | G65: =O65&A65 -> O04/02/26 | H65: =IFNA(VLOOKUP(TRIM(E65),Master!D:M,4,0),"") -> ROUNDUP 200ML | I65: 1 | J65: =IFNA(VLOOKUP(E65,Master!D:U,14,0),0) -> 35000 | K65: 0 | L65: =J65*I65-K65 -> 35000 | M65: =IFNA(VLOOKUP(TRIM(E65),Master!D:U,13,0),"") -> 23000 | N65: =L65-(M65*I65) -> 12000 | O65: O | P65: =IFERROR((J65-M65)/J65*100,0) -> 34.285714
A66: 04/02/26 | B66: 10:53:00 | D66: 1 | E66: MT2050 | F66: =A66&E66 -> 04/02/26MT2050 | G66: =O66&A66 -> I04/02/26 | H66: =IFNA(VLOOKUP(TRIM(E66),Master!D:M,4,0),"") -> TANAH SUBUR 10KG BINTANG TANI | I66: 1 | J66: =IFNA(VLOOKUP(E66,Master!D:U,14,0),0) -> 10000 | K66: 0 | L66: =J66*I66-K66 -> 10000 | M66: =IFNA(VLOOKUP(TRIM(E66),Master!D:U,13,0),"") -> 6000 | N66: =L66-(M66*I66) -> 4000 | O66: I | P66: =IFERROR((J66-M66)/J66*100,0) -> 40
A67: 04/02/26 | E67: PK5052 | F67: =A67&E67 -> 04/02/26PK5052 | G67: =O67&A67 -> I04/02/26 | H67: =IFNA(VLOOKUP(TRIM(E67),Master!D:M,4,0),"") -> PUPUK NPK 161616 PAK TANI | I67: 1 | J67: =IFNA(VLOOKUP(E67,Master!D:U,14,0),0) -> 25000 | K67: 0 | L67: =J67*I67-K67 -> 25000 | M67: =IFNA(VLOOKUP(TRIM(E67),Master!D:U,13,0),"") -> 17050 | N67: =L67-(M67*I67) -> 7950 | O67: I | P67: =IFERROR((J67-M67)/J67*100,0) -> 31.8
A68: 04/02/26 | B68: 11:14:00 | D68: 1 | E68: PL3079 | F68: =A68&E68 -> 04/02/26PL3079 | G68: =O68&A68 -> O04/02/26 | H68: =IFNA(VLOOKUP(TRIM(E68),Master!D:M,4,0),"") -> NAME TAG TANAMAN | I68: 10 | J68: =IFNA(VLOOKUP(E68,Master!D:U,14,0),0) -> 1000 | K68: 0 | L68: =J68*I68-K68 -> 10000 | M68: =IFNA(VLOOKUP(TRIM(E68),Master!D:U,13,0),"") -> 200 | N68: =L68-(M68*I68) -> 8000 | O68: O | P68: =IFERROR((J68-M68)/J68*100,0) -> 80
A69: 04/02/26 | E69: PL3038 | F69: =A69&E69 -> 04/02/26PL3038 | G69: =O69&A69 -> O04/02/26 | H69: =IFNA(VLOOKUP(TRIM(E69),Master!D:M,4,0),"") -> KAWAT BONSAI SILVER NO.1 ECERAN | I69: 10 | J69: =IFNA(VLOOKUP(E69,Master!D:U,14,0),0) -> 500 | K69: 0 | L69: =J69*I69-K69 -> 5000 | M69: =IFNA(VLOOKUP(TRIM(E69),Master!D:U,13,0),"") -> 267 | N69: =L69-(M69*I69) -> 2330 | O69: O | P69: =IFERROR((J69-M69)/J69*100,0) -> 46.6
A70: 04/02/26 | E70: PL3040 | F70: =A70&E70 -> 04/02/26PL3040 | G70: =O70&A70 -> O04/02/26 | H70: =IFNA(VLOOKUP(TRIM(E70),Master!D:M,4,0),"") -> KAWAT BONSAI SILVER NO.1.5 ECERAN | I70: 10 | J70: =IFNA(VLOOKUP(E70,Master!D:U,14,0),0) -> 750 | K70: 0 | L70: =J70*I70-K70 -> 7500 | M70: =IFNA(VLOOKUP(TRIM(E70),Master!D:U,13,0),"") -> 444 | N70: =L70-(M70*I70) -> 3060 | O70: O | P70: =IFERROR((J70-M70)/J70*100,0) -> 40.8
A71: 04/02/26 | E71: PK5067 | F71: =A71&E71 -> 04/02/26PK5067 | G71: =O71&A71 -> O04/02/26 | H71: =IFNA(VLOOKUP(TRIM(E71),Master!D:M,4,0),"") -> PUPUK XPK PCK 100GR | I71: 1 | J71: =IFNA(VLOOKUP(E71,Master!D:U,14,0),0) -> 15000 | K71: 0 | L71: =J71*I71-K71 -> 15000 | M71: =IFNA(VLOOKUP(TRIM(E71),Master!D:U,13,0),"") -> 7500 | N71: =L71-(M71*I71) -> 7500 | O71: O | P71: =IFERROR((J71-M71)/J71*100,0) -> 50
A72: 04/02/26 | E72: PK5048 | F72: =A72&E72 -> 04/02/26PK5048 | G72: =O72&A72 -> O04/02/26 | H72: =IFNA(VLOOKUP(TRIM(E72),Master!D:M,4,0),"") -> PUPUK MUTIARA 161616 100GR RPK | I72: 1 | J72: =IFNA(VLOOKUP(E72,Master!D:U,14,0),0) -> 3000 | K72: 0 | L72: =J72*I72-K72 -> 3000 | M72: =IFNA(VLOOKUP(TRIM(E72),Master!D:U,13,0),"") -> 1900 | N72: =L72-(M72*I72) -> 1100 | O72: O | P72: =IFERROR((J72-M72)/J72*100,0) -> 36.666667
A73: 04/02/26 | B73: 14:42:00 | D73: 1 | E73: PK5041 | F73: =A73&E73 -> 04/02/26PK5041 | G73: =O73&A73 -> C04/02/26 | H73: =IFNA(VLOOKUP(TRIM(E73),Master!D:M,4,0),"") -> PUPUK BOOSTER 76 250ML | I73: 1 | J73: =IFNA(VLOOKUP(E73,Master!D:U,14,0),0) -> 45000 | K73: 0 | L73: =J73*I73-K73 -> 45000 | M73: =IFNA(VLOOKUP(TRIM(E73),Master!D:U,13,0),"") -> 25000 | N73: =L73-(M73*I73) -> 20000 | O73: C | P73: =IFERROR((J73-M73)/J73*100,0) -> 44.444444
A74: 04/02/26 | B74: 15:47:00 | D74: 1 | E74: MT2050 | F74: =A74&E74 -> 04/02/26MT2050 | G74: =O74&A74 -> C04/02/26 | H74: =IFNA(VLOOKUP(TRIM(E74),Master!D:M,4,0),"") -> TANAH SUBUR 10KG BINTANG TANI | I74: 1 | J74: =IFNA(VLOOKUP(E74,Master!D:U,14,0),0) -> 10000 | K74: 0 | L74: =J74*I74-K74 -> 10000 | M74: =IFNA(VLOOKUP(TRIM(E74),Master!D:U,13,0),"") -> 6000 | N74: =L74-(M74*I74) -> 4000 | O74: C | P74: =IFERROR((J74-M74)/J74*100,0) -> 40
A75: 04/02/26 | B75: 15:47:00 | D75: 1 | E75: PS4009 | F75: =A75&E75 -> 04/02/26PS4009 | G75: =O75&A75 -> C04/02/26 | H75: =IFNA(VLOOKUP(TRIM(E75),Master!D:M,4,0),"") -> ROUNDUP 200ML | I75: 1 | J75: =IFNA(VLOOKUP(E75,Master!D:U,14,0),0) -> 35000 | K75: 0 | L75: =J75*I75-K75 -> 35000 | M75: =IFNA(VLOOKUP(TRIM(E75),Master!D:U,13,0),"") -> 23000 | N75: =L75-(M75*I75) -> 12000 | O75: C | P75: =IFERROR((J75-M75)/J75*100,0) -> 34.285714
A76: 04/02/26 | B76: 15:52:00 | D76: 1 | E76: MT2050 | F76: =A76&E76 -> 04/02/26MT2050 | G76: =O76&A76 -> C04/02/26 | H76: =IFNA(VLOOKUP(TRIM(E76),Master!D:M,4,0),"") -> TANAH SUBUR 10KG BINTANG TANI | I76: 1 | J76: =IFNA(VLOOKUP(E76,Master!D:U,14,0),0) -> 10000 | K76: 0 | L76: =J76*I76-K76 -> 10000 | M76: =IFNA(VLOOKUP(TRIM(E76),Master!D:U,13,0),"") -> 6000 | N76: =L76-(M76*I76) -> 4000 | O76: C | P76: =IFERROR((J76-M76)/J76*100,0) -> 40
A77: 04/02/26 | E77: MT2039 | F77: =A77&E77 -> 04/02/26MT2039 | G77: =O77&A77 -> C04/02/26 | H77: =IFNA(VLOOKUP(TRIM(E77),Master!D:M,4,0),"") -> SEKAM BAKAR 10KG | I77: 1 | J77: =IFNA(VLOOKUP(E77,Master!D:U,14,0),0) -> 12000 | K77: 0 | L77: =J77*I77-K77 -> 12000 | M77: =IFNA(VLOOKUP(TRIM(E77),Master!D:U,13,0),"") -> 6000 | N77: =L77-(M77*I77) -> 6000 | O77: C | P77: =IFERROR((J77-M77)/J77*100,0) -> 50
A78: 04/02/26 | B78: 16:38:00 | D78: 1 | E78: PL3073 | F78: =A78&E78 -> 04/02/26PL3073 | G78: =O78&A78 -> T04/02/26 | H78: =IFNA(VLOOKUP(TRIM(E78),Master!D:M,4,0),"") -> GERGAJI BONSAI MINI | I78: 1 | J78: =IFNA(VLOOKUP(E78,Master!D:U,14,0),0) -> 60000 | K78: 0 | L78: =J78*I78-K78 -> 60000 | M78: =IFNA(VLOOKUP(TRIM(E78),Master!D:U,13,0),"") -> 37262 | N78: =L78-(M78*I78) -> 22738 | O78: T | P78: =IFERROR((J78-M78)/J78*100,0) -> 37.896667
A79: 04/02/26 | B79: 16:38:00 | D79: 1 | E79: MT2050 | F79: =A79&E79 -> 04/02/26MT2050 | G79: =O79&A79 -> C04/02/26 | H79: =IFNA(VLOOKUP(TRIM(E79),Master!D:M,4,0),"") -> TANAH SUBUR 10KG BINTANG TANI | I79: 1 | J79: =IFNA(VLOOKUP(E79,Master!D:U,14,0),0) -> 10000 | K79: 0 | L79: =J79*I79-K79 -> 10000 | M79: =IFNA(VLOOKUP(TRIM(E79),Master!D:U,13,0),"") -> 6000 | N79: =L79-(M79*I79) -> 4000 | O79: C | P79: =IFERROR((J79-M79)/J79*100,0) -> 40
A80: 04/02/26 | E80: PL3164 | F80: =A80&E80 -> 04/02/26PL3164 | G80: =O80&A80 -> C04/02/26 | H80: =IFNA(VLOOKUP(TRIM(E80),Master!D:M,4,0),"") -> POT GMP HITAM 35 POLOS | I80: 2 | J80: =IFNA(VLOOKUP(E80,Master!D:U,14,0),0) -> 14000 | K80: 0 | L80: =J80*I80-K80 -> 28000 | M80: =IFNA(VLOOKUP(TRIM(E80),Master!D:U,13,0),"") -> 10250 | N80: =L80-(M80*I80) -> 7500 | O80: C | P80: =IFERROR((J80-M80)/J80*100,0) -> 26.785714
A81: 04/02/26 | B81: 16:55:00 | D81: 1 | E81: MT2050 | F81: =A81&E81 -> 04/02/26MT2050 | G81: =O81&A81 -> C04/02/26 | H81: =IFNA(VLOOKUP(TRIM(E81),Master!D:M,4,0),"") -> TANAH SUBUR 10KG BINTANG TANI | I81: 2 | J81: =IFNA(VLOOKUP(E81,Master!D:U,14,0),0) -> 10000 | K81: 0 | L81: =J81*I81-K81 -> 20000 | M81: =IFNA(VLOOKUP(TRIM(E81),Master!D:U,13,0),"") -> 6000 | N81: =L81-(M81*I81) -> 8000 | O81: C | P81: =IFERROR((J81-M81)/J81*100,0) -> 40
A82: 04/02/26 | E82: PL3164 | F82: =A82&E82 -> 04/02/26PL3164 | G82: =O82&A82 -> C04/02/26 | H82: =IFNA(VLOOKUP(TRIM(E82),Master!D:M,4,0),"") -> POT GMP HITAM 35 POLOS | I82: 3 | J82: =IFNA(VLOOKUP(E82,Master!D:U,14,0),0) -> 14000 | K82: 0 | L82: =J82*I82-K82 -> 42000 | M82: =IFNA(VLOOKUP(TRIM(E82),Master!D:U,13,0),"") -> 10250 | N82: =L82-(M82*I82) -> 11250 | O82: C | P82: =IFERROR((J82-M82)/J82*100,0) -> 26.785714
A83: 04/02/26 | B83: 17:29:00 | D83: 1 | E83: MT2052 | F83: =A83&E83 -> 04/02/26MT2052 | G83: =O83&A83 -> C04/02/26 | H83: =IFNA(VLOOKUP(TRIM(E83),Master!D:M,4,0),"") -> TANAH SUBUR 1KG BINTANG TANI | I83: 2 | J83: =IFNA(VLOOKUP(E83,Master!D:U,14,0),0) -> 3000 | K83: 0 | L83: =J83*I83-K83 -> 6000 | M83: =IFNA(VLOOKUP(TRIM(E83),Master!D:U,13,0),"") -> 1200 | N83: =L83-(M83*I83) -> 3600 | O83: C | P83: =IFERROR((J83-M83)/J83*100,0) -> 60
A84: 04/02/26 | B84: 17:41:00 | D84: 1 | E84: PS4011 | F84: =A84&E84 -> 04/02/26PS4011 | G84: =O84&A84 -> C04/02/26 | H84: =IFNA(VLOOKUP(TRIM(E84),Master!D:M,4,0),"") -> STARLON 665 EC HERBISIDA 100ML | I84: 2 | J84: =IFNA(VLOOKUP(E84,Master!D:U,14,0),0) -> 45000 | K84: 0 | L84: =J84*I84-K84 -> 90000 | M84: =IFNA(VLOOKUP(TRIM(E84),Master!D:U,13,0),"") -> 35000 | N84: =L84-(M84*I84) -> 20000 | O84: C | P84: =IFERROR((J84-M84)/J84*100,0) -> 22.222222
A85: 05/02/26 | B85: 10:03:00 | D85: 1 | E85: PL3042 | F85: =A85&E85 -> 05/02/26PL3042 | G85: =O85&A85 -> O05/02/26 | H85: =IFNA(VLOOKUP(TRIM(E85),Master!D:M,4,0),"") -> KAWAT BONSAI SILVER NO.2 ECERAN | I85: 10 | J85: =IFNA(VLOOKUP(E85,Master!D:U,14,0),0) -> 1500 | K85: 0 | L85: =J85*I85-K85 -> 15000 | M85: =IFNA(VLOOKUP(TRIM(E85),Master!D:U,13,0),"") -> 800 | N85: =L85-(M85*I85) -> 7000 | O85: O | P85: =IFERROR((J85-M85)/J85*100,0) -> 46.666667
A86: 05/02/26 | B86: 10:25:00 | D86: 1 | E86: PL3063 | F86: =A86&E86 -> 05/02/26PL3063 | G86: =O86&A86 -> C05/02/26 | H86: =IFNA(VLOOKUP(TRIM(E86),Master!D:M,4,0),"") -> BENANG EXTRA BESAR | I86: 1 | J86: =IFNA(VLOOKUP(E86,Master!D:U,14,0),0) -> 22000 | K86: -3000 | L86: =J86*I86-K86 -> 25000 | M86: =IFNA(VLOOKUP(TRIM(E86),Master!D:U,13,0),"") -> 17000 | N86: =L86-(M86*I86) -> 8000 | O86: C | P86: =IFERROR((J86-M86)/J86*100,0) -> 22.727273
A87: 05/02/26 | B87: 10:27:00 | D87: 1 | E87: PK5037 | F87: =A87&E87 -> 05/02/26PK5037 | G87: =O87&A87 -> O05/02/26 | H87: =IFNA(VLOOKUP(TRIM(E87),Master!D:M,4,0),"") -> PUPUK BIO FLOWER SUPER 100ML | I87: 1 | J87: =IFNA(VLOOKUP(E87,Master!D:U,14,0),0) -> 25000 | K87: 0 | L87: =J87*I87-K87 -> 25000 | M87: =IFNA(VLOOKUP(TRIM(E87),Master!D:U,13,0),"") -> 20000 | N87: =L87-(M87*I87) -> 5000 | O87: O | P87: =IFERROR((J87-M87)/J87*100,0) -> 20
A88: 05/02/26 | E88: PL3040 | F88: =A88&E88 -> 05/02/26PL3040 | G88: =O88&A88 -> O05/02/26 | H88: =IFNA(VLOOKUP(TRIM(E88),Master!D:M,4,0),"") -> KAWAT BONSAI SILVER NO.1.5 ECERAN | I88: 10 | J88: =IFNA(VLOOKUP(E88,Master!D:U,14,0),0) -> 750 | K88: 0 | L88: =J88*I88-K88 -> 7500 | M88: =IFNA(VLOOKUP(TRIM(E88),Master!D:U,13,0),"") -> 444 | N88: =L88-(M88*I88) -> 3060 | O88: O | P88: =IFERROR((J88-M88)/J88*100,0) -> 40.8
A89: 05/02/26 | E89: PL3040 | F89: =A89&E89 -> 05/02/26PL3040 | G89: =O89&A89 -> O05/02/26 | H89: =IFNA(VLOOKUP(TRIM(E89),Master!D:M,4,0),"") -> KAWAT BONSAI SILVER NO.1.5 ECERAN | I89: 5 | J89: =IFNA(VLOOKUP(E89,Master!D:U,14,0),0) -> 750 | K89: 0 | L89: =J89*I89-K89 -> 3750 | M89: =IFNA(VLOOKUP(TRIM(E89),Master!D:U,13,0),"") -> 444 | N89: =L89-(M89*I89) -> 1530 | O89: O | P89: =IFERROR((J89-M89)/J89*100,0) -> 40.8
A90: 05/02/26 | E90: PL3042 | F90: =A90&E90 -> 05/02/26PL3042 | G90: =O90&A90 -> O05/02/26 | H90: =IFNA(VLOOKUP(TRIM(E90),Master!D:M,4,0),"") -> KAWAT BONSAI SILVER NO.2 ECERAN | I90: 5 | J90: =IFNA(VLOOKUP(E90,Master!D:U,14,0),0) -> 1500 | K90: 0 | L90: =J90*I90-K90 -> 7500 | M90: =IFNA(VLOOKUP(TRIM(E90),Master!D:U,13,0),"") -> 800 | N90: =L90-(M90*I90) -> 3500 | O90: O | P90: =IFERROR((J90-M90)/J90*100,0) -> 46.666667
A91: 05/02/26 | E91: PK5013 | F91: =A91&E91 -> 05/02/26PK5013 | G91: =O91&A91 -> O05/02/26 | H91: =IFNA(VLOOKUP(TRIM(E91),Master!D:M,4,0),"") -> DEKASTAR 171110 KTK 100GR | I91: 1 | J91: =IFNA(VLOOKUP(E91,Master!D:U,14,0),0) -> 30000 | K91: 0 | L91: =J91*I91-K91 -> 30000 | M91: =IFNA(VLOOKUP(TRIM(E91),Master!D:U,13,0),"") -> 24000 | N91: =L91-(M91*I91) -> 6000 | O91: O | P91: =IFERROR((J91-M91)/J91*100,0) -> 20
A92: 05/02/26 | B92: 14:27:00 | D92: 1 | E92: MT2050 | F92: =A92&E92 -> 05/02/26MT2050 | G92: =O92&A92 -> T05/02/26 | H92: =IFNA(VLOOKUP(TRIM(E92),Master!D:M,4,0),"") -> TANAH SUBUR 10KG BINTANG TANI | I92: 2 | J92: =IFNA(VLOOKUP(E92,Master!D:U,14,0),0) -> 10000 | K92: 0 | L92: =J92*I92-K92 -> 20000 | M92: =IFNA(VLOOKUP(TRIM(E92),Master!D:U,13,0),"") -> 6000 | N92: =L92-(M92*I92) -> 8000 | O92: T | P92: =IFERROR((J92-M92)/J92*100,0) -> 40
A93: 05/02/26 | E93: PK5064 | F93: =A93&E93 -> 05/02/26PK5064 | G93: =O93&A93 -> T05/02/26 | H93: =IFNA(VLOOKUP(TRIM(E93),Master!D:M,4,0),"") -> PUPUK UREA 1KG | I93: 2 | J93: =IFNA(VLOOKUP(E93,Master!D:U,14,0),0) -> 14000 | K93: 0 | L93: =J93*I93-K93 -> 28000 | M93: =IFNA(VLOOKUP(TRIM(E93),Master!D:U,13,0),"") -> 10000 | N93: =L93-(M93*I93) -> 8000 | O93: T | P93: =IFERROR((J93-M93)/J93*100,0) -> 28.571429
A94: 05/02/26 | B94: 14:28:00 | D94: 1 | E94: PK5012 | F94: =A94&E94 -> 05/02/26PK5012 | G94: =O94&A94 -> O05/02/26 | H94: =IFNA(VLOOKUP(TRIM(E94),Master!D:M,4,0),"") -> DEKASTAR 171110 BTL 100GR | I94: 2 | J94: =IFNA(VLOOKUP(E94,Master!D:U,14,0),0) -> 25000 | K94: 0 | L94: =J94*I94-K94 -> 50000 | M94: =IFNA(VLOOKUP(TRIM(E94),Master!D:U,13,0),"") -> 14800 | N94: =L94-(M94*I94) -> 20400 | O94: O | P94: =IFERROR((J94-M94)/J94*100,0) -> 40.8
A95: 05/02/26 | B95: 16:05:00 | D95: 1 | E95: MT2037 | F95: =A95&E95 -> 05/02/26MT2037 | G95: =O95&A95 -> C05/02/26 | H95: =IFNA(VLOOKUP(TRIM(E95),Master!D:M,4,0),"") -> PUPUK KOMPOS 5KG | I95: 1 | J95: =IFNA(VLOOKUP(E95,Master!D:U,14,0),0) -> 10000 | K95: 0 | L95: =J95*I95-K95 -> 10000 | M95: =IFNA(VLOOKUP(TRIM(E95),Master!D:U,13,0),"") -> 5000 | N95: =L95-(M95*I95) -> 5000 | O95: C | P95: =IFERROR((J95-M95)/J95*100,0) -> 50
A96: 05/02/26 | B96: 16:05:00 | D96: 1 | E96: MT2050 | F96: =A96&E96 -> 05/02/26MT2050 | G96: =O96&A96 -> C05/02/26 | H96: =IFNA(VLOOKUP(TRIM(E96),Master!D:M,4,0),"") -> TANAH SUBUR 10KG BINTANG TANI | I96: 5 | J96: =IFNA(VLOOKUP(E96,Master!D:U,14,0),0) -> 10000 | K96: 0 | L96: =J96*I96-K96 -> 50000 | M96: =IFNA(VLOOKUP(TRIM(E96),Master!D:U,13,0),"") -> 6000 | N96: =L96-(M96*I96) -> 20000 | O96: C | P96: =IFERROR((J96-M96)/J96*100,0) -> 40
A97: 05/02/26 | E97: PL3164 | F97: =A97&E97 -> 05/02/26PL3164 | G97: =O97&A97 -> C05/02/26 | H97: =IFNA(VLOOKUP(TRIM(E97),Master!D:M,4,0),"") -> POT GMP HITAM 35 POLOS | I97: 3 | J97: =IFNA(VLOOKUP(E97,Master!D:U,14,0),0) -> 14000 | K97: 0 | L97: =J97*I97-K97 -> 42000 | M97: =IFNA(VLOOKUP(TRIM(E97),Master!D:U,13,0),"") -> 10250 | N97: =L97-(M97*I97) -> 11250 | O97: C | P97: =IFERROR((J97-M97)/J97*100,0) -> 26.785714
A98: 05/02/26 | B98: 17:17:00 | D98: 1 | E98: MT2022 | F98: =A98&E98 -> 05/02/26MT2022 | G98: =O98&A98 -> C05/02/26 | H98: =IFNA(VLOOKUP(TRIM(E98),Master!D:M,4,0),"") -> PASIR MALANG 10KG | I98: 1 | J98: =IFNA(VLOOKUP(E98,Master!D:U,14,0),0) -> 15000 | K98: 0 | L98: =J98*I98-K98 -> 15000 | M98: =IFNA(VLOOKUP(TRIM(E98),Master!D:U,13,0),"") -> 8000 | N98: =L98-(M98*I98) -> 7000 | O98: C | P98: =IFERROR((J98-M98)/J98*100,0) -> 46.666667
A99: 05/02/26 | B99: 17:26:00 | D99: 1 | E99: MT2050 | F99: =A99&E99 -> 05/02/26MT2050 | G99: =O99&A99 -> C05/02/26 | H99: =IFNA(VLOOKUP(TRIM(E99),Master!D:M,4,0),"") -> TANAH SUBUR 10KG BINTANG TANI | I99: 3 | J99: =IFNA(VLOOKUP(E99,Master!D:U,14,0),0) -> 10000 | K99: 0 | L99: =J99*I99-K99 -> 30000 | M99: =IFNA(VLOOKUP(TRIM(E99),Master!D:U,13,0),"") -> 6000 | N99: =L99-(M99*I99) -> 12000 | O99: C | P99: =IFERROR((J99-M99)/J99*100,0) -> 40
A100: 05/02/26 | B100: 17:33:00 | D100: 1 | E100: MT2050 | F100: =A100&E100 -> 05/02/26MT2050 | G100: =O100&A100 -> C05/02/26 | H100: =IFNA(VLOOKUP(TRIM(E100),Master!D:M,4,0),"") -> TANAH SUBUR 10KG BINTANG TANI | I100: 1 | J100: =IFNA(VLOOKUP(E100,Master!D:U,14,0),0) -> 10000 | K100: 0 | L100: =J100*I100-K100 -> 10000 | M100: =IFNA(VLOOKUP(TRIM(E100),Master!D:U,13,0),"") -> 6000 | N100: =L100-(M100*I100) -> 4000 | O100: C | P100: =IFERROR((J100-M100)/J100*100,0) -> 40
A101: 05/02/26 | E101: PK5043 | F101: =A101&E101 -> 05/02/26PK5043 | G101: =O101&A101 -> C05/02/26 | H101: =IFNA(VLOOKUP(TRIM(E101),Master!D:M,4,0),"") -> PUPUK KAMBING 5KG | I101: 1 | J101: =IFNA(VLOOKUP(E101,Master!D:U,14,0),0) -> 15000 | K101: 0 | L101: =J101*I101-K101 -> 15000 | M101: =IFNA(VLOOKUP(TRIM(E101),Master!D:U,13,0),"") -> 8000 | N101: =L101-(M101*I101) -> 7000 | O101: C | P101: =IFERROR((J101-M101)/J101*100,0) -> 46.666667
A102: 05/02/26 | E102: PK5048 | F102: =A102&E102 -> 05/02/26PK5048 | G102: =O102&A102 -> C05/02/26 | H102: =IFNA(VLOOKUP(TRIM(E102),Master!D:M,4,0),"") -> PUPUK MUTIARA 161616 100GR RPK | I102: 1 | J102: =IFNA(VLOOKUP(E102,Master!D:U,14,0),0) -> 3000 | K102: -2000 | L102: =J102*I102-K102 -> 5000 | M102: =IFNA(VLOOKUP(TRIM(E102),Master!D:U,13,0),"") -> 1900 | N102: =L102-(M102*I102) -> 3100 | O102: C | P102: =IFERROR((J102-M102)/J102*100,0) -> 36.666667
...

Sheet Master
D3: 1 | E3: 2 | F3: 3 | G3: 4 | H3: 5 | I3: 6 | J3: 7 | K3: 8 | L3: 9 | M3: 10 | N3: 11 | O3: 12 | P3: 13 | Q3: 14 | R3: 15 | S3: 16 | T3: 17 | U3: 18 | V3: 19 | W3: 20 | X3: 21 | Y3: 22
A4: CODE | B4: COUNTER | D4: BARCODE | E4: CATEGORY | F4: SUB CATEGORY | G4: ITEM DESCRIPTIONS | H4: NOTES | I4: COGS | J4: SELL PRICE | K4: MARGIN | L4: MARGIN VAL | M4: VENDOR | N4: 01/12/24 | O4: HJ | P4: 02/12/24 | Q4: HJ | R4: 03/11/24 | S4: HJ | T4: 04/11/24 | U4: HJ | V4: 05/11/24 | W4: HJ | X4: 06/11/24 | Y4: HJ
A5: OK | B5: =IF(A4=A5,B4+1,1) -> 1 | C5: =IF(A4=A5,C4,C4+1) -> 1 | D5: OK1001 | E5: LAIN LAIN | F5: LAIN LAIN | G5: ETHREL 100ML | J5: 65000 | K5: =(J5-I5)/J5*100 -> 100 | L5: =J5-I5 -> 65000 | M5: SHOPEE | N5: =I5 | O5: =J5 -> 65000 | P5: =N5 | Q5: =O5 -> 65000
A6: OK | B6: =IF(A5=A6,B5+1,1) -> 2 | C6: =IF(A5=A6,C5,C5+1) -> 1 | D6: OK1002 | E6: LAIN LAIN | F6: LAIN LAIN | G6: KARANG | I6: 1 | J6: 1 | K6: =(J6-I6)/J6*100 -> 0 | L6: =J6-I6 -> 0 | N6: 1 | O6: 1 | P6: =N6 -> 1 | Q6: =O6 -> 1
A7: OK | B7: =IF(A6=A7,B6+1,1) -> 3 | C7: =IF(A6=A7,C6,C6+1) -> 1 | D7: OK1003 | E7: LAIN LAIN | F7: LAIN LAIN | G7: ONGKIR | I7: 0 | J7: 1 | K7: =(J7-I7)/J7*100 -> 100 | L7: =J7-I7 -> 1 | N7: 0 | O7: 1 | P7: =N7 -> 0 | Q7: =O7 -> 1
A8: MT | B8: =IF(A7=A8,B7+1,1) -> 1 | C8: =IF(A7=A8,C7,C7+1) -> 2 | D8: MT2001 | E8: MEDIA TANAM | F8: MEDIA TANAM | G8: ANDAM | I8: 7142.8571 | J8: 15000 | K8: =(J8-I8)/J8*100 -> 52.380952 | L8: =J8-I8 -> 7857.1429 | N8: 7142.8571 | O8: 15000 | P8: =N8 -> 7142.8571 | Q8: =O8 -> 15000
A9: MT | B9: =IF(A8=A9,B8+1,1) -> 2 | C9: =IF(A8=A9,C8,C8+1) -> 2 | D9: MT2002 | E9: MEDIA TANAM | F9: MEDIA TANAM | G9: ANDAM 25KG | I9: 30000 | J9: 50000 | K9: =(J9-I9)/J9*100 -> 40 | L9: =J9-I9 -> 20000 | N9: =I9 -> 30000 | O9: =J9 -> 50000 | P9: =N9 -> 30000 | Q9: =O9 -> 50000
A10: MT | B10: =IF(A9=A10,B9+1,1) -> 3 | C10: =IF(A9=A10,C9,C9+1) -> 2 | D10: MT2003 | E10: MEDIA TANAM | F10: MEDIA TANAM | G10: ARANG 5KG | I10: 8000 | J10: 15000 | K10: =(J10-I10)/J10*100 -> 46.666667 | L10: =J10-I10 -> 7000 | N10: 8000 | O10: 15000 | P10: =N10 -> 8000 | Q10: =O10 -> 15000
A11: MT | B11: =IF(A10=A11,B10+1,1) -> 4 | C11: =IF(A10=A11,C10,C10+1) -> 2 | D11: MT2004 | E11: MEDIA TANAM | F11: MEDIA TANAM | G11: COCO FIBER | I11: 8000 | J11: 13000 | K11: =(J11-I11)/J11*100 -> 38.461538 | L11: =J11-I11 -> 5000 | M11: BINTANG TANI | N11: 8000 | O11: 13000 | P11: =N11 -> 8000 | Q11: =O11 -> 13000
A12: MT | B12: =IF(A11=A12,B11+1,1) -> 5 | C12: =IF(A11=A12,C11,C11+1) -> 2 | D12: MT2005 | E12: MEDIA TANAM | F12: MEDIA TANAM | G12: COCOPEAT BLOCK MINI | I12: 18000 | J12: 25000 | K12: =(J12-I12)/J12*100 -> 28 | L12: =J12-I12 -> 7000 | N12: 18000 | O12: 25000 | P12: =N12 -> 18000 | Q12: =O12 -> 25000
A13: MT | B13: =IF(A12=A13,B12+1,1) -> 6 | C13: =IF(A12=A13,C12,C12+1) -> 2 | D13: MT2006 | E13: MEDIA TANAM | F13: MEDIA TANAM | G13: COCOPEAT FERMENTASI 10KG | I13: 10000 | J13: 15000 | K13: =(J13-I13)/J13*100 -> 33.333333 | L13: =J13-I13 -> 5000 | M13: VENDOR OTHER | N13: 10000 | O13: 15000 | P13: =N13 -> 10000 | Q13: =O13 -> 15000
A14: MT | B14: =IF(A13=A14,B13+1,1) -> 7 | C14: =IF(A13=A14,C13,C13+1) -> 2 | D14: MT2007 | E14: MEDIA TANAM | F14: MEDIA TANAM | G14: COCOPEAT FERMENTASI 5KG | I14: 3000 | J14: 8000 | K14: =(J14-I14)/J14*100 -> 62.5 | L14: =J14-I14 -> 5000 | N14: =I14 -> 3000 | O14: =J14 -> 8000 | P14: =N14 -> 3000 | Q14: =O14 -> 8000
A15: MT | B15: =IF(A14=A15,B14+1,1) -> 8 | C15: =IF(A14=A15,C14,C14+1) -> 2 | D15: MT2008 | E15: MEDIA TANAM | F15: MEDIA TANAM | G15: COCOPEAT NON FERMENTASI 10KG | I15: 6000 | J15: 10000 | K15: =(J15-I15)/J15*100 -> 40 | L15: =J15-I15 -> 4000 | M15: BINTANG TANI | N15: 6000 | O15: 10000 | P15: =N15 -> 6000 | Q15: =O15 -> 10000
A16: MT | B16: =IF(A15=A16,B15+1,1) -> 9 | C16: =IF(A15=A16,C15,C15+1) -> 2 | D16: MT2009 | E16: MEDIA TANAM | F16: MEDIA TANAM | G16: COCOPEAT NON FERMENTASI 5KG | I16: 3000 | J16: 5000 | K16: =(J16-I16)/J16*100 -> 40 | L16: =J16-I16 -> 2000 | N16: 3000 | O16: 5000 | P16: =N16 -> 3000 | Q16: =O16 -> 5000
A17: MT | B17: =IF(A16=A17,B16+1,1) -> 10 | C17: =IF(A16=A17,C16,C16+1) -> 2 | D17: MT2010 | E17: MEDIA TANAM | F17: MEDIA TANAM | G17: DAUN BAMBU | I17: 6000 | J17: 12000 | K17: =(J17-I17)/J17*100 -> 50 | L17: =J17-I17 -> 6000 | M17: BINTANG TANI | N17: 6000 | O17: 12000 | P17: =N17 -> 6000 | Q17: =O17 -> 12000
A18: MT | B18: =IF(A17=A18,B17+1,1) -> 11 | C18: =IF(A17=A18,C17,C17+1) -> 2 | D18: MT2011 | E18: MEDIA TANAM | F18: MEDIA TANAM | G18: HUMUS BAMBU | I18: 4285.7143 | J18: 12000 | K18: =(J18-I18)/J18*100 -> 64.285714 | L18: =J18-I18 -> 7714.2857 | N18: 4285.7143 | O18: 12000 | P18: =N18 -> 4285.7143 | Q18: =O18 -> 12000
A19: MT | B19: =IF(A18=A19,B18+1,1) -> 12 | C19: =IF(A18=A19,C18,C18+1) -> 2 | D19: MT2012 | E19: MEDIA TANAM | F19: MEDIA TANAM | G19: HUMUS BAMBU 25KG | I19: 30000 | J19: 50000 | K19: =(J19-I19)/J19*100 -> 40 | L19: =J19-I19 -> 20000 | M19: GENTA | N19: =I19 -> 30000 | O19: =J19 -> 50000 | P19: =N19 -> 30000 | Q19: =O19 -> 50000
A20: MT | B20: =IF(A19=A20,B19+1,1) -> 13 | C20: =IF(A19=A20,C19,C19+1) -> 2 | D20: MT2013 | E20: MEDIA TANAM | F20: MEDIA TANAM | G20: HYDROTON 1KG | I20: 37000 | J20: 50000 | K20: =(J20-I20)/J20*100 -> 26 | L20: =J20-I20 -> 13000 | N20: =I20 -> 37000 | O20: =J20 -> 50000 | P20: =N20 -> 37000 | Q20: =O20 -> 50000
A21: MT | B21: =IF(A20=A21,B20+1,1) -> 14 | C21: =IF(A20=A21,C20,C20+1) -> 2 | D21: MT2014 | E21: MEDIA TANAM | F21: MEDIA TANAM | G21: HYDROTON 500GR | I21: 18500 | J21: 25000 | K21: =(J21-I21)/J21*100 -> 26 | L21: =J21-I21 -> 6500 | N21: =I21 -> 18500 | O21: =J21 -> 25000 | P21: =N21 -> 18500 | Q21: =O21 -> 25000
A22: MT | B22: =IF(A21=A22,B21+1,1) -> 15 | C22: =IF(A21=A22,C21,C21+1) -> 2 | D22: MT2015 | E22: MEDIA TANAM | F22: MEDIA TANAM | G22: MEDIA AROID MIX | I22: 10000 | J22: 15000 | K22: =(J22-I22)/J22*100 -> 33.333333 | L22: =J22-I22 -> 5000 | N22: 10000 | O22: 15000 | P22: =N22 -> 10000 | Q22: =O22 -> 15000
A23: MT | B23: =IF(A22=A23,B22+1,1) -> 16 | C23: =IF(A22=A23,C22,C22+1) -> 2 | D23: MT2016 | E23: MEDIA TANAM | F23: MEDIA TANAM | G23: MOSS HITAM 1 KAMPIL | I23: 50000 | J23: 70000 | K23: =(J23-I23)/J23*100 -> 28.571429 | L23: =J23-I23 -> 20000 | M23: VENDOR OTHER | N23: 50000 | O23: 70000 | P23: =N23 -> 50000 | Q23: =O23 -> 70000
A24: MT | B24: =IF(A23=A24,B23+1,1) -> 17 | C24: =IF(A23=A24,C23,C23+1) -> 2 | D24: MT2017 | E24: MEDIA TANAM | F24: MEDIA TANAM | G24: MOSS HITAM 10KG | I24: 12000 | J24: 20000 | K24: =(J24-I24)/J24*100 -> 40 | L24: =J24-I24 -> 8000 | N24: =I24 -> 12000 | O24: =J24 -> 20000 | P24: =N24 -> 12000 | Q24: =O24 -> 20000
A25: MT | B25: =IF(A24=A25,B24+1,1) -> 18 | C25: =IF(A24=A25,C24,C24+1) -> 2 | D25: MT2018 | E25: MEDIA TANAM | F25: MEDIA TANAM | G25: MOSS HITAM 5KG | I25: 7500 | J25: 12000 | K25: =(J25-I25)/J25*100 -> 37.5 | L25: =J25-I25 -> 4500 | M25: BINTANG TANI | N25: 7500 | O25: 12000 | P25: =N25 -> 7500 | Q25: =O25 -> 12000
A26: MT | B26: =IF(A25=A26,B25+1,1) -> 19 | C26: =IF(A25=A26,C25,C25+1) -> 2 | D26: MT2019 | E26: MEDIA TANAM | F26: MEDIA TANAM | G26: MOSS SPHAGNUM 200GR | I26: =100000/4 -> 25000 | J26: 35000 | K26: =(J26-I26)/J26*100 -> 28.571429 | L26: =J26-I26 -> 10000 | N26: =I26 -> 25000 | O26: =J26 -> 35000 | P26: =N26 -> 25000 | Q26: =O26 -> 35000
A27: MT | B27: =IF(A26=A27,B26+1,1) -> 20 | C27: =IF(A26=A27,C26,C26+1) -> 2 | D27: MT2020 | E27: MEDIA TANAM | F27: MEDIA TANAM | G27: PAKIS CACAH | I27: 7000 | J27: 12000 | K27: =(J27-I27)/J27*100 -> 41.666667 | L27: =J27-I27 -> 5000 | N27: 7000 | O27: 12000 | P27: =N27 -> 7000 | Q27: =O27 -> 12000
A28: MT | B28: =IF(A27=A28,B27+1,1) -> 21 | C28: =IF(A27=A28,C27,C27+1) -> 2 | D28: MT2021 | E28: MEDIA TANAM | F28: MEDIA TANAM | G28: PAPAN PAKIS | I28: 5000 | J28: 6000 | K28: =(J28-I28)/J28*100 -> 16.666667 | L28: =J28-I28 -> 1000 | N28: 4000 | O28: 6000 | P28: =N28 -> 4000 | Q28: =O28 -> 6000
A29: MT | B29: =IF(A28=A29,B28+1,1) -> 22 | C29: =IF(A28=A29,C28,C28+1) -> 2 | D29: MT2022 | E29: MEDIA TANAM | F29: MEDIA TANAM | G29: PASIR MALANG 10KG | I29: 8000 | J29: 15000 | K29: =(J29-I29)/J29*100 -> 46.666667 | L29: =J29-I29 -> 7000 | M29: BINTANG TANI | N29: 8000 | O29: 15000 | P29: =N29 -> 8000 | Q29: =O29 -> 15000
A30: MT | B30: =IF(A29=A30,B29+1,1) -> 23 | C30: =IF(A29=A30,C29,C29+1) -> 2 | D30: MT2023 | E30: MEDIA TANAM | F30: MEDIA TANAM | G30: PASIR MALANG 1KG | I30: =8500/10 -> 850 | J30: 3000 | K30: =(J30-I30)/J30*100 -> 71.666667 | L30: =J30-I30 -> 2150 | N30: =I30 -> 850 | O30: =J30 -> 3000 | P30: =N30 -> 850 | Q30: =O30 -> 3000
A31: MT | B31: =IF(A30=A31,B30+1,1) -> 24 | C31: =IF(A30=A31,C30,C30+1) -> 2 | D31: MT2024 | E31: MEDIA TANAM | F31: MEDIA TANAM | G31: PASIR MALANG 25KG | I31: 25000 | J31: 35000 | K31: =(J31-I31)/J31*100 -> 28.571429 | L31: =J31-I31 -> 10000 | M31: BINTANG TANI | N31: 25000 | O31: 35000 | P31: =N31 -> 25000 | Q31: =O31 -> 35000
A32: MT | B32: =IF(A31=A32,B31+1,1) -> 25 | C32: =IF(A31=A32,C31,C31+1) -> 2 | D32: MT2025 | E32: MEDIA TANAM | F32: MEDIA TANAM | G32: PASIR MALANG HALUS | I32: 13000 | J32: 17000 | K32: =(J32-I32)/J32*100 -> 23.529412 | L32: =J32-I32 -> 4000 | N32: 13000 | O32: 17000 | P32: =N32 -> 13000 | Q32: =O32 -> 17000
A33: MT | B33: =IF(A32=A33,B32+1,1) -> 26 | C33: =IF(A32=A33,C32,C32+1) -> 2 | D33: MT2026 | E33: MEDIA TANAM | F33: MEDIA TANAM | G33: PASIR MALANG KASAR 10KG | I33: 8000 | J33: 15000 | K33: =(J33-I33)/J33*100 -> 46.666667 | L33: =J33-I33 -> 7000 | M33: BINTANG TANI | N33: 8000 | O33: 15000 | P33: =N33 -> 8000 | Q33: =O33 -> 15000
A34: MT | B34: =IF(A33=A34,B33+1,1) -> 27 | C34: =IF(A33=A34,C33,C33+1) -> 2 | D34: MT2027 | E34: MEDIA TANAM | F34: MEDIA TANAM | G34: PASIR MALANG MERAH KASAR | I34: 15000 | J34: 20000 | K34: =(J34-I34)/J34*100 -> 25 | L34: =J34-I34 -> 5000 | N34: 15000 | O34: 20000 | P34: =N34 -> 15000 | Q34: =O34 -> 20000
A35: MT | B35: =IF(A34=A35,B34+1,1) -> 28 | C35: =IF(A34=A35,C34,C34+1) -> 2 | D35: MT2028 | E35: MEDIA TANAM | F35: MEDIA TANAM | G35: PASIR MALANG MERAH PASIRAN 5KG | I35: 13000 | J35: 17000 | K35: =(J35-I35)/J35*100 -> 23.529412 | L35: =J35-I35 -> 4000 | M35: GENTA | N35: 13000 | O35: 17000 | P35: =N35 -> 13000 | Q35: =O35 -> 17000
A36: MT | B36: =IF(A35=A36,B35+1,1) -> 29 | C36: =IF(A35=A36,C35,C35+1) -> 2 | D36: MT2029 | E36: MEDIA TANAM | F36: MEDIA TANAM | G36: PASIR MALANG MERAH SEDANG 5KG | I36: 13000 | J36: 17000 | K36: =(J36-I36)/J36*100 -> 23.529412 | L36: =J36-I36 -> 4000 | M36: GENTA | N36: 13000 | O36: 17000 | P36: =N36 -> 13000 | Q36: =O36 -> 17000
A37: MT | B37: =IF(A36=A37,B36+1,1) -> 30 | C37: =IF(A36=A37,C36,C36+1) -> 2 | D37: MT2030 | E37: MEDIA TANAM | F37: MEDIA TANAM | G37: PERLITE | I37: 20000 | J37: 40000 | K37: =(J37-I37)/J37*100 -> 50 | L37: =J37-I37 -> 20000 | N37: =I37 -> 20000 | O37: =J37 -> 40000 | P37: =N37 -> 20000 | Q37: =O37 -> 40000
A38: MT | B38: =IF(A37=A38,B37+1,1) -> 31 | C38: =IF(A37=A38,C37,C37+1) -> 2 | D38: MT2031 | E38: MEDIA TANAM | F38: MEDIA TANAM | G38: PINE BARK | I38: 12000 | J38: 20000 | K38: =(J38-I38)/J38*100 -> 40 | L38: =J38-I38 -> 8000 | N38: 12000 | O38: 20000 | P38: =N38 -> 12000 | Q38: =O38 -> 20000
A39: MT | B39: =IF(A38=A39,B38+1,1) -> 32 | C39: =IF(A38=A39,C38,C38+1) -> 2 | D39: MT2032 | E39: MEDIA TANAM | F39: MEDIA TANAM | G39: PUMICE 1-2M PASIRAN /KG | I39: 3250 | J39: 7500 | K39: =(J39-I39)/J39*100 -> 56.666667 | L39: =J39-I39 -> 4250 | M39: GENTA | N39: 3250 | O39: 7500 | P39: =N39 -> 3250 | Q39: =O39 -> 7500
A40: MT | B40: =IF(A39=A40,B39+1,1) -> 33 | C40: =IF(A39=A40,C39,C39+1) -> 2 | D40: MT2033 | E40: MEDIA TANAM | F40: MEDIA TANAM | G40: PUMICE 5-7M SEDANG /KG | I40: 3250 | J40: 7500 | K40: =(J40-I40)/J40*100 -> 56.666667 | L40: =J40-I40 -> 4250 | M40: GENTA | N40: 3250 | O40: 7500 | P40: =N40 -> 3250 | Q40: =O40 -> 7500
A41: MT | B41: =IF(A40=A41,B40+1,1) -> 34 | C41: =IF(A40=A41,C40,C40+1) -> 2 | D41: MT2034 | E41: MEDIA TANAM | F41: MEDIA TANAM | G41: PUMICE/BATU APUNG | J41: 17000 | K41: =(J41-I41)/J41*100 -> 100 | L41: =J41-I41 -> 17000 | O41: 17000 | P41: =N41 | Q41: =O41 -> 17000
A42: MT | B42: =IF(A41=A42,B41+1,1) -> 35 | C42: =IF(A41=A42,C41,C41+1) -> 2 | D42: MT2035 | E42: MEDIA TANAM | F42: MEDIA TANAM | G42: PUPUK KAMBING BUTIRAN | I42: 8000 | J42: 15000 | K42: =(J42-I42)/J42*100 -> 46.666667 | L42: =J42-I42 -> 7000 | N42: 8000 | O42: 15000 | P42: =N42 -> 8000 | Q42: =O42 -> 15000
A43: MT | B43: =IF(A42=A43,B42+1,1) -> 36 | C43: =IF(A42=A43,C42,C42+1) -> 2 | D43: MT2036 | E43: MEDIA TANAM | F43: MEDIA TANAM | G43: PUPUK KOMPOS 10KG | I43: 10000 | J43: 15000 | K43: =(J43-I43)/J43*100 -> 33.333333 | L43: =J43-I43 -> 5000 | N43: =I43 -> 10000 | O43: =J43 -> 15000 | P43: =N43 -> 10000 | Q43: =O43 -> 15000
A44: MT | B44: =IF(A43=A44,B43+1,1) -> 37 | C44: =IF(A43=A44,C43,C43+1) -> 2 | D44: MT2037 | E44: MEDIA TANAM | F44: MEDIA TANAM | G44: PUPUK KOMPOS 5KG | I44: 5000 | J44: 10000 | K44: =(J44-I44)/J44*100 -> 50 | L44: =J44-I44 -> 5000 | N44: 5000 | O44: 10000 | P44: =N44 -> 5000 | Q44: =O44 -> 10000
A45: MT | B45: =IF(A44=A45,B44+1,1) -> 38 | C45: =IF(A44=A45,C44,C44+1) -> 2 | D45: MT2038 | E45: MEDIA TANAM | F45: MEDIA TANAM | G45: ROCK WALL 33CM | I45: 32000 | J45: 38000 | K45: =(J45-I45)/J45*100 -> 15.789474 | L45: =J45-I45 -> 6000 | M45: TRIA GARDEN | N45: 32000 | O45: 38000 | P45: =N45 -> 32000 | Q45: =O45 -> 38000
A46: MT | B46: =IF(A45=A46,B45+1,1) -> 39 | C46: =IF(A45=A46,C45,C45+1) -> 2 | D46: MT2039 | E46: MEDIA TANAM | F46: MEDIA TANAM | G46: SEKAM BAKAR 10KG | I46: 6000 | J46: 10000 | K46: =(J46-I46)/J46*100 -> 40 | L46: =J46-I46 -> 4000 | M46: BINTANG TANI | N46: 6000 | O46: 12000 | P46: =N46 -> 6000 | Q46: =O46 -> 12000
A47: MT | B47: =IF(A46=A47,B46+1,1) -> 40 | C47: =IF(A46=A47,C46,C46+1) -> 2 | D47: MT2040 | E47: MEDIA TANAM | F47: MEDIA TANAM | G47: SEKAM BAKAR 25KG | I47: 17000 | J47: 25000 | K47: =(J47-I47)/J47*100 -> 32 | L47: =J47-I47 -> 8000 | M47: BINTANG TANI | N47: 17000 | O47: 25000 | P47: =N47 -> 17000 | Q47: =O47 -> 25000
A48: MT | B48: =IF(A47=A48,B47+1,1) -> 41 | C48: =IF(A47=A48,C47,C47+1) -> 2 | D48: MT2041 | E48: MEDIA TANAM | F48: MEDIA TANAM | G48: SEKAM BAKAR 5KG | I48: 3400 | J48: 8000 | K48: =(J48-I48)/J48*100 -> 57.5 | L48: =J48-I48 -> 4600 | M48: VENDOR OTHER | N48: 3400 | O48: 8000 | P48: =N48 -> 3400 | Q48: =O48 -> 8000
A49: MT | B49: =IF(A48=A49,B48+1,1) -> 42 | C49: =IF(A48=A49,C48,C48+1) -> 2 | D49: MT2042 | E49: MEDIA TANAM | F49: MEDIA TANAM | G49: SEKAM FERMENTASI 10KG | I49: 6000 | J49: 12000 | K49: =(J49-I49)/J49*100 -> 50 | L49: =J49-I49 -> 6000 | N49: 6000 | O49: 12000 | P49: =N49 -> 6000 | Q49: =O49 -> 12000
A50: MT | B50: =IF(A49=A50,B49+1,1) -> 43 | C50: =IF(A49=A50,C49,C49+1) -> 2 | D50: MT2043 | E50: MEDIA TANAM | F50: MEDIA TANAM | G50: SEKAM FERMENTASI 5KG | I50: 3000 | J50: 8000 | K50: =(J50-I50)/J50*100 -> 62.5 | L50: =J50-I50 -> 5000 | M50: BINTANG TANI | N50: 3000 | O50: 8000 | P50: =N50 -> 3000 | Q50: =O50 -> 8000
A51: MT | B51: =IF(A50=A51,B50+1,1) -> 44 | C51: =IF(A50=A51,C50,C50+1) -> 2 | D51: MT2044 | E51: MEDIA TANAM | F51: MEDIA TANAM | G51: SEKAM MENTAH 10KG | I51: 6000 | J51: 10000 | K51: =(J51-I51)/J51*100 -> 40 | L51: =J51-I51 -> 4000 | M51: BINTANG TANI | N51: 6000 | O51: 10000 | P51: =N51 -> 6000 | Q51: =O51 -> 10000
A52: MT | B52: =IF(A51=A52,B51+1,1) -> 45 | C52: =IF(A51=A52,C51,C51+1) -> 2 | D52: MT2045 | E52: MEDIA TANAM | F52: MEDIA TANAM | G52: SEKAM MENTAH 25KG | I52: 8000 | J52: 15000 | K52: =(J52-I52)/J52*100 -> 46.666667 | L52: =J52-I52 -> 7000 | N52: 8000 | O52: 15000 | P52: =N52 -> 8000 | Q52: =O52 -> 15000
A53: MT | B53: =IF(A52=A53,B52+1,1) -> 46 | C53: =IF(A52=A53,C52,C52+1) -> 2 | D53: MT2046 | E53: MEDIA TANAM | F53: MEDIA TANAM | G53: SEKAM MENTAH 5KG | I53: 1667 | J53: 5000 | K53: =(J53-I53)/J53*100 -> 66.66 | L53: =J53-I53 -> 3333 | M53: BINTANG TANI | N53: 1667 | O53: 5000 | P53: =N53 -> 1667 | Q53: =O53 -> 5000
A54: MT | B54: =IF(A53=A54,B53+1,1) -> 47 | C54: =IF(A53=A54,C53,C53+1) -> 2 | D54: MT2047 | E54: MEDIA TANAM | F54: MEDIA TANAM | G54: TANAH MURNI 10KG | I54: 5000 | J54: 10000 | K54: =(J54-I54)/J54*100 -> 50 | L54: =J54-I54 -> 5000 | N54: =I54 -> 5000 | O54: =J54 -> 10000 | P54: =N54 -> 5000 | Q54: =O54 -> 10000
A55: MT | B55: =IF(A54=A55,B54+1,1) -> 48 | C55: =IF(A54=A55,C54,C54+1) -> 2 | D55: MT2048 | E55: MEDIA TANAM | F55: MEDIA TANAM | G55: TANAH MURNI 1KG | I55: =5000/10 -> 500 | J55: 3000 | K55: =(J55-I55)/J55*100 -> 83.333333 | L55: =J55-I55 -> 2500 | N55: =I55 -> 500 | O55: =J55 -> 3000 | P55: =N55 -> 500 | Q55: =O55 -> 3000
A56: MT | B56: =IF(A55=A56,B55+1,1) -> 49 | C56: =IF(A55=A56,C55,C55+1) -> 2 | D56: MT2049 | E56: MEDIA TANAM | F56: MEDIA TANAM | G56: TANAH SUBUR 1/4 | I56: 1000 | J56: 3000 | K56: =(J56-I56)/J56*100 -> 66.666667 | L56: =J56-I56 -> 2000 | N56: 1000 | O56: 3000 | P56: =N56 -> 1000 | Q56: =O56 -> 3000
A57: MT | B57: =IF(A56=A57,B56+1,1) -> 50 | C57: =IF(A56=A57,C56,C56+1) -> 2 | D57: MT2050 | E57: MEDIA TANAM | F57: MEDIA TANAM | G57: TANAH SUBUR 10KG BINTANG TANI | I57: 6000 | J57: 10000 | K57: =(J57-I57)/J57*100 -> 40 | L57: =J57-I57 -> 4000 | M57: BINTANG TANI | N57: 6000 | O57: 10000 | P57: =N57 -> 6000 | Q57: =O57 -> 10000
A58: MT | B58: =IF(A57=A58,B57+1,1) -> 51 | C58: =IF(A57=A58,C57,C57+1) -> 2 | D58: MT2051 | E58: MEDIA TANAM | F58: MEDIA TANAM | G58: TANAH SUBUR 10KG SIMANTRI | I58: 6000 | J58: 10000 | K58: =(J58-I58)/J58*100 -> 40 | L58: =J58-I58 -> 4000 | N58: 6000 | O58: 10000 | P58: =N58 -> 6000 | Q58: =O58 -> 10000
A59: MT | B59: =IF(A58=A59,B58+1,1) -> 52 | C59: =IF(A58=A59,C58,C58+1) -> 2 | D59: MT2052 | E59: MEDIA TANAM | F59: MEDIA TANAM | G59: TANAH SUBUR 1KG BINTANG TANI | I59: =6000/5 -> 1200 | J59: 3000 | K59: =(J59-I59)/J59*100 -> 60 | L59: =J59-I59 -> 1800 | N59: =I59 -> 1200 | O59: =J59 -> 3000 | P59: =N59 -> 1200 | Q59: =O59 -> 3000
A60: MT | B60: =IF(A59=A60,B59+1,1) -> 53 | C60: =IF(A59=A60,C59,C59+1) -> 2 | D60: MT2053 | E60: MEDIA TANAM | F60: MEDIA TANAM | G60: TANAH SUBUR 25KG BINTANG TANI | I60: 15000 | J60: 25000 | K60: =(J60-I60)/J60*100 -> 40 | L60: =J60-I60 -> 10000 | M60: BINTANG TANI | N60: 15000 | O60: 25000 | P60: =N60 -> 15000 | Q60: =O60 -> 25000
A61: PL | B61: =IF(A60=A61,B60+1,1) -> 1 | C61: =IF(A60=A61,C60,C60+1) -> 3 | D61: PL3001 | E61: PERLENGKAPAN | F61: CATOK | G61: CATOK BONSAI IMPORT 21CM COKLAT | I61: 176500 | J61: 250000 | K61: =(J61-I61)/J61*100 -> 29.4 | L61: =J61-I61 -> 73500 | M61: SHOPEE | N61: 176500 | O61: 250000 | P61: =N61 -> 176500 | Q61: =O61 -> 250000
A62: PL | B62: =IF(A61=A62,B61+1,1) -> 2 | C62: =IF(A61=A62,C61,C61+1) -> 3 | D62: PL3002 | E62: PERLENGKAPAN | F62: CATOK | G62: CATOK BONSAI IMPORT 21CM MIRING | I62: 212000 | J62: 265000 | K62: =(J62-I62)/J62*100 -> 20 | L62: =J62-I62 -> 53000 | M62: SHOPEE | N62: 212000 | O62: 265000 | P62: 235000 | Q62: =O62 -> 265000
A63: PL | B63: =IF(A62=A63,B62+1,1) -> 3 | C63: =IF(A62=A63,C62,C62+1) -> 3 | D63: PL3003 | E63: PERLENGKAPAN | F63: GUNTING | G63: CATOK BONSAI IMPORT 21CM HIJAU | I63: 214500 | J63: 265000 | K63: =(J63-I63)/J63*100 -> 19.056604 | L63: =J63-I63 -> 50500 | M63: SHOPEE | N63: 214500 | O63: 265000 | P63: 235000 | Q63: =O63 -> 265000
A64: PL | B64: =IF(A63=A64,B63+1,1) -> 4 | C64: =IF(A63=A64,C63,C63+1) -> 3 | D64: PL3004 | E64: PERLENGKAPAN | F64: GUNTING | G64: CATOK BONSAI LOKAL 21CM | I64: 38500 | J64: 65000 | K64: =(J64-I64)/J64*100 -> 40.769231 | L64: =J64-I64 -> 26500 | M64: SHOPEE | N64: 38500 | O64: 65000 | P64: =N64 -> 38500 | Q64: =O64 -> 65000
A65: PL | B65: =IF(A64=A65,B64+1,1) -> 5 | C65: =IF(A64=A65,C64,C64+1) -> 3 | D65: PL3005 | E65: PERLENGKAPAN | F65: GUNTING | G65: GUNTING DAHAN/STEK FUKUDA | I65: 60500 | J65: 85000 | K65: =(J65-I65)/J65*100 -> 28.823529 | L65: =J65-I65 -> 24500 | M65: SHOPEE | N65: 60500 | O65: 85000 | P65: =N65 -> 60500 | Q65: =O65 -> 85000
A66: PL | B66: =IF(A65=A66,B65+1,1) -> 6 | C66: =IF(A65=A66,C65,C65+1) -> 3 | D66: PL3006 | E66: PERLENGKAPAN | F66: GUNTING | G66: GUNTING DAHAN/STEK MERAH/HIJAU | I66: 10000 | J66: 20000 | K66: =(J66-I66)/J66*100 -> 50 | L66: =J66-I66 -> 10000 | M66: SHOPEE | N66: 10000 | O66: 20000 | P66: =N66 -> 10000 | Q66: =O66 -> 20000
A67: PL | B67: =IF(A66=A67,B66+1,1) -> 7 | C67: =IF(A66=A67,C66,C66+1) -> 3 | D67: PL3007 | E67: PERLENGKAPAN | F67: GUNTING | G67: GUNTING DAHAN/STEK PUTIH | I67: 20000 | J67: 35000 | K67: =(J67-I67)/J67*100 -> 42.857143 | L67: =J67-I67 -> 15000 | M67: SHOPEE | N67: 20000 | O67: 35000 | P67: =N67 -> 20000 | Q67: =O67 -> 35000
A68: PL | B68: =IF(A67=A68,B67+1,1) -> 8 | C68: =IF(A67=A68,C67,C67+1) -> 3 | D68: PL3008 | E68: PERLENGKAPAN | F68: GUNTING | G68: GUNTING DAHAN/STEK WIPRO | I68: 105104 | J68: 125000 | K68: =(J68-I68)/J68*100 -> 15.9168 | L68: =J68-I68 -> 19896 | M68: SHOPEE | N68: 105104 | O68: 135000 | P68: =N68 -> 105104 | Q68: =O68 -> 135000
A69: PL | B69: =IF(A68=A69,B68+1,1) -> 9 | C69: =IF(A68=A69,C68,C68+1) -> 3 | D69: PL3009 | E69: PERLENGKAPAN | F69: GUNTING | G69: GUNTING PRUNING HIJAU-KUNING 16CM | I69: 16000 | J69: 45000 | K69: =(J69-I69)/J69*100 -> 64.444444 | L69: =J69-I69 -> 29000 | M69: SHOPEE | N69: 16000 | O69: 45000 | P69: =N69 -> 16000 | Q69: =O69 -> 45000
A70: PL | B70: =IF(A69=A70,B69+1,1) -> 10 | C70: =IF(A69=A70,C69,C69+1) -> 3 | D70: PL3010 | E70: PERLENGKAPAN | F70: GUNTING | G70: GUNTING PRUNING HIJAU-KUNING 21CM NO. 2110 | I70: 48500 | J70: 70000 | K70: =(J70-I70)/J70*100 -> 30.714286 | L70: =J70-I70 -> 21500 | M70: SHOPEE | N70: 48500 | O70: 70000 | P70: =N70 -> 48500 | Q70: =O70 -> 70000
A71: PL | B71: =IF(A70=A71,B70+1,1) -> 11 | C71: =IF(A70=A71,C70,C70+1) -> 3 | D71: PL3011 | E71: PERLENGKAPAN | F71: GUNTING | G71: GUNTING PRUNING IMPORT 12.5CM NO 4104 | I71: 50000 | J71: 60000 | K71: =(J71-I71)/J71*100 -> 16.666667 | L71: =J71-I71 -> 10000 | M71: SHOPEE | N71: 50000 | O71: 60000 | P71: =N71 -> 50000 | Q71: =O71 -> 60000
A72: PL | B72: =IF(A71=A72,B71+1,1) -> 12 | C72: =IF(A71=A72,C71,C71+1) -> 3 | D72: PL3012 | E72: PERLENGKAPAN | F72: GUNTING | G72: GUNTING PRUNING IMPORT 15.3CM NO 4103 | I72: 60000 | J72: 70000 | K72: =(J72-I72)/J72*100 -> 14.285714 | L72: =J72-I72 -> 10000 | M72: SHOPEE | N72: 60000 | O72: 70000 | P72: =N72 -> 60000 | Q72: =O72 -> 70000
A73: PL | B73: =IF(A72=A73,B72+1,1) -> 13 | C73: =IF(A72=A73,C72,C72+1) -> 3 | D73: PL3013 | E73: PERLENGKAPAN | F73: GUNTING | G73: GUNTING PRUNING IMPORT 17.5CM NO 4102 | I73: 60000 | J73: 80000 | K73: =(J73-I73)/J73*100 -> 25 | L73: =J73-I73 -> 20000 | M73: SHOPEE | N73: 60000 | O73: 80000 | P73: =N73 -> 60000 | Q73: =O73 -> 80000
A74: PL | B74: =IF(A73=A74,B73+1,1) -> 14 | C74: =IF(A73=A74,C73,C73+1) -> 3 | D74: PL3014 | E74: PERLENGKAPAN | F74: GUNTING | G74: GUNTING PRUNING IMPORT 19.5CM NO 4101 | I74: 70000 | J74: 90000 | K74: =(J74-I74)/J74*100 -> 22.222222 | L74: =J74-I74 -> 20000 | M74: SHOPEE | N74: 70000 | O74: 90000 | P74: =N74 -> 70000 | Q74: =O74 -> 90000
A75: PL | B75: =IF(A74=A75,B74+1,1) -> 15 | C75: =IF(A74=A75,C74,C74+1) -> 3 | D75: PL3015 | E75: PERLENGKAPAN | F75: GUNTING | G75: GUNTING PRUNING IMPORT MELENGKUNG 12CM 3009-W | I75: 28000 | J75: 45000 | K75: =(J75-I75)/J75*100 -> 37.777778 | L75: =J75-I75 -> 17000 | N75: 28000 | O75: 45000 | P75: =N75 -> 28000 | Q75: =O75 -> 45000
A76: PL | B76: =IF(A75=A76,B75+1,1) -> 16 | C76: =IF(A75=A76,C75,C75+1) -> 3 | D76: PL3016 | E76: PERLENGKAPAN | F76: GUNTING | G76: GUNTING PRUNING LANCIP FURANO KUNING | I76: 19600 | J76: 35000 | K76: =(J76-I76)/J76*100 -> 44 | L76: =J76-I76 -> 15400 | N76: 19600 | O76: 35000 | P76: =N76 -> 19600 | Q76: =O76 -> 35000
A77: PL | B77: =IF(A76=A77,B76+1,1) -> 17 | C77: =IF(A76=A77,C76,C76+1) -> 3 | D77: PL3017 | E77: PERLENGKAPAN | F77: GUNTING | G77: GUNTING PRUNING LANCIP MERAH 19CM | I77: 18000 | J77: 30000 | K77: =(J77-I77)/J77*100 -> 40 | L77: =J77-I77 -> 12000 | M77: SHOPEE | N77: 18000 | O77: 30000 | P77: =N77 -> 18000 | Q77: =O77 -> 30000
A78: PL | B78: =IF(A77=A78,B77+1,1) -> 18 | C78: =IF(A77=A78,C77,C77+1) -> 3 | D78: PL3018 | E78: PERLENGKAPAN | F78: GUNTING | G78: GUNTING PRUNING LANCIP MERAH 21CM | I78: 20000 | J78: 35000 | K78: =(J78-I78)/J78*100 -> 42.857143 | L78: =J78-I78 -> 15000 | M78: SHOPEE | N78: 20000 | O78: 35000 | P78: =N78 -> 20000 | Q78: =O78 -> 35000
A79: PL | B79: =IF(A78=A79,B78+1,1) -> 19 | C79: =IF(A78=A79,C78,C78+1) -> 3 | D79: PL3019 | E79: PERLENGKAPAN | F79: GUNTING | G79: GUNTING PRUNING MERAH HITAM 21CM | I79: 32000 | J79: 65000 | K79: =(J79-I79)/J79*100 -> 50.769231 | L79: =J79-I79 -> 33000 | M79: SHOPEE | N79: 32000 | O79: 65000 | P79: =N79 -> 32000 | Q79: =O79 -> 65000
A80: PL | B80: =IF(A79=A80,B79+1,1) -> 20 | C80: =IF(A79=A80,C79,C79+1) -> 3 | D80: PL3020 | E80: PERLENGKAPAN | F80: GUNTING | G80: GUNTING RUMPUT GAGANG KAYU | I80: 80000 | J80: 100000 | K80: =(J80-I80)/J80*100 -> 20 | L80: =J80-I80 -> 20000 | M80: TRIA GARDEN | N80: =I80 -> 80000 | O80: =J80 -> 100000 | P80: =N80 -> 80000 | Q80: =O80 -> 100000
A81: PL | B81: =IF(A80=A81,B80+1,1) -> 21 | C81: =IF(A80=A81,C80,C80+1) -> 3 | D81: PL3021 | E81: PERLENGKAPAN | F81: GUNTING | G81: GUNTING RUMPUT GAGANG PLASTIK | I81: 80000 | J81: 100000 | K81: =(J81-I81)/J81*100 -> 20 | L81: =J81-I81 -> 20000 | M81: TRIA GARDEN | N81: =I81 -> 80000 | O81: =J81 -> 100000 | P81: =N81 -> 80000 | Q81: =O81 -> 100000
A82: PL | B82: =IF(A81=A82,B81+1,1) -> 22 | C82: =IF(A81=A82,C81,C81+1) -> 3 | D82: PL3022 | E82: PERLENGKAPAN | F82: GUNTING | G82: GUNTING STEK HITAM KUNING | I82: 30000 | J82: 65000 | K82: =(J82-I82)/J82*100 -> 53.846154 | L82: =J82-I82 -> 35000 | M82: SHOPEE | N82: =I82 -> 30000 | O82: =J82 -> 65000 | P82: =N82 -> 30000 | Q82: =O82 -> 65000
A83: PL | B83: =IF(A82=A83,B82+1,1) -> 23 | C83: =IF(A82=A83,C82,C82+1) -> 3 | D83: PL3023 | E83: PERLENGKAPAN | F83: KAWAT | G83: KAWAT BONSAI COKELAT NO.2 | I83: 122000 | J83: 140000 | K83: =(J83-I83)/J83*100 -> 12.857143 | L83: =J83-I83 -> 18000 | M83: TRIA GARDEN | N83: 122000 | O83: 140000 | P83: =N83 -> 122000 | Q83: =O83 -> 140000
A84: PL | B84: =IF(A83=A84,B83+1,1) -> 24 | C84: =IF(A83=A84,C83,C83+1) -> 3 | D84: PL3024 | E84: PERLENGKAPAN | F84: KAWAT | G84: KAWAT BONSAI COKELAT NO.3 | I84: 122000 | J84: 140000 | K84: =(J84-I84)/J84*100 -> 12.857143 | L84: =J84-I84 -> 18000 | M84: TRIA GARDEN | N84: 122000 | O84: 140000 | P84: =N84 -> 122000 | Q84: =O84 -> 140000
A85: PL | B85: =IF(A84=A85,B84+1,1) -> 25 | C85: =IF(A84=A85,C84,C84+1) -> 3 | D85: PL3025 | E85: PERLENGKAPAN | F85: KAWAT | G85: KAWAT BONSAI HITAM NO.1 | I85: 122000 | J85: 140000 | K85: =(J85-I85)/J85*100 -> 12.857143 | L85: =J85-I85 -> 18000 | M85: TRIA GARDEN | N85: 122000 | O85: 140000 | P85: =N85 -> 122000 | Q85: =O85 -> 140000
A86: PL | B86: =IF(A85=A86,B85+1,1) -> 26 | C86: =IF(A85=A86,C85,C85+1) -> 3 | D86: PL3026 | E86: PERLENGKAPAN | F86: KAWAT | G86: KAWAT BONSAI HITAM NO.1 ECERAN | I86: 407 | J86: 750 | K86: =(J86-I86)/J86*100 -> 45.733333 | L86: =J86-I86 -> 343 | M86: TRIA GARDEN | N86: 407 | O86: 750 | P86: =N86 -> 407 | Q86: =O86 -> 750
A87: PL | B87: =IF(A86=A87,B86+1,1) -> 27 | C87: =IF(A86=A87,C86,C86+1) -> 3 | D87: PL3027 | E87: PERLENGKAPAN | F87: KAWAT | G87: KAWAT BONSAI HITAM NO.2 | I87: 122000 | J87: 140000 | K87: =(J87-I87)/J87*100 -> 12.857143 | L87: =J87-I87 -> 18000 | M87: TRIA GARDEN | N87: 122000 | O87: 140000 | P87: =N87 -> 122000 | Q87: =O87 -> 140000
A88: PL | B88: =IF(A87=A88,B87+1,1) -> 28 | C88: =IF(A87=A88,C87,C87+1) -> 3 | D88: PL3028 | E88: PERLENGKAPAN | F88: KAWAT | G88: KAWAT BONSAI HITAM NO.2 ECERAN | I88: 1220 | J88: 2000 | K88: =(J88-I88)/J88*100 -> 39 | L88: =J88-I88 -> 780 | M88: TRIA GARDEN | N88: 1220 | O88: 2000 | P88: =N88 -> 1220 | Q88: =O88 -> 2000
A89: PL | B89: =IF(A88=A89,B88+1,1) -> 29 | C89: =IF(A88=A89,C88,C88+1) -> 3 | D89: PL3029 | E89: PERLENGKAPAN | F89: KAWAT | G89: KAWAT BONSAI HITAM NO.3 | I89: 122000 | J89: 140000 | K89: =(J89-I89)/J89*100 -> 12.857143 | L89: =J89-I89 -> 18000 | M89: TRIA GARDEN | N89: 122000 | O89: 140000 | P89: =N89 -> 122000 | Q89: =O89 -> 140000
A90: PL | B90: =IF(A89=A90,B89+1,1) -> 30 | C90: =IF(A89=A90,C89,C89+1) -> 3 | D90: PL3030 | E90: PERLENGKAPAN | F90: KAWAT | G90: KAWAT BONSAI HITAM NO.3 ECERAN | I90: 3050 | J90: 4500 | K90: =(J90-I90)/J90*100 -> 32.222222 | L90: =J90-I90 -> 1450 | M90: TRIA GARDEN | N90: 3050 | O90: 4500 | P90: =N90 -> 3050 | Q90: =O90 -> 4500
A91: PL | B91: =IF(A90=A91,B90+1,1) -> 31 | C91: =IF(A90=A91,C90,C90+1) -> 3 | D91: PL3031 | E91: PERLENGKAPAN | F91: KAWAT | G91: KAWAT BONSAI HITAM NO.4 | I91: 122000 | J91: 140000 | K91: =(J91-I91)/J91*100 -> 12.857143 | L91: =J91-I91 -> 18000 | M91: TRIA GARDEN | N91: 122000 | O91: 140000 | P91: =N91 -> 122000 | Q91: =O91 -> 140000
A92: PL | B92: =IF(A91=A92,B91+1,1) -> 32 | C92: =IF(A91=A92,C91,C91+1) -> 3 | D92: PL3032 | E92: PERLENGKAPAN | F92: KAWAT | G92: KAWAT BONSAI HITAM NO.4 ECERAN | I92: 6100 | J92: 7500 | K92: =(J92-I92)/J92*100 -> 18.666667 | L92: =J92-I92 -> 1400 | M92: TRIA GARDEN | N92: 6100 | O92: 7500 | P92: =N92 -> 6100 | Q92: =O92 -> 7500
A93: PL | B93: =IF(A92=A93,B92+1,1) -> 33 | C93: =IF(A92=A93,C92,C92+1) -> 3 | D93: PL3033 | E93: PERLENGKAPAN | F93: KAWAT | G93: KAWAT BONSAI HITAM NO.5 | I93: 122000 | J93: 140000 | K93: =(J93-I93)/J93*100 -> 12.857143 | L93: =J93-I93 -> 18000 | M93: TRIA GARDEN | N93: 122000 | O93: 140000 | P93: =N93 -> 122000 | Q93: =O93 -> 140000
A94: PL | B94: =IF(A93=A94,B93+1,1) -> 34 | C94: =IF(A93=A94,C93,C93+1) -> 3 | D94: PL3034 | E94: PERLENGKAPAN | F94: KAWAT | G94: KAWAT BONSAI HITAM NO.5 ECERAN | I94: 10167 | J94: 11500 | K94: =(J94-I94)/J94*100 -> 11.591304 | L94: =J94-I94 -> 1333 | M94: TRIA GARDEN | N94: 10167 | O94: 11500 | P94: =N94 -> 10167 | Q94: =O94 -> 11500
... A114: PL | B114: =IF(A113=A114,B113+1,1) -> 54 | C114: =IF(A113=A114,C113,C113+1) -> 3 | D114: PL3054 | E114: PERLENGKAPAN | F114: KAWAT | G114: KAWAT BONSAI SILVER NO.6 ECERAN | I114: 8000 | J114: 10000 | K114: =(J114-I114)/J114*100 -> 20 | L114: =J114-I114 -> 2000 | M114: TRIA GARDEN | N114: 8000 | O114: 10000 | P114: =N114 -> 8000 | Q114: =O114 -> 10000
A115: PL | B115: =IF(A114=A115,B114+1,1) -> 55 | C115: =IF(A114=A115,C114,C114+1) -> 3 | D115: PL3055 | E115: PERLENGKAPAN | F115: PERLENGKAPAN LAIN | G115: AJIR 11X1500MM | J115: 13000 | K115: =(J115-I115)/J115*100 -> 100 | L115: =J115-I115 -> 13000 | M115: TRIA GARDEN | N115: =I115 | O115: =J115 -> 13000 | P115: =N115 | Q115: =O115 -> 13000
A116: PL | B116: =IF(A115=A116,B115+1,1) -> 56 | C116: =IF(A115=A116,C115,C115+1) -> 3 | D116: PL3056 | E116: PERLENGKAPAN | F116: PERLENGKAPAN LAIN | G116: AJIR 8X1200MM | I116: 7500 | J116: 9500 | K116: =(J116-I116)/J116*100 -> 21.052632 | L116: =J116-I116 -> 2000 | N116: 7500 | O116: 9500 | P116: =N116 -> 7500 | Q116: =O116 -> 9500
A117: PL | B117: =IF(A116=A117,B116+1,1) -> 57 | C117: =IF(A116=A117,C116,C116+1) -> 3 | D117: PL3057 | E117: PERLENGKAPAN | F117: PERLENGKAPAN LAIN | G117: AJIR 8X750MM | I117: 4500 | J117: 6000 | K117: =(J117-I117)/J117*100 -> 25 | L117: =J117-I117 -> 1500 | M117: TRIA GARDEN | N117: 4500 | O117: 6000 | P117: =N117 -> 4500 | Q117: =O117 -> 6000
A118: PL | B118: =IF(A117=A118,B117+1,1) -> 58 | C118: =IF(A117=A118,C117,C117+1) -> 3 | D118: PL3058 | E118: PERLENGKAPAN | F118: PERLENGKAPAN LAIN | G118: AJIR 8X900MM | I118: 5500 | J118: 7000 | K118: =(J118-I118)/J118*100 -> 21.428571 | L118: =J118-I118 -> 1500 | N118: 5500 | O118: 7000 | P118: =N118 -> 5500 | Q118: =O118 -> 7000
A119: PL | B119: =IF(A118=A119,B118+1,1) -> 59 | C119: =IF(A118=A119,C118,C118+1) -> 3 | D119: PL3059 | E119: PERLENGKAPAN | F119: PERLENGKAPAN LAIN | G119: BATU ALAM PUTIH 34 | I119: 55000 | J119: 65000 | K119: =(J119-I119)/J119*100 -> 15.384615 | L119: =J119-I119 -> 10000 | N119: 55000 | O119: 70000 | P119: =N119 -> 55000 | Q119: =O119 -> 70000
A120: PL | B120: =IF(A119=A120,B119+1,1) -> 60 | C120: =IF(A119=A120,C119,C119+1) -> 3 | D120: PL3060 | E120: PERLENGKAPAN | F120: PERLENGKAPAN LAIN | G120: BATU PUTIH BESAR | I120: 3300 | J120: 5000 | K120: =(J120-I120)/J120*100 -> 34 | L120: =J120-I120 -> 1700 | N120: 3300 | O120: 5000 | P120: =N120 -> 3300 | Q120: =O120 -> 5000
A121: PL | B121: =IF(A120=A121,B120+1,1) -> 61 | C121: =IF(A120=A121,C120,C120+1) -> 3 | D121: PL3061 | E121: PERLENGKAPAN | F121: PERLENGKAPAN LAIN | G121: BATU PUTIH KECIL | J121: 10000 | K121: =(J121-I121)/J121*100 -> 100 | L121: =J121-I121 -> 10000 | O121: 10000 | P121: =N121 | Q121: =O121 -> 10000
...

Sheet Sales Summary
A2: SALES SUMMARY PER DAY
A4: Date | B4: Total Sales | C4: Margin | D4: Cash | E4: Transfer | F4: Online | G4: Instant | H4: Customer | I4: MT1029
D5: C | E5: T | F5: O | G5: I
A6: 01/02/26 | B6: =SUMIF('Daily Sales'!A:L,A6,'Daily Sales'!L:L) -> 366000 | C6: =SUMIF('Daily Sales'!A:N,A6,'Daily Sales'!N:N) -> 156490 | D6: =SUMIF('Daily Sales'!G:L,$D$5&A6,'Daily Sales'!L:L) -> 276000 | E6: =SUMIF('Daily Sales'!G:L,$E$5&A6,'Daily Sales'!L:L) -> 0 | F6: =SUMIF('Daily Sales'!G:L,$F$5&A6,'Daily Sales'!L:L) -> 80000 | G6: =SUMIF('Daily Sales'!G:L,$G$5&A6,'Daily Sales'!L:L) -> 10000 | H6: =SUMIF('Daily Sales'!A:D,A6,'Daily Sales'!D:D) -> 14 | I6: =SUMIF('Daily Sales'!F:F,A6&$I$4,'Daily Sales'!I:I) -> 0
A7: 02/02/26 | B7: =SUMIF('Daily Sales'!A:L,A7,'Daily Sales'!L:L) -> 400250 | C7: =SUMIF('Daily Sales'!A:N,A7,'Daily Sales'!N:N) -> 107630 | D7: =SUMIF('Daily Sales'!G:L,$D$5&A7,'Daily Sales'!L:L) -> 109000 | E7: =SUMIF('Daily Sales'!G:L,$E$5&A7,'Daily Sales'!L:L) -> 0 | F7: =SUMIF('Daily Sales'!G:L,$F$5&A7,'Daily Sales'!L:L) -> 213250 | G7: =SUMIF('Daily Sales'!G:L,$G$5&A7,'Daily Sales'!L:L) -> 78000 | H7: =SUMIF('Daily Sales'!A:D,A7,'Daily Sales'!D:D) -> 9 | I7: =SUMIF('Daily Sales'!F:F,A7&$I$4,'Daily Sales'!I:I) -> 0
A8: 03/02/26 | B8: =SUMIF('Daily Sales'!A:L,A8,'Daily Sales'!L:L) -> 370000 | C8: =SUMIF('Daily Sales'!A:N,A8,'Daily Sales'!N:N) -> 161722 | D8: =SUMIF('Daily Sales'!G:L,$D$5&A8,'Daily Sales'!L:L) -> 120000 | E8: =SUMIF('Daily Sales'!G:L,$E$5&A8,'Daily Sales'!L:L) -> 50000 | F8: =SUMIF('Daily Sales'!G:L,$F$5&A8,'Daily Sales'!L:L) -> 128000 | G8: =SUMIF('Daily Sales'!G:L,$G$5&A8,'Daily Sales'!L:L) -> 72000 | H8: =SUMIF('Daily Sales'!A:D,A8,'Daily Sales'!D:D) -> 12 | I8: =SUMIF('Daily Sales'!F:F,A8&$I$4,'Daily Sales'!I:I) -> 0
A9: 04/02/26 | B9: =SUMIF('Daily Sales'!A:L,A9,'Daily Sales'!L:L) -> 478500 | C9: =SUMIF('Daily Sales'!A:N,A9,'Daily Sales'!N:N) -> 169028 | D9: =SUMIF('Daily Sales'!G:L,$D$5&A9,'Daily Sales'!L:L) -> 308000 | E9: =SUMIF('Daily Sales'!G:L,$E$5&A9,'Daily Sales'!L:L) -> 60000 | F9: =SUMIF('Daily Sales'!G:L,$F$5&A9,'Daily Sales'!L:L) -> 75500 | G9: =SUMIF('Daily Sales'!G:L,$G$5&A9,'Daily Sales'!L:L) -> 35000 | H9: =SUMIF('Daily Sales'!A:D,A9,'Daily Sales'!D:D) -> 12 | I9: =SUMIF('Daily Sales'!F:F,A9&$I$4,'Daily Sales'!I:I) -> 0
A10: 05/02/26 | B10: =SUMIF('Daily Sales'!A:L,A10,'Daily Sales'!L:L) -> 388750 | C10: =SUMIF('Daily Sales'!A:N,A10,'Daily Sales'!N:N) -> 139840 | D10: =SUMIF('Daily Sales'!G:L,$D$5&A10,'Daily Sales'!L:L) -> 202000 | E10: =SUMIF('Daily Sales'!G:L,$E$5&A10,'Daily Sales'!L:L) -> 48000 | F10: =SUMIF('Daily Sales'!G:L,$F$5&A10,'Daily Sales'!L:L) -> 138750 | G10: =SUMIF('Daily Sales'!G:L,$G$5&A10,'Daily Sales'!L:L) -> 0 | H10: =SUMIF('Daily Sales'!A:D,A10,'Daily Sales'!D:D) -> 10 | I10: =SUMIF('Daily Sales'!F:F,A10&$I$4,'Daily Sales'!I:I) -> 0
A11: 06/02/26 | B11: =SUMIF('Daily Sales'!A:L,A11,'Daily Sales'!L:L) -> 569750 | C11: =SUMIF('Daily Sales'!A:N,A11,'Daily Sales'!N:N) -> 215172 | D11: =SUMIF('Daily Sales'!G:L,$D$5&A11,'Daily Sales'!L:L) -> 245000 | E11: =SUMIF('Daily Sales'!G:L,$E$5&A11,'Daily Sales'!L:L) -> 35000 | F11: =SUMIF('Daily Sales'!G:L,$F$5&A11,'Daily Sales'!L:L) -> 279750 | G11: =SUMIF('Daily Sales'!G:L,$G$5&A11,'Daily Sales'!L:L) -> 10000 | H11: =SUMIF('Daily Sales'!A:D,A11,'Daily Sales'!D:D) -> 13 | I11: =SUMIF('Daily Sales'!F:F,A11&$I$4,'Daily Sales'!I:I) -> 0
A12: 07/02/26 | B12: =SUMIF('Daily Sales'!A:L,A12,'Daily Sales'!L:L) -> 603250 | C12: =SUMIF('Daily Sales'!A:N,A12,'Daily Sales'!N:N) -> 337430 | D12: =SUMIF('Daily Sales'!G:L,$D$5&A12,'Daily Sales'!L:L) -> 552000 | E12: =SUMIF('Daily Sales'!G:L,$E$5&A12,'Daily Sales'!L:L) -> 13000 | F12: =SUMIF('Daily Sales'!G:L,$F$5&A12,'Daily Sales'!L:L) -> 38250 | G12: =SUMIF('Daily Sales'!G:L,$G$5&A12,'Daily Sales'!L:L) -> 0 | H12: =SUMIF('Daily Sales'!A:D,A12,'Daily Sales'!D:D) -> 13 | I12: =SUMIF('Daily Sales'!F:F,A12&$I$4,'Daily Sales'!I:I) -> 0
A13: 08/02/26 | B13: =SUMIF('Daily Sales'!A:L,A13,'Daily Sales'!L:L) -> 668250 | C13: =SUMIF('Daily Sales'!A:N,A13,'Daily Sales'!N:N) -> 243133 | D13: =SUMIF('Daily Sales'!G:L,$D$5&A13,'Daily Sales'!L:L) -> 420000 | E13: =SUMIF('Daily Sales'!G:L,$E$5&A13,'Daily Sales'!L:L) -> 0 | F13: =SUMIF('Daily Sales'!G:L,$F$5&A13,'Daily Sales'!L:L) -> 33250 | G13: =SUMIF('Daily Sales'!G:L,$G$5&A13,'Daily Sales'!L:L) -> 215000 | H13: =SUMIF('Daily Sales'!A:D,A13,'Daily Sales'!D:D) -> 11 | I13: =SUMIF('Daily Sales'!F:F,A13&$I$4,'Daily Sales'!I:I) -> 0
A14: 09/02/26 | B14: =SUMIF('Daily Sales'!A:L,A14,'Daily Sales'!L:L) -> 551750 | C14: =SUMIF('Daily Sales'!A:N,A14,'Daily Sales'!N:N) -> 174586 | D14: =SUMIF('Daily Sales'!G:L,$D$5&A14,'Daily Sales'!L:L) -> 230000 | E14: =SUMIF('Daily Sales'!G:L,$E$5&A14,'Daily Sales'!L:L) -> 0 | F14: =SUMIF('Daily Sales'!G:L,$F$5&A14,'Daily Sales'!L:L) -> 321750 | G14: =SUMIF('Daily Sales'!G:L,$G$5&A14,'Daily Sales'!L:L) -> 0 | H14: =SUMIF('Daily Sales'!A:D,A14,'Daily Sales'!D:D) -> 9 | I14: =SUMIF('Daily Sales'!F:F,A14&$I$4,'Daily Sales'!I:I) -> 0
A15: 10/02/26 | B15: =SUMIF('Daily Sales'!A:L,A15,'Daily Sales'!L:L) -> 594500 | C15: =SUMIF('Daily Sales'!A:N,A15,'Daily Sales'!N:N) -> 211680 | D15: =SUMIF('Daily Sales'!G:L,$D$5&A15,'Daily Sales'!L:L) -> 386000 | E15: =SUMIF('Daily Sales'!G:L,$E$5&A15,'Daily Sales'!L:L) -> 131000 | F15: =SUMIF('Daily Sales'!G:L,$F$5&A15,'Daily Sales'!L:L) -> 57500 | G15: =SUMIF('Daily Sales'!G:L,$G$5&A15,'Daily Sales'!L:L) -> 20000 | H15: =SUMIF('Daily Sales'!A:D,A15,'Daily Sales'!D:D) -> 12 | I15: =SUMIF('Daily Sales'!F:F,A15&$I$4,'Daily Sales'!I:I) -> 0
A16: 11/02/26 | B16: =SUMIF('Daily Sales'!A:L,A16,'Daily Sales'!L:L) -> 563500 | C16: =SUMIF('Daily Sales'!A:N,A16,'Daily Sales'!N:N) -> 175710 | D16: =SUMIF('Daily Sales'!G:L,$D$5&A16,'Daily Sales'!L:L) -> 324000 | E16: =SUMIF('Daily Sales'!G:L,$E$5&A16,'Daily Sales'!L:L) -> 0 | F16: =SUMIF('Daily Sales'!G:L,$F$5&A16,'Daily Sales'!L:L) -> 191500 | G16: =SUMIF('Daily Sales'!G:L,$G$5&A16,'Daily Sales'!L:L) -> 48000 | H16: =SUMIF('Daily Sales'!A:D,A16,'Daily Sales'!D:D) -> 8 | I16: =SUMIF('Daily Sales'!F:F,A16&$I$4,'Daily Sales'!I:I) -> 0
A17: 12/02/26 | B17: =SUMIF('Daily Sales'!A:L,A17,'Daily Sales'!L:L) -> 768000 | C17: =SUMIF('Daily Sales'!A:N,A17,'Daily Sales'!N:N) -> 210500 | D17: =SUMIF('Daily Sales'!G:L,$D$5&A17,'Daily Sales'!L:L) -> 438000 | E17: =SUMIF('Daily Sales'!G:L,$E$5&A17,'Daily Sales'!L:L) -> 10000 | F17: =SUMIF('Daily Sales'!G:L,$F$5&A17,'Daily Sales'!L:L) -> 320000 | G17: =SUMIF('Daily Sales'!G:L,$G$5&A17,'Daily Sales'!L:L) -> 0 | H17: =SUMIF('Daily Sales'!A:D,A17,'Daily Sales'!D:D) -> 14 | I17: =SUMIF('Daily Sales'!F:F,A17&$I$4,'Daily Sales'!I:I) -> 0
... A36: 31/02/25 | B36: =SUMIF('Daily Sales'!A:L,A36,'Daily Sales'!L:L) -> 0 | C36: =SUMIF('Daily Sales'!A:N,A36,'Daily Sales'!N:N) -> 0 | D36: =SUMIF('Daily Sales'!G:L,$D$5&A36,'Daily Sales'!L:L) -> 0 | E36: =SUMIF('Daily Sales'!G:L,$E$5&A36,'Daily Sales'!L:L) -> 0 | F36: =SUMIF('Daily Sales'!G:L,$F$5&A36,'Daily Sales'!L:L) -> 0 | G36: =SUMIF('Daily Sales'!G:L,$G$5&A36,'Daily Sales'!L:L) -> 0 | H36: =SUMIF('Daily Sales'!A:D,A36,'Daily Sales'!D:D) -> 0 | I36: =SUMIF('Daily Sales'!F:F,A36&$I$4,'Daily Sales'!I:I) -> 0
A38: TOTAL | B38: =SUM(B5:B36) -> 13446500 | C38: =SUM(C5:C36) -> 4719545.4 | D38: =SUM(D5:D36) -> 8534500 | E38: =SUM(E5:E36) -> 821000 | F38: =SUM(F5:F36) -> 3255500 | G38: =SUM(G5:G36) -> 835500 | H38: =SUM(H5:H36) -> 278
A39: AVG | B39: =B38/31 -> 433758.06
B40: =B38/26 -> 517173.08 | C40: =C38/B38*100 -> 35.098691

Sheet Stock
A4: Code | B4: Category | C4: Sub Category | D4: NAME TAG TANAMAN | E4: Beginning | F4: 01/11/24 | G4: 02/11/24
A5: MT1001 | B5: MEDIA TANAM | C5: MEDIA TANAM | D5: =VLOOKUP(A5,Master!D:G,4,0) -> #N/A | E5: 0 | F5: =E5+ SUMIF('InOut Inv'!F:H,$F$4&A5,'InOut Inv'!H:H) - SUMIF('Daily Sales'!F:I,$F$4&A5,'Daily Sales'!I:I) -> 0 | G5: =F5+ SUMIF('InOut Inv'!G:I,$F$4&B5,'InOut Inv'!I:I) - SUMIF('Daily Sales'!G:J,$F$4&B5,'Daily Sales'!J:J) -> 0
A6: MT1002 | B6: MEDIA TANAM | C6: MEDIA TANAM | D6: =VLOOKUP(A6,Master!D:G,4,0) -> #N/A | E6: 5 | F6: =E6+ SUMIF('InOut Inv'!F:H,$F$4&A6,'InOut Inv'!H:H) - SUMIF('Daily Sales'!F:I,$F$4&A6,'Daily Sales'!I:I) -> 5 | G6: =F6+ SUMIF('InOut Inv'!G:I,$F$4&B6,'InOut Inv'!I:I) - SUMIF('Daily Sales'!G:J,$F$4&B6,'Daily Sales'!J:J) -> 5
A7: MT1003 | B7: MEDIA TANAM | C7: MEDIA TANAM | D7: =VLOOKUP(A7,Master!D:G,4,0) -> #N/A | E7: 12 | F7: =E7+ SUMIF('InOut Inv'!F:H,$F$4&A7,'InOut Inv'!H:H) - SUMIF('Daily Sales'!F:I,$F$4&A7,'Daily Sales'!I:I) -> 12 | G7: =F7+ SUMIF('InOut Inv'!G:I,$F$4&B7,'InOut Inv'!I:I) - SUMIF('Daily Sales'!G:J,$F$4&B7,'Daily Sales'!J:J) -> 12
A8: MT1004 | B8: MEDIA TANAM | C8: MEDIA TANAM | D8: =VLOOKUP(A8,Master!D:G,4,0) -> #N/A | E8: 5 | F8: =E8+ SUMIF('InOut Inv'!F:H,$F$4&A8,'InOut Inv'!H:H) - SUMIF('Daily Sales'!F:I,$F$4&A8,'Daily Sales'!I:I) -> 5 | G8: =F8+ SUMIF('InOut Inv'!G:I,$F$4&B8,'InOut Inv'!I:I) - SUMIF('Daily Sales'!G:J,$F$4&B8,'Daily Sales'!J:J) -> 5
A9: MT1005 | B9: MEDIA TANAM | C9: MEDIA TANAM | D9: =VLOOKUP(A9,Master!D:G,4,0) -> #N/A | E9: 0 | F9: =E9+ SUMIF('InOut Inv'!F:H,$F$4&A9,'InOut Inv'!H:H) - SUMIF('Daily Sales'!F:I,$F$4&A9,'Daily Sales'!I:I) -> 0 | G9: =F9+ SUMIF('InOut Inv'!G:I,$F$4&B9,'InOut Inv'!I:I) - SUMIF('Daily Sales'!G:J,$F$4&B9,'Daily Sales'!J:J) -> 0
A10: MT1006 | B10: MEDIA TANAM | C10: MEDIA TANAM | D10: =VLOOKUP(A10,Master!D:G,4,0) -> #N/A | E10: 1 | F10: =E10+ SUMIF('InOut Inv'!F:H,$F$4&A10,'InOut Inv'!H:H) - SUMIF('Daily Sales'!F:I,$F$4&A10,'Daily Sales'!I:I) -> 1 | G10: =F10+ SUMIF('InOut Inv'!G:I,$F$4&B10,'InOut Inv'!I:I) - SUMIF('Daily Sales'!G:J,$F$4&B10,'Daily Sales'!J:J) -> 1
A11: MT1007 | B11: MEDIA TANAM | C11: MEDIA TANAM | D11: =VLOOKUP(A11,Master!D:G,4,0) -> #N/A | E11: 3 | F11: =E11+ SUMIF('InOut Inv'!F:H,$F$4&A11,'InOut Inv'!H:H) - SUMIF('Daily Sales'!F:I,$F$4&A11,'Daily Sales'!I:I) -> 3 | G11: =F11+ SUMIF('InOut Inv'!G:I,$F$4&B11,'InOut Inv'!I:I) - SUMIF('Daily Sales'!G:J,$F$4&B11,'Daily Sales'!J:J) -> 3
A12: MT1008 | B12: MEDIA TANAM | C12: MEDIA TANAM | D12: =VLOOKUP(A12,Master!D:G,4,0) -> #N/A | F12: =E12+ SUMIF('InOut Inv'!F:H,$F$4&A12,'InOut Inv'!H:H) - SUMIF('Daily Sales'!F:I,$F$4&A12,'Daily Sales'!I:I) -> 0 | G12: =F12+ SUMIF('InOut Inv'!G:I,$F$4&B12,'InOut Inv'!I:I) - SUMIF('Daily Sales'!G:J,$F$4&B12,'Daily Sales'!J:J) -> 0
A13: MT1009 | B13: MEDIA TANAM | C13: MEDIA TANAM | D13: =VLOOKUP(A13,Master!D:G,4,0) -> #N/A | F13: =E13+ SUMIF('InOut Inv'!F:H,$F$4&A13,'InOut Inv'!H:H) - SUMIF('Daily Sales'!F:I,$F$4&A13,'Daily Sales'!I:I) -> 0 | G13: =F13+ SUMIF('InOut Inv'!G:I,$F$4&B13,'InOut Inv'!I:I) - SUMIF('Daily Sales'!G:J,$F$4&B13,'Daily Sales'!J:J) -> 0
A14: MT1010 | B14: MEDIA TANAM | C14: MEDIA TANAM | D14: =VLOOKUP(A14,Master!D:G,4,0) -> #N/A | E14: 0 | F14: =E14+ SUMIF('InOut Inv'!F:H,$F$4&A14,'InOut Inv'!H:H) - SUMIF('Daily Sales'!F:I,$F$4&A14,'Daily Sales'!I:I) -> 0 | G14: =F14+ SUMIF('InOut Inv'!G:I,$F$4&B14,'InOut Inv'!I:I) - SUMIF('Daily Sales'!G:J,$F$4&B14,'Daily Sales'!J:J) -> 0
A15: MT1011 | B15: MEDIA TANAM | C15: MEDIA TANAM | D15: =VLOOKUP(A15,Master!D:G,4,0) -> #N/A | E15: 3 | F15: =E15+ SUMIF('InOut Inv'!F:H,$F$4&A15,'InOut Inv'!H:H) - SUMIF('Daily Sales'!F:I,$F$4&A15,'Daily Sales'!I:I) -> 3 | G15: =F15+ SUMIF('InOut Inv'!G:I,$F$4&B15,'InOut Inv'!I:I) - SUMIF('Daily Sales'!G:J,$F$4&B15,'Daily Sales'!J:J) -> 3
A16: MT1012 | B16: MEDIA TANAM | C16: MEDIA TANAM | D16: =VLOOKUP(A16,Master!D:G,4,0) -> #N/A | E16: 8 | F16: =E16+ SUMIF('InOut Inv'!F:H,$F$4&A16,'InOut Inv'!H:H) - SUMIF('Daily Sales'!F:I,$F$4&A16,'Daily Sales'!I:I) -> 8 | G16: =F16+ SUMIF('InOut Inv'!G:I,$F$4&B16,'InOut Inv'!I:I) - SUMIF('Daily Sales'!G:J,$F$4&B16,'Daily Sales'!J:J) -> 8
A17: MT1013 | B17: MEDIA TANAM | C17: MEDIA TANAM | D17: =VLOOKUP(A17,Master!D:G,4,0) -> #N/A | E17: 2 | F17: =E17+ SUMIF('InOut Inv'!F:H,$F$4&A17,'InOut Inv'!H:H) - SUMIF('Daily Sales'!F:I,$F$4&A17,'Daily Sales'!I:I) -> 2 | G17: =F17+ SUMIF('InOut Inv'!G:I,$F$4&B17,'InOut Inv'!I:I) - SUMIF('Daily Sales'!G:J,$F$4&B17,'Daily Sales'!J:J) -> 2
A18: MT1014 | B18: MEDIA TANAM | C18: MEDIA TANAM | D18: =VLOOKUP(A18,Master!D:G,4,0) -> #N/A | E18: 2 | F18: =E18+ SUMIF('InOut Inv'!F:H,$F$4&A18,'InOut Inv'!H:H) - SUMIF('Daily Sales'!F:I,$F$4&A18,'Daily Sales'!I:I) -> 2 | G18: =F18+ SUMIF('InOut Inv'!G:I,$F$4&B18,'InOut Inv'!I:I) - SUMIF('Daily Sales'!G:J,$F$4&B18,'Daily Sales'!J:J) -> 2
A19: MT1015 | B19: MEDIA TANAM | C19: MEDIA TANAM | D19: =VLOOKUP(A19,Master!D:G,4,0) -> #N/A | E19: 17 | F19: =E19+ SUMIF('InOut Inv'!F:H,$F$4&A19,'InOut Inv'!H:H) - SUMIF('Daily Sales'!F:I,$F$4&A19,'Daily Sales'!I:I) -> 17 | G19: =F19+ SUMIF('InOut Inv'!G:I,$F$4&B19,'InOut Inv'!I:I) - SUMIF('Daily Sales'!G:J,$F$4&B19,'Daily Sales'!J:J) -> 17
A20: MT1016 | B20: MEDIA TANAM | C20: MEDIA TANAM | D20: =VLOOKUP(A20,Master!D:G,4,0) -> #N/A | E20: 9 | F20: =E20+ SUMIF('InOut Inv'!F:H,$F$4&A20,'InOut Inv'!H:H) - SUMIF('Daily Sales'!F:I,$F$4&A20,'Daily Sales'!I:I) -> 9 | G20: =F20+ SUMIF('InOut Inv'!G:I,$F$4&B20,'InOut Inv'!I:I) - SUMIF('Daily Sales'!G:J,$F$4&B20,'Daily Sales'!J:J) -> 9
A21: MT1017 | B21: MEDIA TANAM | C21: MEDIA TANAM | D21: =VLOOKUP(A21,Master!D:G,4,0) -> #N/A | E21: 0 | F21: =E21+ SUMIF('InOut Inv'!F:H,$F$4&A21,'InOut Inv'!H:H) - SUMIF('Daily Sales'!F:I,$F$4&A21,'Daily Sales'!I:I) -> 0 | G21: =F21+ SUMIF('InOut Inv'!G:I,$F$4&B21,'InOut Inv'!I:I) - SUMIF('Daily Sales'!G:J,$F$4&B21,'Daily Sales'!J:J) -> 0
A22: MT1018 | B22: MEDIA TANAM | C22: MEDIA TANAM | D22: =VLOOKUP(A22,Master!D:G,4,0) -> #N/A | E22: 0 | F22: =E22+ SUMIF('InOut Inv'!F:H,$F$4&A22,'InOut Inv'!H:H) - SUMIF('Daily Sales'!F:I,$F$4&A22,'Daily Sales'!I:I) -> 0 | G22: =F22+ SUMIF('InOut Inv'!G:I,$F$4&B22,'InOut Inv'!I:I) - SUMIF('Daily Sales'!G:J,$F$4&B22,'Daily Sales'!J:J) -> 0
A23: MT1019 | B23: MEDIA TANAM | C23: MEDIA TANAM | D23: =VLOOKUP(A23,Master!D:G,4,0) -> #N/A | E23: 4 | F23: =E23+ SUMIF('InOut Inv'!F:H,$F$4&A23,'InOut Inv'!H:H) - SUMIF('Daily Sales'!F:I,$F$4&A23,'Daily Sales'!I:I) -> 4 | G23: =F23+ SUMIF('InOut Inv'!G:I,$F$4&B23,'InOut Inv'!I:I) - SUMIF('Daily Sales'!G:J,$F$4&B23,'Daily Sales'!J:J) -> 4
A24: MT1020 | B24: MEDIA TANAM | C24: MEDIA TANAM | D24: =VLOOKUP(A24,Master!D:G,4,0) -> #N/A | E24: 0 | F24: =E24+ SUMIF('InOut Inv'!F:H,$F$4&A24,'InOut Inv'!H:H) - SUMIF('Daily Sales'!F:I,$F$4&A24,'Daily Sales'!I:I) -> 0 | G24: =F24+ SUMIF('InOut Inv'!G:I,$F$4&B24,'InOut Inv'!I:I) - SUMIF('Daily Sales'!G:J,$F$4&B24,'Daily Sales'!J:J) -> 0
A25: MT1021 | B25: MEDIA TANAM | C25: MEDIA TANAM | D25: =VLOOKUP(A25,Master!D:G,4,0) -> #N/A | E25: 3 | F25: =E25+ SUMIF('InOut Inv'!F:H,$F$4&A25,'InOut Inv'!H:H) - SUMIF('Daily Sales'!F:I,$F$4&A25,'Daily Sales'!I:I) -> 3 | G25: =F25+ SUMIF('InOut Inv'!G:I,$F$4&B25,'InOut Inv'!I:I) - SUMIF('Daily Sales'!G:J,$F$4&B25,'Daily Sales'!J:J) -> 3
... A39: MT1035 | B39: MEDIA TANAM | C39: MEDIA TANAM | D39: =VLOOKUP(A39,Master!D:G,4,0) -> #N/A | E39: 6 | F39: =E39+ SUMIF('InOut Inv'!F:H,$F$4&A39,'InOut Inv'!H:H) - SUMIF('Daily Sales'!F:I,$F$4&A39,'Daily Sales'!I:I) -> 6 | G39: =F39+ SUMIF('InOut Inv'!G:I,$F$4&B39,'InOut Inv'!I:I) - SUMIF('Daily Sales'!G:J,$F$4&B39,'Daily Sales'!J:J) -> 6
A40: MT1036 | B40: MEDIA TANAM | C40: MEDIA TANAM | D40: =VLOOKUP(A40,Master!D:G,4,0) -> #N/A | F40: =E40+ SUMIF('InOut Inv'!F:H,$F$4&A40,'InOut Inv'!H:H) - SUMIF('Daily Sales'!F:I,$F$4&A40,'Daily Sales'!I:I) -> 0 | G40: =F40+ SUMIF('InOut Inv'!G:I,$F$4&B40,'InOut Inv'!I:I) - SUMIF('Daily Sales'!G:J,$F$4&B40,'Daily Sales'!J:J) -> 0
A41: MT1037 | B41: MEDIA TANAM | C41: MEDIA TANAM | D41: =VLOOKUP(A41,Master!D:G,4,0) -> #N/A | F41: =E41+ SUMIF('InOut Inv'!F:H,$F$4&A41,'InOut Inv'!H:H) - SUMIF('Daily Sales'!F:I,$F$4&A41,'Daily Sales'!I:I) -> 0 | G41: =F41+ SUMIF('InOut Inv'!G:I,$F$4&B41,'InOut Inv'!I:I) - SUMIF('Daily Sales'!G:J,$F$4&B41,'Daily Sales'!J:J) -> 0
A42: MT1038 | B42: MEDIA TANAM | C42: MEDIA TANAM | D42: =VLOOKUP(A42,Master!D:G,4,0) -> #N/A | E42: 3 | F42: =E42+ SUMIF('InOut Inv'!F:H,$F$4&A42,'InOut Inv'!H:H) - SUMIF('Daily Sales'!F:I,$F$4&A42,'Daily Sales'!I:I) -> 3 | G42: =F42+ SUMIF('InOut Inv'!G:I,$F$4&B42,'InOut Inv'!I:I) - SUMIF('Daily Sales'!G:J,$F$4&B42,'Daily Sales'!J:J) -> 3
A43: PL1001 | B43: PERLENGKAPAN | C43: CATOK | D43: =VLOOKUP(A43,Master!D:G,4,0) -> #N/A | E43: 1 | F43: =E43+ SUMIF('InOut Inv'!F:H,$F$4&A43,'InOut Inv'!H:H) - SUMIF('Daily Sales'!F:I,$F$4&A43,'Daily Sales'!I:I) -> 1 | G43: =F43+ SUMIF('InOut Inv'!G:I,$F$4&B43,'InOut Inv'!I:I) - SUMIF('Daily Sales'!G:J,$F$4&B43,'Daily Sales'!J:J) -> 1
A44: PL1002 | B44: PERLENGKAPAN | C44: CATOK | D44: =VLOOKUP(A44,Master!D:G,4,0) -> #N/A | E44: 2 | F44: =E44+ SUMIF('InOut Inv'!F:H,$F$4&A44,'InOut Inv'!H:H) - SUMIF('Daily Sales'!F:I,$F$4&A44,'Daily Sales'!I:I) -> 2 | G44: =F44+ SUMIF('InOut Inv'!G:I,$F$4&B44,'InOut Inv'!I:I) - SUMIF('Daily Sales'!G:J,$F$4&B44,'Daily Sales'!J:J) -> 2
A45: PL2001 | B45: PERLENGKAPAN | C45: GUNTING | D45: =VLOOKUP(A45,Master!D:G,4,0) -> #N/A | E45: 2 | F45: =E45+ SUMIF('InOut Inv'!F:H,$F$4&A45,'InOut Inv'!H:H) - SUMIF('Daily Sales'!F:I,$F$4&A45,'Daily Sales'!I:I) -> 2 | G45: =F45+ SUMIF('InOut Inv'!G:I,$F$4&B45,'InOut Inv'!I:I) - SUMIF('Daily Sales'!G:J,$F$4&B45,'Daily Sales'!J:J) -> 2
A46: PL2002 | B46: PERLENGKAPAN | C46: GUNTING | D46: =VLOOKUP(A46,Master!D:G,4,0) -> #N/A | E46: 1 | F46: =E46+ SUMIF('InOut Inv'!F:H,$F$4&A46,'InOut Inv'!H:H) - SUMIF('Daily Sales'!F:I,$F$4&A46,'Daily Sales'!I:I) -> 1 | G46: =F46+ SUMIF('InOut Inv'!G:I,$F$4&B46,'InOut Inv'!I:I) - SUMIF('Daily Sales'!G:J,$F$4&B46,'Daily Sales'!J:J) -> 1
A47: PL2003 | B47: PERLENGKAPAN | C47: GUNTING | D47: =VLOOKUP(A47,Master!D:G,4,0) -> #N/A | E47: 2 | F47: =E47+ SUMIF('InOut Inv'!F:H,$F$4&A47,'InOut Inv'!H:H) - SUMIF('Daily Sales'!F:I,$F$4&A47,'Daily Sales'!I:I) -> 2 | G47: =F47+ SUMIF('InOut Inv'!G:I,$F$4&B47,'InOut Inv'!I:I) - SUMIF('Daily Sales'!G:J,$F$4&B47,'Daily Sales'!J:J) -> 2
A48: PL2004 | B48: PERLENGKAPAN | C48: GUNTING | D48: =VLOOKUP(A48,Master!D:G,4,0) -> #N/A | E48: 3 | F48: =E48+ SUMIF('InOut Inv'!F:H,$F$4&A48,'InOut Inv'!H:H) - SUMIF('Daily Sales'!F:I,$F$4&A48,'Daily Sales'!I:I) -> 3 | G48: =F48+ SUMIF('InOut Inv'!G:I,$F$4&B48,'InOut Inv'!I:I) - SUMIF('Daily Sales'!G:J,$F$4&B48,'Daily Sales'!J:J) -> 3
A49: PL2005 | B49: PERLENGKAPAN | C49: GUNTING | D49: =VLOOKUP(A49,Master!D:G,4,0) -> #N/A | E49: 2 | F49: =E49+ SUMIF('InOut Inv'!F:H,$F$4&A49,'InOut Inv'!H:H) - SUMIF('Daily Sales'!F:I,$F$4&A49,'Daily Sales'!I:I) -> 2 | G49: =F49+ SUMIF('InOut Inv'!G:I,$F$4&B49,'InOut Inv'!I:I) - SUMIF('Daily Sales'!G:J,$F$4&B49,'Daily Sales'!J:J) -> 2
A50: PL2006 | B50: PERLENGKAPAN | C50: GUNTING | D50: =VLOOKUP(A50,Master!D:G,4,0) -> #N/A | E50: 3 | F50: =E50+ SUMIF('InOut Inv'!F:H,$F$4&A50,'InOut Inv'!H:H) - SUMIF('Daily Sales'!F:I,$F$4&A50,'Daily Sales'!I:I) -> 3 | G50: =F50+ SUMIF('InOut Inv'!G:I,$F$4&B50,'InOut Inv'!I:I) - SUMIF('Daily Sales'!G:J,$F$4&B50,'Daily Sales'!J:J) -> 3
A51: PL2007 | B51: PERLENGKAPAN | C51: GUNTING | D51: =VLOOKUP(A51,Master!D:G,4,0) -> #N/A | E51: 4 | F51: =E51+ SUMIF('InOut Inv'!F:H,$F$4&A51,'InOut Inv'!H:H) - SUMIF('Daily Sales'!F:I,$F$4&A51,'Daily Sales'!I:I) -> 4 | G51: =F51+ SUMIF('InOut Inv'!G:I,$F$4&B51,'InOut Inv'!I:I) - SUMIF('Daily Sales'!G:J,$F$4&B51,'Daily Sales'!J:J) -> 4
A52: PL2008 | B52: PERLENGKAPAN | C52: GUNTING | D52: =VLOOKUP(A52,Master!D:G,4,0) -> #N/A | E52: 1 | F52: =E52+ SUMIF('InOut Inv'!F:H,$F$4&A52,'InOut Inv'!H:H) - SUMIF('Daily Sales'!F:I,$F$4&A52,'Daily Sales'!I:I) -> 1 | G52: =F52+ SUMIF('InOut Inv'!G:I,$F$4&B52,'InOut Inv'!I:I) - SUMIF('Daily Sales'!G:J,$F$4&B52,'Daily Sales'!J:J) -> 1
A53: PL2009 | B53: PERLENGKAPAN | C53: GUNTING | D53: =VLOOKUP(A53,Master!D:G,4,0) -> #N/A | E53: 3 | F53: =E53+ SUMIF('InOut Inv'!F:H,$F$4&A53,'InOut Inv'!H:H) - SUMIF('Daily Sales'!F:I,$F$4&A53,'Daily Sales'!I:I) -> 3 | G53: =F53+ SUMIF('InOut Inv'!G:I,$F$4&B53,'InOut Inv'!I:I) - SUMIF('Daily Sales'!G:J,$F$4&B53,'Daily Sales'!J:J) -> 3
... A98: PL4006 | B98: PERLENGKAPAN | C98: PERLENGKAPAN LAIN | D98: =VLOOKUP(A98,Master!D:G,4,0) -> #N/A | E98: 2 | F98: =E98+ SUMIF('InOut Inv'!F:H,$F$4&A98,'InOut Inv'!H:H) - SUMIF('Daily Sales'!F:I,$F$4&A98,'Daily Sales'!I:I) -> 2 | G98: =F98+ SUMIF('InOut Inv'!G:I,$F$4&B98,'InOut Inv'!I:I) - SUMIF('Daily Sales'!G:J,$F$4&B98,'Daily Sales'!J:J) -> 2
A99: PL4007 | B99: PERLENGKAPAN | C99: PERLENGKAPAN LAIN | D99: =VLOOKUP(A99,Master!D:G,4,0) -> #N/A | F99: =E99+ SUMIF('InOut Inv'!F:H,$F$4&A99,'InOut Inv'!H:H) - SUMIF('Daily Sales'!F:I,$F$4&A99,'Daily Sales'!I:I) -> 0 | G99: =F99+ SUMIF('InOut Inv'!G:I,$F$4&B99,'InOut Inv'!I:I) - SUMIF('Daily Sales'!G:J,$F$4&B99,'Daily Sales'!J:J) -> 0
A100: PL4008 | B100: PERLENGKAPAN | C100: PERLENGKAPAN LAIN | D100: =VLOOKUP(A100,Master!D:G,4,0) -> #N/A | E100: 0 | F100: =E100+ SUMIF('InOut Inv'!F:H,$F$4&A100,'InOut Inv'!H:H) - SUMIF('Daily Sales'!F:I,$F$4&A100,'Daily Sales'!I:I) -> 0 | G100: =F100+ SUMIF('InOut Inv'!G:I,$F$4&B100,'InOut Inv'!I:I) - SUMIF('Daily Sales'!G:J,$F$4&B100,'Daily Sales'!J:J) -> 0
A101: PL4009 | B101: PERLENGKAPAN | C101: PERLENGKAPAN LAIN | D101: =VLOOKUP(A101,Master!D:G,4,0) -> #N/A | E101: 0 | F101: =E101+ SUMIF('InOut Inv'!F:H,$F$4&A101,'InOut Inv'!H:H) - SUMIF('Daily Sales'!F:I,$F$4&A101,'Daily Sales'!I:I) -> 0 | G101: =F101+ SUMIF('InOut Inv'!G:I,$F$4&B101,'InOut Inv'!I:I) - SUMIF('Daily Sales'!G:J,$F$4&B101,'Daily Sales'!J:J) -> 0
A102: PL4010 | B102: PERLENGKAPAN | C102: PERLENGKAPAN LAIN | D102: =VLOOKUP(A102,Master!D:G,4,0) -> #N/A | E102: 83 | F102: =E102+ SUMIF('InOut Inv'!F:H,$F$4&A102,'InOut Inv'!H:H) - SUMIF('Daily Sales'!F:I,$F$4&A102,'Daily Sales'!I:I) -> 83 | G102: =F102+ SUMIF('InOut Inv'!G:I,$F$4&B102,'InOut Inv'!I:I) - SUMIF('Daily Sales'!G:J,$F$4&B102,'Daily Sales'!J:J) -> 83
A103: PL4011 | B103: PERLENGKAPAN | C103: PERLENGKAPAN LAIN | D103: =VLOOKUP(A103,Master!D:G,4,0) -> #N/A | E103: 94 | F103: =E103+ SUMIF('InOut Inv'!F:H,$F$4&A103,'InOut Inv'!H:H) - SUMIF('Daily Sales'!F:I,$F$4&A103,'Daily Sales'!I:I) -> 94 | G103: =F103+ SUMIF('InOut Inv'!G:I,$F$4&B103,'InOut Inv'!I:I) - SUMIF('Daily Sales'!G:J,$F$4&B103,'Daily Sales'!J:J) -> 94
A104: PL4012 | B104: PERLENGKAPAN | C104: PERLENGKAPAN LAIN | D104: =VLOOKUP(A104,Master!D:G,4,0) -> #N/A | E104: 12 | F104: =E104+ SUMIF('InOut Inv'!F:H,$F$4&A104,'InOut Inv'!H:H) - SUMIF('Daily Sales'!F:I,$F$4&A104,'Daily Sales'!I:I) -> 12 | G104: =F104+ SUMIF('InOut Inv'!G:I,$F$4&B104,'InOut Inv'!I:I) - SUMIF('Daily Sales'!G:J,$F$4&B104,'Daily Sales'!J:J) -> 12
A105: PL4013 | B105: PERLENGKAPAN | C105: PERLENGKAPAN LAIN | D105: =VLOOKUP(A105,Master!D:G,4,0) -> #N/A | E105: 5 | F105: =E105+ SUMIF('InOut Inv'!F:H,$F$4&A105,'InOut Inv'!H:H) - SUMIF('Daily Sales'!F:I,$F$4&A105,'Daily Sales'!I:I) -> 5 | G105: =F105+ SUMIF('InOut Inv'!G:I,$F$4&B105,'InOut Inv'!I:I) - SUMIF('Daily Sales'!G:J,$F$4&B105,'Daily Sales'!J:J) -> 5
A106: PL4014 | B106: PERLENGKAPAN | C106: PERLENGKAPAN LAIN | D106: =VLOOKUP(A106,Master!D:G,4,0) -> #N/A | E106: 1 | F106: =E106+ SUMIF('InOut Inv'!F:H,$F$4&A106,'InOut Inv'!H:H) - SUMIF('Daily Sales'!F:I,$F$4&A106,'Daily Sales'!I:I) -> 1 | G106: =F106+ SUMIF('InOut Inv'!G:I,$F$4&B106,'InOut Inv'!I:I) - SUMIF('Daily Sales'!G:J,$F$4&B106,'Daily Sales'!J:J) -> 1
A107: PL4015 | B107: PERLENGKAPAN | C107: PERLENGKAPAN LAIN | D107: =VLOOKUP(A107,Master!D:G,4,0) -> #N/A | E107: 4 | F107: =E107+ SUMIF('InOut Inv'!F:H,$F$4&A107,'InOut Inv'!H:H) - SUMIF('Daily Sales'!F:I,$F$4&A107,'Daily Sales'!I:I) -> 4 | G107: =F107+ SUMIF('InOut Inv'!G:I,$F$4&B107,'InOut Inv'!I:I) - SUMIF('Daily Sales'!G:J,$F$4&B107,'Daily Sales'!J:J) -> 4
A108: PL4016 | B108: PERLENGKAPAN | C108: PERLENGKAPAN LAIN | D108: =VLOOKUP(A108,Master!D:G,4,0) -> #N/A | E108: 20 | F108: =E108+ SUMIF('InOut Inv'!F:H,$F$4&A108,'InOut Inv'!H:H) - SUMIF('Daily Sales'!F:I,$F$4&A108,'Daily Sales'!I:I) -> 20 | G108: =F108+ SUMIF('InOut Inv'!G:I,$F$4&B108,'InOut Inv'!I:I) - SUMIF('Daily Sales'!G:J,$F$4&B108,'Daily Sales'!J:J) -> 20
A109: PL4017 | B109: PERLENGKAPAN | C109: PERLENGKAPAN LAIN | D109: =VLOOKUP(A109,Master!D:G,4,0) -> #N/A | E109: 5 | F109: =E109+ SUMIF('InOut Inv'!F:H,$F$4&A109,'InOut Inv'!H:H) - SUMIF('Daily Sales'!F:I,$F$4&A109,'Daily Sales'!I:I) -> 5 | G109: =F109+ SUMIF('InOut Inv'!G:I,$F$4&B109,'InOut Inv'!I:I) - SUMIF('Daily Sales'!G:J,$F$4&B109,'Daily Sales'!J:J) -> 5
A110: PL4018 | B110: PERLENGKAPAN | C110: PERLENGKAPAN LAIN | D110: =VLOOKUP(A110,Master!D:G,4,0) -> #N/A | E110: 449 | F110: =E110+ SUMIF('InOut Inv'!F:H,$F$4&A110,'InOut Inv'!H:H) - SUMIF('Daily Sales'!F:I,$F$4&A110,'Daily Sales'!I:I) -> 449 | G110: =F110+ SUMIF('InOut Inv'!G:I,$F$4&B110,'InOut Inv'!I:I) - SUMIF('Daily Sales'!G:J,$F$4&B110,'Daily Sales'!J:J) -> 449
A111: PL4019 | B111: PERLENGKAPAN | C111: PERLENGKAPAN LAIN | D111: =VLOOKUP(A111,Master!D:G,4,0) -> #N/A | E111: 0 | F111: =E111+ SUMIF('InOut Inv'!F:H,$F$4&A111,'InOut Inv'!H:H) - SUMIF('Daily Sales'!F:I,$F$4&A111,'Daily Sales'!I:I) -> 0 | G111: =F111+ SUMIF('InOut Inv'!G:I,$F$4&B111,'InOut Inv'!I:I) - SUMIF('Daily Sales'!G:J,$F$4&B111,'Daily Sales'!J:J) -> 0
... A245: PK1050 | B245: PUPUK | C245: PUPUK | D245: =VLOOKUP(A245,Master!D:G,4,0) -> #N/A | E245: 1 | F245: =E245+ SUMIF('InOut Inv'!F:H,$F$4&A245,'InOut Inv'!H:H) - SUMIF('Daily Sales'!F:I,$F$4&A245,'Daily Sales'!I:I) -> 1 | G245: =F245+ SUMIF('InOut Inv'!G:I,$F$4&B245,'InOut Inv'!I:I) - SUMIF('Daily Sales'!G:J,$F$4&B245,'Daily Sales'!J:J) -> 1
A246: OK1001 | B246: LAIN LAIN | C246: LAIN LAIN | D246: =VLOOKUP(A246,Master!D:G,4,0) -> ETHREL 100ML | F246: =E246+ SUMIF('InOut Inv'!F:H,$F$4&A246,'InOut Inv'!H:H) - SUMIF('Daily Sales'!F:I,$F$4&A246,'Daily Sales'!I:I) -> 0 | G246: =F246+ SUMIF('InOut Inv'!G:I,$F$4&B246,'InOut Inv'!I:I) - SUMIF('Daily Sales'!G:J,$F$4&B246,'Daily Sales'!J:J) -> 0
A247: OK1002 | B247: LAIN LAIN | C247: LAIN LAIN | D247: =VLOOKUP(A247,Master!D:G,4,0) -> KARANG | F247: =E247+ SUMIF('InOut Inv'!F:H,$F$4&A247,'InOut Inv'!H:H) - SUMIF('Daily Sales'!F:I,$F$4&A247,'Daily Sales'!I:I) -> 0 | G247: =F247+ SUMIF('InOut Inv'!G:I,$F$4&B247,'InOut Inv'!I:I) - SUMIF('Daily Sales'!G:J,$F$4&B247,'Daily Sales'!J:J) -> 0
E248: =SUM(E5:E247) -> 76556
F256: 4 | G256: 4

Sheet InOut Inv
A2: INVENTORY IN - OUT OCTOBER 2024
A4: Date | B4: Time | C4: INV. NO | D4: Vendor | E4: Code | F4: z | G4: Item Descriptions | H4: Qty | I4: Price | J4: Discount | K4: Total | L4: Payment | M4: Type
A5: 01/10/24 | B5: 09:00:00 | F5: =A5&E5 -> 01/10/24 | G5: =_xludf.IFNA(VLOOKUP(E5,Master!D:J,4,0),"") -> #NAME? | I5: 0 | J5: 0 | K5: =I5*H5-J5 -> 0 | L5: C | M5: INCOMING
A6: 03/10/24 | B6: 08:45:00 | C6: 14107 | D6: TRIA GARDEN | E6: PK1045 | F6: =A6&E6 -> 03/10/24PK1045 | G6: =_xludf.IFNA(VLOOKUP(E6,Master!D:J,4,0),"") -> #NAME? | H6: 1 | I6: 30000 | J6: 0 | K6: =I6*H6-J6 -> 30000 | L6: C | M6: INCOMING
A7: 03/10/24 | B7: 08:45:00 | C7: 14574 | D7: TRIA GARDEN | E7: PK1011 | F7: =A7&E7 -> 03/10/24PK1011 | G7: =_xludf.IFNA(VLOOKUP(E7,Master!D:J,4,0),"") -> #NAME? | H7: 3 | I7: 74000 | J7: 0 | K7: =I7*H7-J7 -> 222000 | L7: C | M7: INCOMING
A8: 04/10/24 | B8: 08:29:00 | C8: 14687 | D8: TRIA GARDEN | E8: PS3009 | F8: =A8&E8 -> 04/10/24PS3009 | G8: =_xludf.IFNA(VLOOKUP(E8,Master!D:J,4,0),"") -> #NAME? | H8: 1 | I8: 68000 | J8: 0 | K8: =I8*H8-J8 -> 68000 | L8: C | M8: INCOMING
A9: 04/10/24 | B9: 08:29:00 | C9: 14687 | D9: TRIA GARDEN | E9: PL3015 | F9: =A9&E9 -> 04/10/24PL3015 | G9: =_xludf.IFNA(VLOOKUP(E9,Master!D:J,4,0),"") -> #NAME? | H9: 1 | I9: 85000 | J9: 0 | K9: =I9*H9-J9 -> 85000 | L9: C | M9: INCOMING
A10: 04/10/24 | B10: 08:29:00 | C10: 14687 | D10: TRIA GARDEN | E10: PL3017 | F10: =A10&E10 -> 04/10/24PL3017 | G10: =_xludf.IFNA(VLOOKUP(E10,Master!D:J,4,0),"") -> #NAME? | H10: 1 | I10: 85000 | J10: 0 | K10: =I10*H10-J10 -> 85000 | L10: C | M10: INCOMING
A11: 04/10/24 | B11: 08:29:00 | C11: 14687 | D11: TRIA GARDEN | E11: PL3021 | F11: =A11&E11 -> 04/10/24PL3021 | G11: =_xludf.IFNA(VLOOKUP(E11,Master!D:J,4,0),"") -> #NAME? | H11: 1 | I11: 85000 | J11: 0 | K11: =I11*H11-J11 -> 85000 | L11: C | M11: INCOMING
A12: 04/10/24 | B12: 08:29:00 | C12: 14687 | D12: TRIA GARDEN | E12: PL3023 | F12: =A12&E12 -> 04/10/24PL3023 | G12: =_xludf.IFNA(VLOOKUP(E12,Master!D:J,4,0),"") -> #NAME? | H12: 2 | I12: 85000 | J12: 0 | K12: =I12*H12-J12 -> 170000 | L12: C | M12: INCOMING
A13: 04/10/24 | B13: 08:29:00 | C13: 14687 | D13: TRIA GARDEN | E13: PS3011 | F13: =A13&E13 -> 04/10/24PS3011 | G13: =_xludf.IFNA(VLOOKUP(E13,Master!D:J,4,0),"") -> #NAME? | H13: 1 | I13: 105000 | J13: 0 | K13: =I13*H13-J13 -> 105000 | L13: C | M13: INCOMING
A14: 04/10/24 | B14: 08:29:00 | C14: 17193 | D14: TRIA GARDEN | E14: PL4022 | F14: =A14&E14 -> 04/10/24PL4022 | G14: =_xludf.IFNA(VLOOKUP(E14,Master!D:J,4,0),"") -> #NAME? | H14: 2 | I14: 29000 | J14: 0 | K14: =I14*H14-J14 -> 58000 | L14: C | M14: INCOMING
A15: 04/10/24 | B15: 08:29:00 | C15: 17193 | D15: TRIA GARDEN | E15: PL4023 | F15: =A15&E15 -> 04/10/24PL4023 | G15: =_xludf.IFNA(VLOOKUP(E15,Master!D:J,4,0),"") -> #NAME? | H15: 2 | I15: 33000 | J15: 0 | K15: =I15*H15-J15 -> 66000 | L15: C | M15: INCOMING
A16: 04/10/24 | B16: 08:29:00 | C16: 17193 | D16: TRIA GARDEN | E16: PK1028 | F16: =A16&E16 -> 04/10/24PK1028 | G16: =_xludf.IFNA(VLOOKUP(E16,Master!D:J,4,0),"") -> #NAME? | H16: 7 | I16: 19000 | J16: 0 | K16: =I16*H16-J16 -> 133000 | L16: C | M16: INCOMING
A17: 04/10/24 | B17: 08:29:00 | C17: 17193 | D17: TRIA GARDEN | E17: PK1014 | F17: =A17&E17 -> 04/10/24PK1014 | G17: =_xludf.IFNA(VLOOKUP(E17,Master!D:J,4,0),"") -> #NAME? | H17: 3 | I17: 12000 | J17: 0 | K17: =I17*H17-J17 -> 36000 | L17: C | M17: INCOMING
... A19: 04/10/24 | B19: 08:29:00 | C19: 17193 | D19: TRIA GARDEN | E19: PK1013 | F19: =A19&E19 -> 04/10/24PK1013 | G19: =_xludf.IFNA(VLOOKUP(E19,Master!D:J,4,0),"") -> #NAME? | H19: 1 | I19: 24000 | J19: 0 | K19: =I19*H19-J19 -> 24000 | L19: C | M19: INCOMING
A20: 04/10/24 | B20: 08:29:00 | C20: 17193 | D20: TRIA GARDEN | E20: PL6010 | F20: =A20&E20 -> 04/10/24PL6010 | G20: =_xludf.IFNA(VLOOKUP(E20,Master!D:J,4,0),"") -> #NAME? | H20: 24 | I20: =27000/12 -> 2250 | J20: 0 | K20: =I20*H20-J20 -> 54000 | L20: C | M20: INCOMING
A21: 04/10/24 | B21: 08:29:00 | C21: 17193 | D21: TRIA GARDEN | E21: PK1038 | F21: =A21&E21 -> 04/10/24PK1038 | G21: =_xludf.IFNA(VLOOKUP(E21,Master!D:J,4,0),"") -> #NAME? | H21: 4 | I21: 6000 | J21: 0 | K21: =I21*H21-J21 -> 24000 | L21: C | M21: INCOMING
A22: 04/10/24 | B22: 08:29:00 | C22: 17193 | D22: TRIA GARDEN | E22: MT1004 | F22: =A22&E22 -> 04/10/24MT1004 | G22: =_xludf.IFNA(VLOOKUP(E22,Master!D:J,4,0),"") -> #NAME? | H22: 5 | I22: 18000 | J22: 0 | K22: =I22*H22-J22 -> 90000 | L22: C | M22: INCOMING
A23: 07/10/24 | B23: 08:34:00 | C23: 14734 | D23: TRIA GARDEN | E23: PS3010 | F23: =A23&E23 -> 07/10/24PS3010 | G23: =_xludf.IFNA(VLOOKUP(E23,Master!D:J,4,0),"") -> #NAME? | H23: 1 | I23: 20000 | J23: 0 | K23: =I23*H23-J23 -> 20000 | L23: C | M23: INCOMING
A24: 07/10/24 | B24: 08:34:00 | C24: 14734 | D24: TRIA GARDEN | E24: PK1023 | F24: =A24&E24 -> 07/10/24PK1023 | G24: =_xludf.IFNA(VLOOKUP(E24,Master!D:J,4,0),"") -> #NAME? | H24: 2 | I24: 25000 | J24: 0 | K24: =I24*H24-J24 -> 50000 | L24: C | M24: INCOMING
A25: 07/10/24 | B25: 08:37:00 | C25: 17433 | D25: TRIA GARDEN | E25: MT1014 | F25: =A25&E25 -> 07/10/24MT1014 | G25: =_xludf.IFNA(VLOOKUP(E25,Master!D:J,4,0),"") -> #NAME? | H25: 10 | I25: 4000 | J25: 0 | K25: =I25*H25-J25 -> 40000 | L25: C | M25: INCOMING
A26: 07/10/24 | B26: 08:34:00 | C26: 17431 | D26: TRIA GARDEN | E26: PK1012 | F26: =A26&E26 -> 07/10/24PK1012 | G26: =_xludf.IFNA(VLOOKUP(E26,Master!D:J,4,0),"") -> #NAME? | H26: 3 | I26: 25000 | J26: 0 | K26: =I26*H26-J26 -> 75000 | L26: C | M26: INCOMING
A27: 07/10/24 | B27: 08:34:00 | C27: 17431 | D27: TRIA GARDEN | E27: PK1051 | F27: =A27&E27 -> 07/10/24PK1051 | G27: =_xludf.IFNA(VLOOKUP(E27,Master!D:J,4,0),"") -> #NAME? | H27: 1 | I27: 45000 | J27: 0 | K27: =I27*H27-J27 -> 45000 | L27: C | M27: INCOMING
A28: 07/10/24 | B28: 08:34:00 | C28: 17431 | D28: TRIA GARDEN | E28: PK1052 | F28: =A28&E28 -> 07/10/24PK1052 | G28: =_xludf.IFNA(VLOOKUP(E28,Master!D:J,4,0),"") -> #NAME? | H28: 1 | I28: 60000 | J28: 0 | K28: =I28*H28-J28 -> 60000 | L28: C | M28: INCOMING
A29: 07/10/24 | B29: 08:34:00 | C29: 17431 | D29: TRIA GARDEN | E29: PK1038 | F29: =A29&E29 -> 07/10/24PK1038 | G29: =_xludf.IFNA(VLOOKUP(E29,Master!D:J,4,0),"") -> #NAME? | H29: 2 | I29: 6000 | J29: 0 | K29: =I29*H29-J29 -> 12000 | L29: C | M29: INCOMING
A30: 07/10/24 | B30: 08:34:00 | C30: 17431 | D30: TRIA GARDEN | E30: PL4023 | F30: =A30&E30 -> 07/10/24PL4023 | G30: =_xludf.IFNA(VLOOKUP(E30,Master!D:J,4,0),"") -> #NAME? | H30: 1 | I30: 33000 | J30: 0 | K30: =I30*H30-J30 -> 33000 | L30: C | M30: INCOMING
A31: 07/10/24 | B31: 08:34:00 | C31: 17431 | D31: TRIA GARDEN | E31: PL6028 | F31: =A31&E31 -> 07/10/24PL6028 | G31: =_xludf.IFNA(VLOOKUP(E31,Master!D:J,4,0),"") -> #NAME? | H31: 12 | I31: =30000/12 -> 2500 | J31: 0 | K31: =I31*H31-J31 -> 30000 | L31: C | M31: INCOMING
A32: 07/10/24 | B32: 08:34:00 | C32: 17431 | D32: TRIA GARDEN | E32: PL6029 | F32: =A32&E32 -> 07/10/24PL6029 | G32: =_xludf.IFNA(VLOOKUP(E32,Master!D:J,4,0),"") -> #NAME? | H32: 12 | I32: =42000/12 -> 3500 | J32: 0 | K32: =I32*H32-J32 -> 42000 | L32: C | M32: INCOMING
A33: 07/10/24 | B33: 08:34:00 | C33: 17431 | D33: TRIA GARDEN | E33: PL6011 | F33: =A33&E33 -> 07/10/24PL6011 | G33: =_xludf.IFNA(VLOOKUP(E33,Master!D:J,4,0),"") -> #NAME? | H33: 12 | I33: =45000/12 -> 3750 | J33: 0 | K33: =I33*H33-J33 -> 45000 | L33: C | M33: INCOMING
A34: 07/10/24 | F34: =A34&E34 -> 07/10/24 | G34: =_xludf.IFNA(VLOOKUP(E34,Master!D:J,4,0),"") -> #NAME? | H34: 0 | I34: 0 | J34: 0 | K34: =I34*H34-J34 -> 0 | L34: C | M34: INCOMING
A35: 07/10/24 | F35: =A35&E35 -> 07/10/24 | G35: =_xludf.IFNA(VLOOKUP(E35,Master!D:J,4,0),"") -> #NAME? | H35: 0 | I35: 0 | J35: 0 | K35: =I35*H35-J35 -> 0 | L35: C | M35: INCOMING
A36: 08/10/24 | B36: 08:35:00 | C36: 14757 | D36: TRIA GARDEN | E36: PS3012 | F36: =A36&E36 -> 08/10/24PS3012 | G36: =_xludf.IFNA(VLOOKUP(E36,Master!D:J,4,0),"") -> #NAME? | H36: 1 | I36: 40000 | J36: 0 | K36: =I36*H36-J36 -> 40000 | L36: C | M36: INCOMING
A37: 08/10/24 | B37: 08:35:00 | C37: 14757 | D37: TRIA GARDEN | E37: PS3009 | F37: =A37&E37 -> 08/10/24PS3009 | G37: =_xludf.IFNA(VLOOKUP(E37,Master!D:J,4,0),"") -> #NAME? | H37: 2 | I37: 68000 | J37: 0 | K37: =I37*H37-J37 -> 136000 | L37: C | M37: INCOMING
A38: 08/10/24 | B38: 08:35:00 | C38: 17518 | D38: TRIA GARDEN | E38: PK1014 | F38: =A38&E38 -> 08/10/24PK1014 | G38: =_xludf.IFNA(VLOOKUP(E38,Master!D:J,4,0),"") -> #NAME? | H38: 5 | I38: 12000 | J38: 0 | K38: =I38*H38-J38 -> 60000 | L38: C | M38: INCOMING
A39: 08/10/24 | B39: 08:35:00 | C39: 17518 | D39: TRIA GARDEN | E39: PS1001 | F39: =A39&E39 -> 08/10/24PS1001 | G39: =_xludf.IFNA(VLOOKUP(E39,Master!D:J,4,0),"") -> #NAME? | H39: 1 | I39: 43000 | J39: 0 | K39: =I39*H39-J39 -> 43000 | L39: C | M39: INCOMING
A40: 08/10/24 | B40: 08:35:00 | C40: 17518 | D40: TRIA GARDEN | E40: PK1011 | F40: =A40&E40 -> 08/10/24PK1011 | G40: =_xludf.IFNA(VLOOKUP(E40,Master!D:J,4,0),"") -> #NAME? | H40: 2 | I40: 78000 | J40: 0 | K40: =I40*H40-J40 -> 156000 | L40: C | M40: INCOMING
A41: 08/10/24 | B41: 08:35:00 | C41: 17518 | D41: TRIA GARDEN | E41: PL6007 | F41: =A41&E41 -> 08/10/24PL6007 | G41: =_xludf.IFNA(VLOOKUP(E41,Master!D:J,4,0),"") -> #NAME? | H41: 12 | I41: =96000/12 -> 8000 | J41: 0 | K41: =I41*H41-J41 -> 96000 | L41: C | M41: INCOMING
A42: 08/10/24 | B42: 08:35:00 | C42: 17518 | D42: TRIA GARDEN | E42: PL6022 | F42: =A42&E42 -> 08/10/24PL6022 | G42: =_xludf.IFNA(VLOOKUP(E42,Master!D:J,4,0),"") -> #NAME? | H42: 3 | I42: 30500 | J42: 0 | K42: =I42*H42-J42 -> 91500 | L42: C | M42: INCOMING
A43: 08/10/24 | B43: 08:35:00 | C43: 17518 | D43: TRIA GARDEN | E43: PL6031 | F43: =A43&E43 -> 08/10/24PL6031 | G43: =_xludf.IFNA(VLOOKUP(E43,Master!D:J,4,0),"") -> #NAME? | H43: 2 | I43: 58000 | J43: 0 | K43: =I43*H43-J43 -> 116000 | L43: C | M43: INCOMING
A44: 08/10/24 | B44: 08:39:00 | C44: 17519 | D44: TRIA GARDEN | E44: PK1028 | F44: =A44&E44 -> 08/10/24PK1028 | G44: =_xludf.IFNA(VLOOKUP(E44,Master!D:J,4,0),"") -> #NAME? | H44: 5 | I44: 19000 | J44: 0 | K44: =I44*H44-J44 -> 95000 | L44: C | M44: INCOMING
A45: 08/10/24 | F45: =A45&E45 -> 08/10/24 | G45: =_xludf.IFNA(VLOOKUP(E45,Master!D:J,4,0),"") -> #NAME? | I45: 0 | J45: 0 | K45: =I45*H45-J45 -> 0 | L45: C | M45: INCOMING
A46: 08/10/24 | F46: =A46&E46 -> 08/10/24 | G46: =_xludf.IFNA(VLOOKUP(E46,Master!D:J,4,0),"") -> #NAME? | I46: 0 | J46: 0 | K46: =I46*H46-J46 -> 0 | L46: C | M46: INCOMING
A47: 08/10/24 | F47: =A47&E47 -> 08/10/24 | G47: =_xludf.IFNA(VLOOKUP(E47,Master!D:J,4,0),"") -> #NAME? | I47: 0 | J47: 0 | K47: =I47*H47-J47 -> 0 | L47: C | M47: INCOMING
A48: 09/10/24 | B48: 08:29:00 | C48: 17631 | D48: TRIA GARDEN | E48: PL6009 | F48: =A48&E48 -> 09/10/24PL6009 | G48: =_xludf.IFNA(VLOOKUP(E48,Master!D:J,4,0),"") -> #NAME? | H48: 24 | I48: =22500/12 -> 1875 | J48: 0 | K48: =I48*H48-J48 -> 45000 | L48: C | M48: INCOMING
A49: 09/10/24 | B49: 08:29:00 | C49: 17631 | D49: TRIA GARDEN | E49: PL6010 | F49: =A49&E49 -> 09/10/24PL6010 | G49: =_xludf.IFNA(VLOOKUP(E49,Master!D:J,4,0),"") -> #NAME? | H49: 24 | I49: =27000/12 -> 2250 | J49: 0 | K49: =I49*H49-J49 -> 54000 | L49: C | M49: INCOMING
A50: 09/10/24 | B50: 08:29:00 | C50: 17631 | D50: TRIA GARDEN | E50: PL6013 | F50: =A50&E50 -> 09/10/24PL6013 | G50: =_xludf.IFNA(VLOOKUP(E50,Master!D:J,4,0),"") -> #NAME? | H50: 12 | I50: =72000/12 -> 6000 | J50: 0 | K50: =I50*H50-J50 -> 72000 | L50: C | M50: INCOMING
A51: 09/10/24 | B51: 08:29:00 | C51: 17631 | D51: TRIA GARDEN | E51: PL6014 | F51: =A51&E51 -> 09/10/24PL6014 | G51: =_xludf.IFNA(VLOOKUP(E51,Master!D:J,4,0),"") -> #NAME? | H51: 12 | I51: =123000/12 -> 10250 | J51: 0 | K51: =I51*H51-J51 -> 123000 | L51: C | M51: INCOMING
A52: 11/10/24 | B52: 08:30:00 | C52: 17810 | D52: TRIA GARDEN | E52: PL6022 | F52: =A52&E52 -> 11/10/24PL6022 | G52: =_xludf.IFNA(VLOOKUP(E52,Master!D:J,4,0),"") -> #NAME? | H52: 3 | I52: 30500 | J52: 0 | K52: =I52*H52-J52 -> 91500 | L52: C | M52: INCOMING
A53: 11/10/24 | B53: 08:30:00 | C53: 17810 | D53: TRIA GARDEN | E53: PL6016 | F53: =A53&E53 -> 11/10/24PL6016 | G53: =_xludf.IFNA(VLOOKUP(E53,Master!D:J,4,0),"") -> #NAME? | H53: 6 | I53: 20750 | J53: 0 | K53: =I53*H53-J53 -> 124500 | L53: C | M53: INCOMING
A54: 11/10/24 | B54: 08:30:00 | C54: 17810 | D54: TRIA GARDEN | E54: PL6030 | F54: =A54&E54 -> 11/10/24PL6030 | G54: =_xludf.IFNA(VLOOKUP(E54,Master!D:J,4,0),"") -> #NAME? | H54: 3 | I54: 19000 | J54: 0 | K54: =I54*H54-J54 -> 57000 | L54: C | M54: INCOMING
A55: 11/10/24 | B55: 08:30:00 | C55: 17810 | D55: TRIA GARDEN | E55: PS3003 | F55: =A55&E55 -> 11/10/24PS3003 | G55: =_xludf.IFNA(VLOOKUP(E55,Master!D:J,4,0),"") -> #NAME? | H55: 2 | I55: 40000 | J55: 0 | K55: =I55*H55-J55 -> 80000 | L55: C | M55: INCOMING
A56: 11/10/24 | B56: 08:30:00 | C56: 14810 | D56: TRIA GARDEN | E56: PS2004 | F56: =A56&E56 -> 11/10/24PS2004 | G56: =_xludf.IFNA(VLOOKUP(E56,Master!D:J,4,0),"") -> #NAME? | H56: 1 | I56: 33000 | J56: 0 | K56: =I56*H56-J56 -> 33000 | L56: C | M56: INCOMING
A57: 12/10/24 | B57: 15:18:00 | C57: 14846 | D57: TRIA GARDEN | E57: PL3017 | F57: =A57&E57 -> 12/10/24PL3017 | G57: =_xludf.IFNA(VLOOKUP(E57,Master!D:J,4,0),"") -> #NAME? | H57: 1 | I57: 85000 | J57: 0 | K57: =I57*H57-J57 -> 85000 | L57: C | M57: INCOMING
A58: 12/10/24 | B58: 15:18:00 | C58: 14846 | D58: TRIA GARDEN | E58: PL3027 | F58: =A58&E58 -> 12/10/24PL3027 | G58: =_xludf.IFNA(VLOOKUP(E58,Master!D:J,4,0),"") -> #NAME? | H58: 1 | I58: 85000 | J58: 0 | K58: =I58*H58-J58 -> 85000 | L58: C | M58: INCOMING
A59: 12/10/24 | B59: 15:18:00 | C59: 17988 | D59: TRIA GARDEN | E59: PK1028 | F59: =A59&E59 -> 12/10/24PK1028 | G59: =_xludf.IFNA(VLOOKUP(E59,Master!D:J,4,0),"") -> #NAME? | H59: 3 | I59: 19000 | J59: 0 | K59: =I59*H59-J59 -> 57000 | L59: C | M59: INCOMING
A60: 12/10/24 | B60: 15:18:00 | C60: 17988 | D60: TRIA GARDEN | E60: PL4033 | F60: =A60&E60 -> 12/10/24PL4033 | G60: =_xludf.IFNA(VLOOKUP(E60,Master!D:J,4,0),"") -> #NAME? | H60: 2 | I60: 12500 | J60: 0 | K60: =I60*H60-J60 -> 25000 | L60: C | M60: INCOMING
A61: 12/10/24 | B61: 15:18:00 | C61: 17988 | D61: TRIA GARDEN | E61: MT1014 | F61: =A61&E61 -> 12/10/24MT1014 | G61: =_xludf.IFNA(VLOOKUP(E61,Master!D:J,4,0),"") -> #NAME? | H61: 10 | I61: 4000 | J61: 0 | K61: =I61*H61-J61 -> 40000 | L61: C | M61: INCOMING
A62: 12/10/24 | B62: 12:18:00 | D62: ALBERT | E62: MT1030 | F62: =A62&E62 -> 12/10/24MT1030 | G62: =_xludf.IFNA(VLOOKUP(E62,Master!D:J,4,0),"") -> #NAME? | H62: 30 | I62: 6000 | J62: 0 | K62: =I62*H62-J62 -> 180000 | L62: C | M62: INCOMING
A63: 12/10/24 | B63: 12:18:00 | D63: ALBERT | E63: MT1030 | F63: =A63&E63 -> 12/10/24MT1030 | G63: =_xludf.IFNA(VLOOKUP(E63,Master!D:J,4,0),"") -> #NAME? | H63: 3 | I63: 6000 | J63: 18000 | K63: =I63*H63-J63 -> 0 | L63: C | M63: INCOMING | N63: BONUS
A64: 12/10/24 | B64: 12:18:00 | E64: MT1013 | F64: =A64&E64 -> 12/10/24MT1013 | G64: =_xludf.IFNA(VLOOKUP(E64,Master!D:J,4,0),"") -> #NAME? | H64: 1 | I64: 7000 | J64: 0 | K64: =I64*H64-J64 -> 7000 | L64: C | M64: TRANSFER | N64: BAWA DARI KOS
A65: 12/10/24 | B65: 12:18:00 | E65: MT1019 | F65: =A65&E65 -> 12/10/24MT1019 | G65: =_xludf.IFNA(VLOOKUP(E65,Master!D:J,4,0),"") -> #NAME? | H65: 8 | I65: 12000 | J65: 0 | K65: =I65*H65-J65 -> 96000 | L65: C | M65: REPACK
A66: 12/10/24 | F66: =A66&E66 -> 12/10/24 | G66: =_xludf.IFNA(VLOOKUP(E66,Master!D:J,4,0),"") -> #NAME? | I66: 0 | J66: 0 | K66: =I66*H66-J66 -> 0 | L66: C | M66: INCOMING
A67: 12/10/24 | F67: =A67&E67 -> 12/10/24 | G67: =_xludf.IFNA(VLOOKUP(E67,Master!D:J,4,0),"") -> #NAME? | I67: 0 | J67: 0 | K67: =I67*H67-J67 -> 0 | L67: C | M67: INCOMING
F179: =A179&E179 | G179: =_xludf.IFNA(VLOOKUP(E179,Master!D:J,4,0),"") -> #NAME?
F180: =A180&E180 | G180: =_xludf.IFNA(VLOOKUP(E180,Master!D:J,4,0),"") -> #NAME?

Sheet Incoming
A2: INVENTORY INC NOVEMBER 2025
A4: Date | B4: Time | C4: INV. NO | D4: Vendor | E4: Code | F4: z | G4: Item Descriptions | H4: Qty | I4: Price | J4: Discount | K4: Total | L4: Payment | M4: Notes
F5: =A5&E5 | G5: =_xludf.IFNA(VLOOKUP(E5,Master!D:J,4,0),"") -> #NAME? | I5: 0 | J5: 0 | K5: =I5*H5-J5 -> 0 | L5: C
A6: 31/10/25 | B6: 17:04:00 | C6: 005771/KSR/TGB/1025 | D6: TRIA GARDEN | H6: 1 | I6: 30000 | J6: 0 | K6: 340000 | L6: T | M6: Trf pakai uang BNI
A7: 02/11/25 | B7: 11:17:00 | C7: 028234/KSR/SCA/1125 | D7: SARANA CIPTA AGRO | H7: 3 | I7: 74000 | J7: 0 | K7: 443000 | L7: T | M7: Trf pakai uang BNI
A8: 03/11/25 | B8: 08:19:00 | C8: 005826/KSR/TGB/1125 | D8: TRIA GARDEN | H8: 1 | I8: 68000 | J8: 0 | K8: 425000 | L8: T | M8: Trf pakai uang BNI
F179: =A179&E179 | G179: =_xludf.IFNA(VLOOKUP(E179,Master!D:J,4,0),"") -> #NAME?
F180: =A180&E180 | G180: =_xludf.IFNA(VLOOKUP(E180,Master!D:J,4,0),"") -> #NAME?

Sheet PettyCash
A2: PETTY CASH OCTOBER 2024
A5: No | B5: Date | C5: Trx Number | D5: Descriptions | E5: In | F5: Out | G5: Balance
A6: 1 | B6: 01/10/24 | D6: Opening Balance | G6: 2840100
A7: 2 | B7: 01/10/24 | D7: Sales Summary 01/10/24 | E7: 713000 | G7: =G6+E7-F7 -> 3553100
B31: 22/10/24 | D31: Total cash | G31: 3060000
A46: 32
A47: 33
A48: 34
A49: 35
A50: 36
A51: 37
A52: 38
A53: 39
A54: 40
A55: 41
A56: 42
A57: 43
... A146: 132

Sheet Save Margin
A2: SAVE MARGIN
A4: No | B4: Date | C4: Descriptions | D4: In | E4: Out | F4: Balance
F5: 0
A6: 1 | B6: 01/11/25 | C6: Margin | D6: 1000000 | F6: =F5+D6-E6 -> 1000000
A7: 2 | B7: 01/11/25
A8: 3
A9: 4
A10: 5
A11: 6
A12: 7
A13: 8
A14: 9
A15: 10

Sheet Bank
A2: BANK SEPTEMBER 2024
A5: No | B5: Date | C5: Trx Number | D5: Descriptions | E5: In | F5: Out | G5: Balance
A6: 1 | B6: 01/09/24 | D6: Opening Balance | G6: 0
A7: 2 | B7: 01/09/24 | D7: Purchase Pinebark | F7: 425000 | G7: =(G6+E7)-F7 -> -425000
A8: 3 | B8: 03/09/24 | D8: Payment Cocopeat Instant | E8: 10000 | G8: =(G7+E8)-F8 -> -415000
A9: 4 | B9: 04/09/24 | D9: Payment Tanah Subur Instant | E9: 30000 | G9: =(G8+E9)-F9 -> -385000
A10: 5 | B10: 02/09/24 | G10: =(G9+E10)-F10 -> -385000
A11: 6 | G11: =(G10+E11)-F11 -> -385000
A12: 7 | G12: =(G11+E12)-F12 -> -385000
A13: 8 | G13: =(G12+E13)-F13 -> -385000
A14: 9 | G14: =(G13+E14)-F14 -> -385000
A15: 10 | G15: =(G14+E15)-F15 -> -385000
A16: 11 | G16: =(G15+E16)-F16 -> -385000
A17: 12 | G17: =(G16+E17)-F17 -> -385000
A18: 13 | G18: =(G17+E18)-F18 -> -385000

Sheet Order
A2: JANUARI 2026 | R2: Agustus | W2: September | AB2: Oktober
A4: Bali Green House - Panjer | R4: Bali Green House - Panjer | W4: Bali Green House - Panjer | AB4: Bali Green House - Panjer | AH4: Bali Green House - Panjer
A5: 13/01/2026 | R5: 45724 | W5: 14/09/2025 | AB5: 46001 | AH5: 27/12/2025
A6: No | B6: Item | C6: Qty | D6: Toko | E6: Gudang | R6: No | S6: Item | T6: Qty | W6: No | X6: Item | Y6: Qty | AB6: No | AC6: Item | AD6: Qty | AE6: Toko | AF6: Gudang | AH6: No | AI6: Item | AJ6: Qty | AK6: Toko | AL6: Gudang
A7: 1 | B7: Tanah Subur 10kg | C7: 150 | D7: 50 | E7: 100 | R7: 1 | S7: Tanah Subur 10kg | T7: 100 | W7: 1 | X7: Tanah Subur 10kg | Y7: 70 | AB7: 1 | AC7: Tanah Subur 10kg | AD7: 100 | AE7: 50 | AF7: 50 | AH7: 1 | AI7: Tanah Subur 10kg | AJ7: 100 | AK7: 40 | AL7: 60
A8: 2 | B8: Tanah Subur 25kg | C8: 30 | D8: 10 | E8: 20 | R8: 2 | S8: Tanah Subur 25kg | T8: 40 | W8: 2 | X8: Tanah Subur 25kg | Y8: 50 | AB8: 2 | AC8: Tanah Subur 25kg | AD8: 30 | AE8: 10 | AF8: 20 | AH8: 2 | AI8: Tanah Subur 25kg | AJ8: 20 | AK8: 20 | AL8: 0
A9: 3 | B9: Sekam Bakar 10kg | C9: 20 | D9: 10 | E9: 10 | R9: 3 | S9: Pasir Malang halus 10kg | T9: 10 | W9: 3 | X9: Pasir Malang halus 10kg | Y9: 10 | AB9: 3 | AC9: Pasir Malang halus 10kg | AD9: 20 | AE9: 10 | AF9: 10 | AH9: 3 | AI9: Sekam Bakar 10kg | AJ9: 20 | AK9: 10 | AL9: 10
A10: 4 | B10: Sekam Mentah 10kg | C10: 20 | D10: 10 | E10: 10 | R10: 4 | S10: Pasir Malang Halus 25kg | T10: 5 | W10: 4 | X10: Pasir Malang Halus 25kg | Y10: 5 | AB10: 4 | AC10: Pasir Malang Halus 25kg | AD10: 5 | AE10: 5 | AF10: 0 | AH10: 4 | AI10: Sekam Fermentasi 10kg | AJ10: 20 | AK10: 10 | AL10: 10
A11: 5 | B11: Sekam Mentah 25kg | C11: 10 | D11: 0 | E11: 10 | R11: 5 | S11: Sekam Bakar 25kg | T11: 10 | W11: 5 | X11: Sekam Bakar 25kg | Y11: 10 | AB11: 5 | AC11: Pakis Cacah | AD11: 10 | AE11: 10 | AF11: 0 | AH11: 5 | AI11: Pasir Malang Halus 10kg | AJ11: 10 | AK11: 10 | AL11: 0
A12: 6 | B12: Pasir Malang Halus 10kg | C12: 10 | D12: 10 | E12: 0 | R12: 6 | S12: Sekam Bakar 10kg | T12: 20 | W12: 6 | X12: Sekam Bakar 10kg | Y12: 20 | AB12: 6 | AC12: Sekam Bakar 10kg | AD12: 20 | AE12: 10 | AF12: 10 | AH12: 6 | AI12: Pasir Malang Kasar 10kg | AJ12: 10 | AK12: 10 | AL12: 0
A13: 7 | B13: Pasir Malang Kasar 10kg | C13: 10 | D13: 10 | E13: 0 | R13: 7 | S13: Sekam Fermentasi 10kg | T13: 10 | W13: 7 | X13: Sekam Fermentasi 10kg | Y13: 20 | AB13: 7 | AC13: Sekam Fermentasi 10kg | AD13: 20 | AE13: 10 | AF13: 10 | AH13: 7 | AI13: Pasir Malang Halus 25kg | AJ13: 5 | AK13: 5 | AL13: 0
A14: 8 | B14: Pasir Malang Halus 25kg | C14: 5 | D14: 5 | E14: 0 | AH14: 8 | AI14: Pupuk Kambing Butiran | AJ14: 20 | AK14: 10 | AL14: 10
A15: 9 | B15: Pupuk Kambing Halus 5kg | C15: 30 | D15: 10 | E15: 20 | AH15: 9 | AI15: Pakis Cacah | AJ15: 10 | AK15: 10 | AL15: 0
A16: 10 | B16: Cocopeat 10kg | C16: 10 | D16: 10 | E16: 0 | R16: 10 | S16: Pupuk Kambing Halus 5kg | T16: 20 | W16: 10 | X16: Pupuk Kambing Halus 5kg | Y16: 20 | AB16: 10 | AC16: Pupuk Kambing Halus 5kg | AD16: 30 | AE16: 10 | AF16: 20 | AJ16: =SUM(AJ7:AJ15) -> 215
C17: =SUM(C7:C16) -> 295 | R17: 11 | S17: Pupuk Kambing Butiran 10kg | T17: 10 | W17: 11 | X17: Sekam Bakar 50kg | Y17: 5 | AB17: 11 | AC17: Pasir Malang Kasar 10kg | AD17: 5 | AE17: 5 | AF17: 0
R18: 12 | S18: Tanah Murni 10kg | T18: 10 | W18: 12 | X18: Sekam Mentah 50kg | Y18: 5
R19: 13 | S19: Pakis Cacah | T19: 10 | Y19: =SUM(Y7:Y18) -> 215 | AD19: =SUM(AD7:AD18) -> 240
T20: =SUM(T5:T19) -> 245
R23: Bali Green House - Panjer | W23: Bali Green House - Panjer | AB23: Bali Green House - Lovina
R24: 16/08/2025 | W24: 27/09/2025 | AB24: 19/10/2025
R25: No | S25: Item | T25: Qty | W25: No | X25: Item | Y25: Qty | AB25: No | AC25: Item | AD25: Qty
R26: 1 | S26: Tanah Subur 10kg | T26: 100 | W26: 1 | X26: Tanah Subur 10kg | Y26: 150 | AB26: 1 | AC26: Pasir Malang Halus 25kg | AD26: 25
R27: 2 | S27: Tanah Subur 25kg | T27: 40 | W27: 2 | X27: Tanah Subur 25kg | Y27: 30 | AB27: 2 | AC27: Pasir Malang halus 10kg | AD27: 70
R28: 3 | S28: Pasir Malang halus 10kg | T28: 5 | W28: 3 | X28: Sekam Bakar 25kg | Y28: 20 | AB28: 3 | AC28: Cocopeat 10kg | AD28: 20
R29: 4 | S29: Pasir Malang Halus 25kg | T29: 5 | W29: 4 | X29: Sekam Mentah 10kg | Y29: 10 | AB29: 4 | AC29: Pupuk Kambing Halus 5kg | AD29: 20
R30: 5 | S30: Sekam Bakar 25kg | T30: 10 | W30: 5 | X30: Sekam Mentah 25kg | Y30: 10 | AB30: 5 | AC30: Sekam Bakar 10kg | AD30: 10
R31: 6 | S31: Sekam Bakar 10kg | T31: 20 | W31: 6 | X31: Pupuk Kambing Halus 5kg | Y31: 20 | AB31: 6 | AC31: Sekam Bakar 25kg | AD31: 10
R32: 7 | S32: Sekam Fermentasi 10kg | T32: 10 | W32: 7 | X32: Pakis Cacah | Y32: 10
R33: 8 | S33: Sekam Mentah 10kg | T33: 10 | Y33: =SUM(Y26:Y32) -> 250
R34: 9 | S34: Sekam Mentah 25kg | T34: 10
R35: 10 | S35: Pupuk Kambing Halus 5kg | T35: 20 | AD35: =SUM(AD26:AD31) -> 155
R36: 11 | S36: Cocopeat 10kg | T36: 10
R37: 12 | S37: Pasir Malang Kasar 10kg | T37: 5 | AB37: Bali Green House - Lovina
T38: =SUM(T24:T37) -> 245 | AB38: Tambahan - 21/10/2025
AB39: No | AC39: Item | AD39: Qty
AB40: 1 | AC40: Pasir Malang halus 10kg | AD40: 10
R41: Bali Green House - Panjer | AB41: 2 | AC41: Pasir Malang Kasar 10kg | AD41: 10
R42: 28/08/2025 | AB42: 3 | AC42: Pupuk Kambing Halus 5kg | AD42: 10
R43: No | S43: Item | T43: Qty | V43: Stok media: | AB43: 4 | AC43: Sekam Fermentasi 10kg | AD43: 10
R44: 1 | S44: Tanah Subur 10kg | T44: 100 | V44: - Tanah subur 10kg 2 | AB44: 5 | AC44: Tanah Subur 25kg | AD44: 10
R45: 2 | S45: Tanah Subur 25kg | T45: 30 | V45: - ⁠tanah subur 25kg 12 | AD45: =SUM(AD40:AD44) -> 50
R46: 3 | S46: Pasir Malang Halus 25kg | T46: 5 | V46: - ⁠tanah murni 10kg 16
R47: 4 | S47: Sekam Bakar 25kg | T47: 10 | V47: - ⁠pasir malang 10kg 10
R48: 5 | S48: Sekam Bakar 10kg | T48: 20 | V48: - ⁠pasir malang 25kg 2
R49: 6 | S49: Sekam Fermentasi 10kg | T49: 10 | V49: - ⁠pasir malang kasar 10kg 4
R50: 7 | S50: Sekam Mentah 10kg | T50: 10 | V50: - ⁠sekam mentah 10kg 2
P51: Qty | R51: 8 | S51: Sekam Mentah 25kg | T51: 10 | V51: - ⁠sekam mentah 25kg 5
P52: 60 | R52: 9 | S52: Pupuk Kambing Halus 5kg | T52: 20 | V52: - ⁠sekam bakar 10kg 4
P53: 30 | R53: 10 | S53: Cocopeat 50kg | T53: 2 | V53: - ⁠sekam bakar 25kg -
P54: 5 | R54: 11 | S54: Pasir Malang Kasar 10kg | T54: 10 | V54: - ⁠sekam fermentasi 10kg 6 | AB54: Bali Green House - Panjer
P55: 10 | T55: =SUM(T42:T54) -> 227 | V55: - ⁠pupuk kambing 6 | AB55: 25/10/2025
P56: 10 | V56: - ⁠Pupuk butiran 2 | AB56: No | AC56: Item | AD56: Qty | AE56: Toko | AF56: Gudang
P57: 15 | AB57: 1 | AC57: Tanah Subur 10kg | AD57: 100 | AE57: 50 | AF57: 50
P58: 10 | AB58: 2 | AC58: Tanah Subur 25kg | AD58: 50 | AE58: 10 | AF58: 40
R59: Bali Green House - Panjer | AB59: 3 | AC59: Sekam Bakar 10kg | AD59: 10 | AE59: 10 | AF59: 0
R60: 45756 | AB60: 4 | AC60: Sekam Fermentasi 10kg | AD60: 10 | AE60: 10 | AF60: 0
R61: No | S61: Item | T61: Qty | AB61: 5 | AC61: Sekam Mentah 10kg | AD61: 10 | AE61: 0 | AF61: 10
R62: 1 | S62: Tanah Subur 10kg | T62: 100 | AB62: 6 | AC62: Sekam Mentah 25kg | AD62: 10 | AE62: 0 | AF62: 10
R63: 2 | S63: Tanah Subur 25kg | T63: 50 | AB63: 7 | AC63: Pasir Malang Kasar 10kg | AD63: 10 | AE63: 10 | AF63: 0
P64: Qty | R64: 3 | S64: Sekam Fermentasi 10kg | T64: 20 | AC64: Pasir Malang Halus 25kg | AD64: 5 | AE64: 5 | AF64: 0
P65: 100 | R65: 4 | S65: Mos kampil besar | T65: 5
P66: 40
P67: 5
P68: 10
P69: 5 | AD69: =SUM(AD57:AD68) -> 205
P70: =SUM(P65:P69) -> 160
AB72: Bali Green House - Panjer
T73: =SUM(T60:T72) -> 175 | AB73: 24/11/2025
AB74: No | AC74: Item | AD74: Qty | AE74: Toko | AF74: Gudang
AB75: 1 | AC75: Tanah Subur 10kg | AD75: 150 | AE75: 50 | AF75: 100
R76: Bali Green House - Lovina | AB76: 2 | AC76: Tanah Subur 25kg | AD76: 20 | AE76: 10 | AF76: 10
R77: 45847 | AB77: 3 | AC77: Sekam Bakar 10kg | AD77: 10 | AE77: 10 | AF77: 0
P78: Qty | R78: No | S78: Item | T78: Qty | AB78: 4 | AC78: Cocopeat 10kg | AD78: 10 | AE78: 10 | AF78: 0
P79: 100 | R79: 1 | S79: Tanah Subur 10kg | T79: 60 | AB79: 5 | AC79: Sekam Mentah 10kg | AD79: 10 | AE79: 0 | AF79: 10
P80: 40 | R80: 2 | S80: Tanah Subur 25kg | T80: 10 | AB80: 6 | AC80: Pasir Malang Halus 10kg | AD80: 10 | AE80: 10 | AF80: 0
P81: 10 | R81: 3 | S81: Pasir Malang Halus 25kg | T81: 10 | AB81: 7 | AC81: Pasir Malang Kasar 10kg | AD81: 10 | AE81: 10 | AF81: 0
P82: 5 | R82: 4 | S82: Pasir Malang Kasar 10kg | T82: 20 | AB82: 8 | AC82: Pasir Malang Halus 25kg | AD82: 5 | AE82: 5 | AF82: 0
P83: 5 | R83: 5 | S83: Sekam Bakar 25kg | T83: 10 | AD83: =SUM(AD75:AD82) -> 225
P84: 10 | R84: 6 | S84: Sekam Bakar 10kg | T84: 20
P85: 10 | R85: 7 | S85: Sekam Fermentasi 10kg | T85: 20
P86: 10 | R86: 8 | S86: Sekam Mentah 10kg | T86: 10
P87: 20 | R87: 9 | S87: Sekam Mentah 25kg | T87: 10 | AB87: Bali Green House - Panjer
R88: 10 | S88: Pupuk Kambing Halus 5kg | T88: 10 | AB88: 45912
P89: =SUM(P79:P88) -> 210 | R89: 11 | S89: Pupuk Kambing Butiran | T89: 10 | AB89: No | AC89: Item | AD89: Qty | AE89: Toko | AF89: Gudang
R90: 12 | S90: Cocopeat 10kg | T90: 10 | AB90: 1 | AC90: Tanah Subur 10kg | AD90: 150 | AE90: 50 | AF90: 100
T91: =SUM(T77:T90) -> 200 | AB91: 2 | AC91: Tanah Subur 25kg | AD91: 40 | AE91: 20 | AF91: 20
AB92: 3 | AC92: Sekam Bakar 10kg | AD92: 10 | AE92: 10 | AF92: 0
AB93: 4 | AC93: Cocopeat 10kg | AD93: 10 | AE93: 10 | AF93: 0
P94: Qty | AB94: 5 | AC94: Sekam Bakar 50kg | AD94: 5 | AE94: 0 | AF94: 5
P95: 20 | AB95: 6 | AC95: Sekam Fermentasi 10kg | AD95: 10 | AE95: 10 | AF95: 0
P96: 10 | AB96: 7 | AC96: Pupuk Kambing Halus 5kg | AD96: 50 | AE96: 10 | AF96: 40
P97: 35 | AB97: 8 | AC97: Pasir Malang Halus 25kg | AD97: 5 | AE97: 5 | AF97: 0
P98: 40 | AD98: =SUM(AD90:AD97) -> 280
P99: 10
P100: 10
P101: 10
P102: 20
P103: =SUM(P95:P102) -> 155 | AB103: Bali Green House - Panjer
AB104: 27/12/2025
AB105: No | AC105: Item | AD105: Qty | AE105: Toko | AF105: Gudang
...
